Workbook
Name Slicer_Category: #N/A
Name Slicer_DATE_BIN_MONTHS: #N/A
Name Slicer_Region: #N/A

Sheet Q1&Q2
A1: Order_ID | B1: Customer_ID | C1: Product_ID | D1: Order_Date | E1: Delivery_Date | F1: Customer_Name | G1: Gender | H1: DOB | I1: City | J1: Region | K1: Category | L1: Product_Name | M1: Quantity | N1: Unit_Price | O1: Discount_% | P1: Sales | Q1: Rating | R1: Payment_Mode | S1: Salesperson | T1: Email | U1: Phone | V1: Order_Status | W1: Customer_classification | X1: proper customer name | Y1: Customer_code | Z1: Standardized email-id
A2: ORD10001 | B2: C008 | C2: P202 | D2: 18/09/2025 | E2: 22/09/2025 | F2: Kavya Nair | G2: Female | H2: 01/08/1976 | I2: Hyderabad | J2: South | K2: Home Appliances | L2: Iron | M2: 4 | N2: 2200 | O2: 10 | P2: 7920 | Q2: 4 | R2: Cash | S2: Ritika | T2: KAvya.nair@company.com | U2: 9431429797 | V2: Completed | W2: {=_xlfn.IFS( OR(Q2<=2, V2="Cancelled"), "BLACKLISTED", AND(P2>=100000, Q2>=4, O2<=10, V2="Completed"), "PLATINUM", AND( P2<=99999, P2>=50000, Q2>=3, V2= "Completed"), "GOLD", AND( P2<50000, V2="Completed"), "SILVER", TRUE, "UNCLASSIFIED")} -> #NAME? | X2: =PROPER(TRIM(F2)) -> Kavya Nair | Y2: =LEFT(X2,3)&RIGHT(A2,4)&LEFT(I2,2) -> Kav0001Hy | Z2: =IF(IFERROR(FIND("@", T2), 0), TRIM(LOWER(T2)), "Invalid Email" ) -> kavya.nair@company.com
A3: ORD10002 | B3: C008 | C3: P104 | D3: 27/04/2025 | E3: 04/05/2025 | F3: Kavya Nair | G3: Female | H3: 16/10/2000 | I3: Delhi | J3: North | K3: Electronics | L3: Monitor | M3: 17 | N3: 12000 | O3: 10 | P3: 183600 | Q3: 1 | R3: NetBanking | S3: Rahul | T3: kavya.nair@company.com | U3: 9129865339 | V3: Completed | W3: {=_xlfn.IFS( OR(Q3<=2, V3="Cancelled"), "BLACKLISTED", AND(P3>=100000, Q3>=4, O3<=10, V3="Completed"), "PLATINUM", AND( P3<=99999, P3>=50000, Q3>=3, V3= "Completed"), "GOLD", AND( P3<50000, V3="Completed"), "SILVER", TRUE, "UNCLASSIFIED")} -> #NAME? | X3: =PROPER(TRIM(F3)) -> Kavya Nair | Y3: =LEFT(X3,3)&RIGHT(A3,4)&LEFT(I3,2) -> Kav0002De | Z3: =IF(IFERROR(FIND("@", T3), 0), TRIM(LOWER(T3)), "Invalid Email" ) -> kavya.nair@company.com
A4: ORD10003 | B4: C010 | C4: P101 | D4: 03/09/2025 | E4: 14/09/2025 | F4: pooja shah | G4: Female | H4: 16/09/1994 | I4: Bengaluru | J4: South | K4: Electronics | L4: Laptop | M4: 5 | N4: 55000 | O4: 5 | P4: 261250 | Q4: 3 | R4: NetBanking | S4: Aisha | T4: pooja.shah@company.com | U4: 9380975626 | V4: Pending | W4: {=_xlfn.IFS( OR(Q4<=2, V4="Cancelled"), "BLACKLISTED", AND(P4>=100000, Q4>=4, O4<=10, V4="Completed"), "PLATINUM", AND( P4<=99999, P4>=50000, Q4>=3, V4= "Completed"), "GOLD", AND( P4<50000, V4="Completed"), "SILVER", TRUE, "UNCLASSIFIED")} -> #NAME? | X4: =PROPER(TRIM(F4)) -> Pooja Shah | Y4: =LEFT(X4,3)&RIGHT(A4,4)&LEFT(I4,2) -> Poo0003Be | Z4: =IF(IFERROR(FIND("@", T4), 0), TRIM(LOWER(T4)), "Invalid Email" ) -> pooja.shah@company.com
A5: ORD10002 | B5: C008 | C5: P202 | D5: 21/03/2026 | E5: 02/04/2026 | F5: Kavya Nair | G5: Female | H5: 07/03/2004 | I5: Bengaluru | J5: South | K5: Home Appliances | L5: Iron | M5: 5 | N5: 2200 | O5: 5 | P5: 10450 | Q5: 5 | R5: NetBanking | S5: Aisha | T5: kavya.nair@company.com | U5: 9600261125 | V5: Cancelled | W5: {=_xlfn.IFS( OR(Q5<=2, V5="Cancelled"), "BLACKLISTED", AND(P5>=100000, Q5>=4, O5<=10, V5="Completed"), "PLATINUM", AND( P5<=99999, P5>=50000, Q5>=3, V5= "Completed"), "GOLD", AND( P5<50000, V5="Completed"), "SILVER", TRUE, "UNCLASSIFIED")} -> #NAME? | X5: =PROPER(TRIM(F5)) -> Kavya Nair | Y5: =LEFT(X5,3)&RIGHT(A5,4)&LEFT(I5,2) -> Kav0002Be | Z5: =IF(IFERROR(FIND("@", T5), 0), TRIM(LOWER(T5)), "Invalid Email" ) -> kavya.nair@company.com
A6: ORD10005 | B6: C009 | C6: P103 | D6: 27/09/2025 | E6: 07/10/2025 | F6: Mohit Verma | G6: Male | H6: 13/04/1976 | I6: Delhi | J6: North | K6: Electronics | L6: Keyboard | M6: 8 | N6: 1200 | O6: 5 | P6: 9120 | Q6: 2 | R6: Card | S6: Aisha | T6: mohit.verma@company.com | U6: 9724635978 | V6: Pending | W6: {=_xlfn.IFS( OR(Q6<=2, V6="Cancelled"), "BLACKLISTED", AND(P6>=100000, Q6>=4, O6<=10, V6="Completed"), "PLATINUM", AND( P6<=99999, P6>=50000, Q6>=3, V6= "Completed"), "GOLD", AND( P6<50000, V6="Completed"), "SILVER", TRUE, "UNCLASSIFIED")} -> #NAME? | X6: =PROPER(TRIM(F6)) -> Mohit Verma | Y6: =LEFT(X6,3)&RIGHT(A6,4)&LEFT(I6,2) -> Moh0005De | Z6: =IF(IFERROR(FIND("@", T6), 0), TRIM(LOWER(T6)), "Invalid Email" ) -> mohit.verma@company.com
A7: ORD10006 | B7: C007 | C7: P202 | D7: 04/01/2026 | E7: 12/01/2026 | F7: arjun Rao | G7: Male | H7: 07/02/1988 | I7: Hyderabad | J7: South | K7: Home Appliances | L7: Iron | M7: 4 | N7: 2200 | O7: 0 | P7: 8800 | Q7: 1 | R7: UPI | S7: Ritika | T7: arjun.rao@company.com | U7: 9780584905 | V7: Completed | W7: {=_xlfn.IFS( OR(Q7<=2, V7="Cancelled"), "BLACKLISTED", AND(P7>=100000, Q7>=4, O7<=10, V7="Completed"), "PLATINUM", AND( P7<=99999, P7>=50000, Q7>=3, V7= "Completed"), "GOLD", AND( P7<50000, V7="Completed"), "SILVER", TRUE, "UNCLASSIFIED")} -> #NAME? | X7: =PROPER(TRIM(F7)) -> Arjun Rao | Y7: =LEFT(X7,3)&RIGHT(A7,4)&LEFT(I7,2) -> Arj0006Hy | Z7: =IF(IFERROR(FIND("@", T7), 0), TRIM(LOWER(T7)), "Invalid Email" ) -> arjun.rao@company.com
A8: ORD10007 | B8: C008 | C8: P201 | D8: 31/02/2025 | E8: 25/02/2026 | F8: Kavya Nair | G8: Female | H8: 20/03/2003 | I8: Hyderabad | J8: South | K8: Home Appliances | L8: Mixer | M8: 2 | N8: 3500 | O8: 5 | P8: 6650 | Q8: 1 | R8: UPI | S8: Ritika | T8: kavya.nair@company.com | U8: 9958252176 | V8: Completed | W8: {=_xlfn.IFS( OR(Q8<=2, V8="Cancelled"), "BLACKLISTED", AND(P8>=100000, Q8>=4, O8<=10, V8="Completed"), "PLATINUM", AND( P8<=99999, P8>=50000, Q8>=3, V8= "Completed"), "GOLD", AND( P8<50000, V8="Completed"), "SILVER", TRUE, "UNCLASSIFIED")} -> #NAME? | X8: =PROPER(TRIM(F8)) -> Kavya Nair | Y8: =LEFT(X8,3)&RIGHT(A8,4)&LEFT(I8,2) -> Kav0007Hy | Z8: =IF(IFERROR(FIND("@", T8), 0), TRIM(LOWER(T8)), "Invalid Email" ) -> kavya.nair@company.com
A9: ORD10008 | B9: C002 | C9: P104 | D9: 13/04/2025 | E9: 19/04/2025 | F9: Priya Patel | G9: Female | H9: 07/03/1995 | I9: Mumbai | J9: West | K9: Electronics | L9: Monitor | M9: 14 | N9: 12000 | O9: 15 | P9: 142800 | Q9: 4 | R9: NetBanking | S9: Ritika | T9: priYa.patel@company.com | U9: 9705521654 | V9: Completed | W9: {=_xlfn.IFS( OR(Q9<=2, V9="Cancelled"), "BLACKLISTED", AND(P9>=100000, Q9>=4, O9<=10, V9="Completed"), "PLATINUM", AND( P9<=99999, P9>=50000, Q9>=3, V9= "Completed"), "GOLD", AND( P9<50000, V9="Completed"), "SILVER", TRUE, "UNCLASSIFIED")} -> #NAME? | X9: =PROPER(TRIM(F9)) -> Priya Patel | Y9: =LEFT(X9,3)&RIGHT(A9,4)&LEFT(I9,2) -> Pri0008Mu | Z9: =IF(IFERROR(FIND("@", T9), 0), TRIM(LOWER(T9)), "Invalid Email" ) -> priya.patel@company.com
A10: ORD10009 | B10: C008 | C10: P104 | D10: 31/01/2026 | E10: 02/02/2026 | F10: kavya Nair | G10: Female | H10: 06/04/1997 | I10: Pune | J10: West | K10: Electronics | L10: Monitor | M10: 4 | N10: 12000 | O10: 15 | P10: 40800 | Q10: 4 | R10: UPI | S10: Neha | T10: kavya.nair@company.com | U10: 9588041011 | V10: Completed | W10: {=_xlfn.IFS( OR(Q10<=2, V10="Cancelled"), "BLACKLISTED", AND(P10>=100000, Q10>=4, O10<=10, V10="Completed"), "PLATINUM", AND( P10<=99999, P10>=50000, Q10>=3, V10= "Completed"), "GOLD", AND( P10<50000, V10="Completed"), "SILVER", TRUE, "UNCLASSIFIED")} -> #NAME? | X10: =PROPER(TRIM(F10)) -> Kavya Nair | Y10: =LEFT(X10,3)&RIGHT(A10,4)&LEFT(I10,2) -> Kav0009Pu | Z10: =IF(IFERROR(FIND("@", T10), 0), TRIM(LOWER(T10)), "Invalid Email" ) -> kavya.nair@company.com
A11: ORD10010 | B11: C002 | C11: P301 | D11: 25/03/2025 | E11: 27/03/2025 | F11: Priya Patel | G11: Female | H11: 07/01/1990 | I11: Mumbai | J11: West | K11: Stationery | L11: Notebook | M11: 6 | N11: 60 | O11: 0 | P11: 360 | Q11: 4 | R11: Card | S11: Neha | T11: PRiya.patel@company.com | U11: 9340540608 | V11: Completed | W11: {=_xlfn.IFS( OR(Q11<=2, V11="Cancelled"), "BLACKLISTED", AND(P11>=100000, Q11>=4, O11<=10, V11="Completed"), "PLATINUM", AND( P11<=99999, P11>=50000, Q11>=3, V11= "Completed"), "GOLD", AND( P11<50000, V11="Completed"), "SILVER", TRUE, "UNCLASSIFIED")} -> #NAME? | X11: =PROPER(TRIM(F11)) -> Priya Patel | Y11: =LEFT(X11,3)&RIGHT(A11,4)&LEFT(I11,2) -> Pri0010Mu | Z11: =IF(IFERROR(FIND("@", T11), 0), TRIM(LOWER(T11)), "Invalid Email" ) -> priya.patel@company.com
A12: ORD10011 | B12: C003 | C12: P202 | D12: 19/09/2025 | E12: 23/09/2025 | F12: Rohit Singh | G12: Male | H12: 10/05/1982 | I12: Delhi | J12: North | K12: Home Appliances | L12: Iron | M12: -3 | N12: 2200 | O12: 0 | P12: 35200 | Q12: 2 | R12: Card | S12: Rahul | T12: rohit.singh@company.com | U12: 9521710321 | V12: Pending | W12: {=_xlfn.IFS( OR(Q12<=2, V12="Cancelled"), "BLACKLISTED", AND(P12>=100000, Q12>=4, O12<=10, V12="Completed"), "PLATINUM", AND( P12<=99999, P12>=50000, Q12>=3, V12= "Completed"), "GOLD", AND( P12<50000, V12="Completed"), "SILVER", TRUE, "UNCLASSIFIED")} -> #NAME? | X12: =PROPER(TRIM(F12)) -> Rohit Singh | Y12: =LEFT(X12,3)&RIGHT(A12,4)&LEFT(I12,2) -> Roh0011De | Z12: =IF(IFERROR(FIND("@", T12), 0), TRIM(LOWER(T12)), "Invalid Email" ) -> rohit.singh@company.com
A13: ORD10012 | B13: C008 | C13: P201 | D13: 08/03/2025 | E13: 15/03/2025 | F13: Kavya Nair | G13: Female | H13: 23/01/1982 | I13: Ahmedabad | J13: West | K13: Home Appliances | L13: Mixer | M13: 10 | N13: 3500 | O13: 5 | P13: 33250 | Q13: 5 | R13: Card | S13: Aisha | T13: kavya.nair@company.com | U13: 9123535241 | V13: Cancelled | W13: {=_xlfn.IFS( OR(Q13<=2, V13="Cancelled"), "BLACKLISTED", AND(P13>=100000, Q13>=4, O13<=10, V13="Completed"), "PLATINUM", AND( P13<=99999, P13>=50000, Q13>=3, V13= "Completed"), "GOLD", AND( P13<50000, V13="Completed"), "SILVER", TRUE, "UNCLASSIFIED")} -> #NAME? | X13: =PROPER(TRIM(F13)) -> Kavya Nair | Y13: =LEFT(X13,3)&RIGHT(A13,4)&LEFT(I13,2) -> Kav0012Ah | Z13: =IF(IFERROR(FIND("@", T13), 0), TRIM(LOWER(T13)), "Invalid Email" ) -> kavya.nair@company.com
... A39: ORD10038 | B39: C006 | C39: P201 | D39: 08/03/2026 | E39: 20/03/2026 | F39: Sneha Joshi | G39: Female | H39: 21/06/1980 | I39: Delhi | J39: North | K39: Home Appliances | L39: Mixer | M39: 20 | N39: 3500 | O39: 10 | P39: 63000 | Q39: 3 | R39: Card | S39: Rahul | T39: sneha.joshi@company.com | U39: 9283578533 | V39: Cancelled | W39: {=_xlfn.IFS( OR(Q39<=2, V39="Cancelled"), "BLACKLISTED", AND(P39>=100000, Q39>=4, O39<=10, V39="Completed"), "PLATINUM", AND( P39<=99999, P39>=50000, Q39>=3, V39= "Completed"), "GOLD", AND( P39<50000, V39="Completed"), "SILVER", TRUE, "UNCLASSIFIED")} -> #NAME? | X39: =PROPER(TRIM(F39)) -> Sneha Joshi | Y39: =LEFT(X39,3)&RIGHT(A39,4)&LEFT(I39,2) -> Sne0038De | Z39: =IF(IFERROR(FIND("@", T39), 0), TRIM(LOWER(T39)), "Invalid Email" ) -> sneha.joshi@company.com
A40: ORD10039 | B40: C008 | C40: P302 | D40: 13/02/2025 | E40: 19/02/2025 | F40: Kavya Nair | G40: Female | H40: 17/06/1979 | I40: Pune | J40: West | K40: Stationery | L40: Pen | M40: 5 | N40: 1200 | O40: 0 | P40: 100 | Q40: 1 | R40: Cash | S40: Rahul | T40: kavya.nair@company.com | U40: 9963005771 | V40: Cancelled | W40: {=_xlfn.IFS( OR(Q40<=2, V40="Cancelled"), "BLACKLISTED", AND(P40>=100000, Q40>=4, O40<=10, V40="Completed"), "PLATINUM", AND( P40<=99999, P40>=50000, Q40>=3, V40= "Completed"), "GOLD", AND( P40<50000, V40="Completed"), "SILVER", TRUE, "UNCLASSIFIED")} -> #NAME? | X40: =PROPER(TRIM(F40)) -> Kavya Nair | Y40: =LEFT(X40,3)&RIGHT(A40,4)&LEFT(I40,2) -> Kav0039Pu | Z40: =IF(IFERROR(FIND("@", T40), 0), TRIM(LOWER(T40)), "Invalid Email" ) -> kavya.nair@company.com
A41: ORD10040 | B41: C010 | C41: P203 | D41: 05/10/2025 | E41: 15/10/2025 | F41: Pooja Shah | G41: Female | H41: 18/06/1992 | I41: Mumbai | J41: West | K41: Home Appliances | L41: Microwave | M41: 20 | N41: 8500 | O41: 0 | P41: 170000 | Q41: 1 | R41: UPI | S41: Neha | T41: pooja.shah@company.com | U41: 9484632635 | V41: Cancelled | W41: {=_xlfn.IFS( OR(Q41<=2, V41="Cancelled"), "BLACKLISTED", AND(P41>=100000, Q41>=4, O41<=10, V41="Completed"), "PLATINUM", AND( P41<=99999, P41>=50000, Q41>=3, V41= "Completed"), "GOLD", AND( P41<50000, V41="Completed"), "SILVER", TRUE, "UNCLASSIFIED")} -> #NAME? | X41: =PROPER(TRIM(F41)) -> Pooja Shah | Y41: =LEFT(X41,3)&RIGHT(A41,4)&LEFT(I41,2) -> Poo0040Mu | Z41: =IF(IFERROR(FIND("@", T41), 0), TRIM(LOWER(T41)), "Invalid Email" ) -> pooja.shah@company.com
A42: ORD10041 | B42: C007 | C42: P301 | D42: 10/02/2026 | E42: 12/02/2026 | F42: Arjun Rao | G42: Male | H42: 06/06/1994 | I42: Bengaluru | J42: South | K42: Stationery | L42: Notebook | M42: 8 | N42: 60 | O42: 15 | P42: 408 | Q42: 5 | R42: UPI | S42: Rahul | T42: arjun.rao@company.com | U42: 9276319484 | V42: Pending | W42: {=_xlfn.IFS( OR(Q42<=2, V42="Cancelled"), "BLACKLISTED", AND(P42>=100000, Q42>=4, O42<=10, V42="Completed"), "PLATINUM", AND( P42<=99999, P42>=50000, Q42>=3, V42= "Completed"), "GOLD", AND( P42<50000, V42="Completed"), "SILVER", TRUE, "UNCLASSIFIED")} -> #NAME? | X42: =PROPER(TRIM(F42)) -> Arjun Rao | Y42: =LEFT(X42,3)&RIGHT(A42,4)&LEFT(I42,2) -> Arj0041Be | Z42: =IF(IFERROR(FIND("@", T42), 0), TRIM(LOWER(T42)), "Invalid Email" ) -> arjun.rao@company.com
A43: ORD10042 | B43: C010 | C43: P201 | D43: 04/06/2025 | E43: 16/06/2025 | F43: Pooja Shah | G43: Female | H43: 22/09/1988 | I43: Pune | J43: West | K43: Home Appliances | L43: Mixer | M43: 8 | N43: 3500 | O43: 5 | P43: 26600 | Q43: 1 | R43: Card | S43: Neha | T43: pooja.shah@company.com | U43: 9619034852 | V43: Pending | W43: {=_xlfn.IFS( OR(Q43<=2, V43="Cancelled"), "BLACKLISTED", AND(P43>=100000, Q43>=4, O43<=10, V43="Completed"), "PLATINUM", AND( P43<=99999, P43>=50000, Q43>=3, V43= "Completed"), "GOLD", AND( P43<50000, V43="Completed"), "SILVER", TRUE, "UNCLASSIFIED")} -> #NAME? | X43: =PROPER(TRIM(F43)) -> Pooja Shah | Y43: =LEFT(X43,3)&RIGHT(A43,4)&LEFT(I43,2) -> Poo0042Pu | Z43: =IF(IFERROR(FIND("@", T43), 0), TRIM(LOWER(T43)), "Invalid Email" ) -> pooja.shah@company.com
A44: ORD10043 | B44: C009 | C44: P203 | D44: 08/02/2026 | E44: 14/02/2026 | F44: Mohit Verma | G44: Male | H44: 14/07/2001 | I44: Jaipur | J44: North | K44: Home Appliances | L44: Microwave | M44: 1 | N44: 8500 | O44: 0 | P44: 8500 | Q44: 2 | R44: Card | S44: Neha | T44: mohit.verma@company.com | U44: 9636416962 | V44: Pending | W44: {=_xlfn.IFS( OR(Q44<=2, V44="Cancelled"), "BLACKLISTED", AND(P44>=100000, Q44>=4, O44<=10, V44="Completed"), "PLATINUM", AND( P44<=99999, P44>=50000, Q44>=3, V44= "Completed"), "GOLD", AND( P44<50000, V44="Completed"), "SILVER", TRUE, "UNCLASSIFIED")} -> #NAME? | X44: =PROPER(TRIM(F44)) -> Mohit Verma | Y44: =LEFT(X44,3)&RIGHT(A44,4)&LEFT(I44,2) -> Moh0043Ja | Z44: =IF(IFERROR(FIND("@", T44), 0), TRIM(LOWER(T44)), "Invalid Email" ) -> mohit.verma@company.com
A45: ORD10044 | B45: C001 | C45: P303 | D45: 30/03/2025 | E45: 31/03/2025 | F45: amit Sharma | G45: Male | H45: 09/08/1991 | I45: Pune | J45: West | K45: Stationery | L45: Marker | M45: 8 | N45: 45 | O45: 15 | P45: 306 | Q45: 2 | R45: Card | S45: Aisha | T45: amit.sharma@company.com | U45: 9357133880 | V45: Completed | W45: {=_xlfn.IFS( OR(Q45<=2, V45="Cancelled"), "BLACKLISTED", AND(P45>=100000, Q45>=4, O45<=10, V45="Completed"), "PLATINUM", AND( P45<=99999, P45>=50000, Q45>=3, V45= "Completed"), "GOLD", AND( P45<50000, V45="Completed"), "SILVER", TRUE, "UNCLASSIFIED")} -> #NAME? | X45: =PROPER(TRIM(F45)) -> Amit Sharma | Y45: =LEFT(X45,3)&RIGHT(A45,4)&LEFT(I45,2) -> Ami0044Pu | Z45: =IF(IFERROR(FIND("@", T45), 0), TRIM(LOWER(T45)), "Invalid Email" ) -> amit.sharma@company.com
A46: ORD10045 | B46: C006 | C46: P202 | D46: 25/04/2025 | E46: 28/04/2025 | F46: Sneha Joshi | G46: Female | H46: 21/10/1988 | I46: Pune | J46: West | K46: Home Appliances | L46: Iron | M46: 16 | N46: 2200 | O46: 5 | P46: 33440 | Q46: 5 | R46: Card | S46: Aisha | T46: sneha.joshi@company.com | U46: 9575210324 | V46: Cancelled | W46: {=_xlfn.IFS( OR(Q46<=2, V46="Cancelled"), "BLACKLISTED", AND(P46>=100000, Q46>=4, O46<=10, V46="Completed"), "PLATINUM", AND( P46<=99999, P46>=50000, Q46>=3, V46= "Completed"), "GOLD", AND( P46<50000, V46="Completed"), "SILVER", TRUE, "UNCLASSIFIED")} -> #NAME? | X46: =PROPER(TRIM(F46)) -> Sneha Joshi | Y46: =LEFT(X46,3)&RIGHT(A46,4)&LEFT(I46,2) -> Sne0045Pu | Z46: =IF(IFERROR(FIND("@", T46), 0), TRIM(LOWER(T46)), "Invalid Email" ) -> sneha.joshi@company.com
A47: ORD10046 | B47: C009 | C47: P201 | D47: 13/10/2025 | E47: 23/10/2025 | F47: Mohit Verma | G47: Male | H47: 19/11/2002 | I47: Bengaluru | J47: South | K47: Home Appliances | L47: Mixer | M47: 19 | N47: 3500 | O47: 20 | P47: 53200 | Q47: 3 | R47: Cash | S47: Karan | T47: mohit.verma@company.com | U47: 9276080204 | V47: Cancelled | W47: {=_xlfn.IFS( OR(Q47<=2, V47="Cancelled"), "BLACKLISTED", AND(P47>=100000, Q47>=4, O47<=10, V47="Completed"), "PLATINUM", AND( P47<=99999, P47>=50000, Q47>=3, V47= "Completed"), "GOLD", AND( P47<50000, V47="Completed"), "SILVER", TRUE, "UNCLASSIFIED")} -> #NAME? | X47: =PROPER(TRIM(F47)) -> Mohit Verma | Y47: =LEFT(X47,3)&RIGHT(A47,4)&LEFT(I47,2) -> Moh0046Be | Z47: =IF(IFERROR(FIND("@", T47), 0), TRIM(LOWER(T47)), "Invalid Email" ) -> mohit.verma@company.com
A48: ORD10047 | B48: C006 | C48: P102 | D48: 11/10/2025 | E48: 14/10/2025 | F48: Sneha Joshi | G48: Female | H48: 06/07/2000 | I48: Pune | J48: West | K48: Electronics | L48: Mouse | M48: 15 | N48: 700 | O48: 15 | P48: 8925 | Q48: 4 | R48: UPI | S48: Neha | T48: sneha.joshicompany.com | U48: 9856624471 | V48: Completed | W48: {=_xlfn.IFS( OR(Q48<=2, V48="Cancelled"), "BLACKLISTED", AND(P48>=100000, Q48>=4, O48<=10, V48="Completed"), "PLATINUM", AND( P48<=99999, P48>=50000, Q48>=3, V48= "Completed"), "GOLD", AND( P48<50000, V48="Completed"), "SILVER", TRUE, "UNCLASSIFIED")} -> #NAME? | X48: =PROPER(TRIM(F48)) -> Sneha Joshi | Y48: =LEFT(X48,3)&RIGHT(A48,4)&LEFT(I48,2) -> Sne0047Pu | Z48: =IF(IFERROR(FIND("@", T48), 0), TRIM(LOWER(T48)), "Invalid Email" ) -> Invalid Email
A49: ORD10048 | B49: C006 | C49: P102 | D49: 27/11/2025 | E49: 03/12/2025 | F49: Sneha Joshi | G49: Female | H49: 26/11/1998 | I49: Jaipur | J49: North | K49: Electronics | L49: Mouse | M49: 19 | N49: 700 | O49: 20 | P49: 10640 | Q49: 1 | R49: Cash | S49: Neha | T49: sneha.joshi@company.com | U49: 9238141322 | V49: Completed | W49: {=_xlfn.IFS( OR(Q49<=2, V49="Cancelled"), "BLACKLISTED", AND(P49>=100000, Q49>=4, O49<=10, V49="Completed"), "PLATINUM", AND( P49<=99999, P49>=50000, Q49>=3, V49= "Completed"), "GOLD", AND( P49<50000, V49="Completed"), "SILVER", TRUE, "UNCLASSIFIED")} -> #NAME? | X49: =PROPER(TRIM(F49)) -> Sneha Joshi | Y49: =LEFT(X49,3)&RIGHT(A49,4)&LEFT(I49,2) -> Sne0048Ja | Z49: =IF(IFERROR(FIND("@", T49), 0), TRIM(LOWER(T49)), "Invalid Email" ) -> sneha.joshi@company.com
A50: ORD10049 | B50: C009 | C50: P104 | D50: 19/04/2026 | F50: Mohit Verma | G50: Male | H50: 03/06/1996 | I50: Delhi | J50: North | K50: Electronics | L50: Monitor | M50: 19 | N50: 12000 | O50: 0 | P50: 228000 | Q50: 1 | R50: NetBanking | S50: Aisha | T50: mohit.verma@company.com | U50: 9890380030 | V50: Completed | W50: {=_xlfn.IFS( OR(Q50<=2, V50="Cancelled"), "BLACKLISTED", AND(P50>=100000, Q50>=4, O50<=10, V50="Completed"), "PLATINUM", AND( P50<=99999, P50>=50000, Q50>=3, V50= "Completed"), "GOLD", AND( P50<50000, V50="Completed"), "SILVER", TRUE, "UNCLASSIFIED")} -> #NAME? | X50: =PROPER(TRIM(F50)) -> Mohit Verma | Y50: =LEFT(X50,3)&RIGHT(A50,4)&LEFT(I50,2) -> Moh0049De | Z50: =IF(IFERROR(FIND("@", T50), 0), TRIM(LOWER(T50)), "Invalid Email" ) -> mohit.verma@company.com
A51: ORD10050 | B51: C004 | C51: P103 | D51: 19/04/2026 | E51: 21/04/2026 | F51: Anita Gupta | G51: Female | H51: 15/03/1987 | I51: Pune | J51: West | K51: Electronics | L51: Keyboard | M51: 6 | N51: 1200 | O51: 5 | P51: 6840 | Q51: 2 | R51: Cash | S51: Ritika | T51: anita.gupta@company.com | U51: 9495893170 | V51: Pending | W51: {=_xlfn.IFS( OR(Q51<=2, V51="Cancelled"), "BLACKLISTED", AND(P51>=100000, Q51>=4, O51<=10, V51="Completed"), "PLATINUM", AND( P51<=99999, P51>=50000, Q51>=3, V51= "Completed"), "GOLD", AND( P51<50000, V51="Completed"), "SILVER", TRUE, "UNCLASSIFIED")} -> #NAME? | X51: =PROPER(TRIM(F51)) -> Anita Gupta | Y51: =LEFT(X51,3)&RIGHT(A51,4)&LEFT(I51,2) -> Ani0050Pu | Z51: =IF(IFERROR(FIND("@", T51), 0), TRIM(LOWER(T51)), "Invalid Email" ) -> anita.gupta@company.com
A52: ORD10051 | B52: C010 | C52: P202 | D52: 28/03/2025 | E52: 07/04/2025 | F52: POoja Shah | G52: Female | H52: 20/02/1979 | I52: Bengaluru | J52: South | K52: Home Appliances | L52: Iron | M52: 7 | N52: 2200 | O52: 15 | P52: 13090 | Q52: 1 | R52: UPI | S52: Aisha | T52: pooja.shah@company.com | U52: 9485166307 | V52: Completed | W52: {=_xlfn.IFS( OR(Q52<=2, V52="Cancelled"), "BLACKLISTED", AND(P52>=100000, Q52>=4, O52<=10, V52="Completed"), "PLATINUM", AND( P52<=99999, P52>=50000, Q52>=3, V52= "Completed"), "GOLD", AND( P52<50000, V52="Completed"), "SILVER", TRUE, "UNCLASSIFIED")} -> #NAME? | X52: =PROPER(TRIM(F52)) -> Pooja Shah | Y52: =LEFT(X52,3)&RIGHT(A52,4)&LEFT(I52,2) -> Poo0051Be | Z52: =IF(IFERROR(FIND("@", T52), 0), TRIM(LOWER(T52)), "Invalid Email" ) -> pooja.shah@company.com
A53: ORD10052 | B53: C002 | C53: P301 | D53: 25/08/2025 | E53: 28/08/2025 | F53: Priya Patel | G53: Female | H53: 09/08/2000 | I53: Jaipur | J53: North | K53: Stationery | L53: Notebook | M53: 8 | N53: 60 | O53: 10 | P53: 432 | Q53: 5 | R53: Card | S53: Aisha | T53: priya.patel@company.com | U53: 9924709648 | V53: Cancelled | W53: {=_xlfn.IFS( OR(Q53<=2, V53="Cancelled"), "BLACKLISTED", AND(P53>=100000, Q53>=4, O53<=10, V53="Completed"), "PLATINUM", AND( P53<=99999, P53>=50000, Q53>=3, V53= "Completed"), "GOLD", AND( P53<50000, V53="Completed"), "SILVER", TRUE, "UNCLASSIFIED")} -> #NAME? | X53: =PROPER(TRIM(F53)) -> Priya Patel | Y53: =LEFT(X53,3)&RIGHT(A53,4)&LEFT(I53,2) -> Pri0052Ja | Z53: =IF(IFERROR(FIND("@", T53), 0), TRIM(LOWER(T53)), "Invalid Email" ) -> priya.patel@company.com
A54: ORD10053 | B54: C005 | C54: P101 | D54: 19/08/2025 | E54: 23/08/2025 | F54: Vikas Mehta | G54: Male | H54: 17/01/1976 | I54: Kolkata | J54: East | K54: Electronics | L54: Laptop | M54: 12 | N54: 55000 | O54: 5 | P54: 627000 | Q54: 2 | R54: UPI | S54: Rahul | T54: vikas.mehta@company.com | U54: 9350554626 | V54: Pending | W54: {=_xlfn.IFS( OR(Q54<=2, V54="Cancelled"), "BLACKLISTED", AND(P54>=100000, Q54>=4, O54<=10, V54="Completed"), "PLATINUM", AND( P54<=99999, P54>=50000, Q54>=3, V54= "Completed"), "GOLD", AND( P54<50000, V54="Completed"), "SILVER", TRUE, "UNCLASSIFIED")} -> #NAME? | X54: =PROPER(TRIM(F54)) -> Vikas Mehta | Y54: =LEFT(X54,3)&RIGHT(A54,4)&LEFT(I54,2) -> Vik0053Ko | Z54: =IF(IFERROR(FIND("@", T54), 0), TRIM(LOWER(T54)), "Invalid Email" ) -> vikas.mehta@company.com
A55: ORD10054 | B55: C008 | C55: P102 | D55: 27/07/2025 | E55: 05/08/2025 | F55: Kavya Nair | G55: Female | H55: 04/04/1975 | I55: Jaipur | J55: North | K55: Electronics | L55: Mouse | M55: 3 | N55: 700 | O55: 0 | P55: 2100 | Q55: 3 | R55: Card | S55: Karan | T55: kavya.nair@company.com | U55: 9743295580 | V55: Cancelled | W55: {=_xlfn.IFS( OR(Q55<=2, V55="Cancelled"), "BLACKLISTED", AND(P55>=100000, Q55>=4, O55<=10, V55="Completed"), "PLATINUM", AND( P55<=99999, P55>=50000, Q55>=3, V55= "Completed"), "GOLD", AND( P55<50000, V55="Completed"), "SILVER", TRUE, "UNCLASSIFIED")} -> #NAME? | X55: =PROPER(TRIM(F55)) -> Kavya Nair | Y55: =LEFT(X55,3)&RIGHT(A55,4)&LEFT(I55,2) -> Kav0054Ja | Z55: =IF(IFERROR(FIND("@", T55), 0), TRIM(LOWER(T55)), "Invalid Email" ) -> kavya.nair@company.com
A56: ORD10055 | B56: C003 | C56: P301 | D56: 21/02/2025 | E56: 26/02/2025 | F56: RoHit Singh | G56: Male | H56: 11/12/1976 | I56: Ahmedabad | J56: West | K56: Stationery | L56: Notebook | M56: 19 | N56: 60 | O56: 15 | P56: 969 | Q56: 4 | R56: Card | S56: Rahul | T56: rohit.singh@company.com | U56: 9822926495 | V56: Cancelled | W56: {=_xlfn.IFS( OR(Q56<=2, V56="Cancelled"), "BLACKLISTED", AND(P56>=100000, Q56>=4, O56<=10, V56="Completed"), "PLATINUM", AND( P56<=99999, P56>=50000, Q56>=3, V56= "Completed"), "GOLD", AND( P56<50000, V56="Completed"), "SILVER", TRUE, "UNCLASSIFIED")} -> #NAME? | X56: =PROPER(TRIM(F56)) -> Rohit Singh | Y56: =LEFT(X56,3)&RIGHT(A56,4)&LEFT(I56,2) -> Roh0055Ah | Z56: =IF(IFERROR(FIND("@", T56), 0), TRIM(LOWER(T56)), "Invalid Email" ) -> rohit.singh@company.com
A57: ORD10056 | B57: C001 | C57: P301 | D57: 10/08/2025 | E57: 11/08/2025 | F57: Amit Sharma | G57: Male | H57: 03/12/1979 | I57: Jaipur | J57: North | K57: Stationery | L57: Notebook | M57: 9 | N57: 60 | O57: 20 | P57: 432 | Q57: 1 | R57: NetBanking | S57: Neha | T57: amit.sharma@company.com | U57: 9518298190 | V57: Pending | W57: {=_xlfn.IFS( OR(Q57<=2, V57="Cancelled"), "BLACKLISTED", AND(P57>=100000, Q57>=4, O57<=10, V57="Completed"), "PLATINUM", AND( P57<=99999, P57>=50000, Q57>=3, V57= "Completed"), "GOLD", AND( P57<50000, V57="Completed"), "SILVER", TRUE, "UNCLASSIFIED")} -> #NAME? | X57: =PROPER(TRIM(F57)) -> Amit Sharma | Y57: =LEFT(X57,3)&RIGHT(A57,4)&LEFT(I57,2) -> Ami0056Ja | Z57: =IF(IFERROR(FIND("@", T57), 0), TRIM(LOWER(T57)), "Invalid Email" ) -> amit.sharma@company.com
A58: ORD10057 | B58: C001 | C58: P102 | D58: 24/03/2026 | E58: 30/03/2026 | F58: Amit Sharma | G58: Male | H58: 27/12/1978 | I58: Bengaluru | J58: South | K58: Electronics | L58: Mouse | M58: 6 | N58: 700 | O58: 0 | P58: 4200 | Q58: 4 | R58: UPI | S58: Rahul | T58: amit.sharmcompany.com | U58: 9366223547 | V58: Cancelled | W58: {=_xlfn.IFS( OR(Q58<=2, V58="Cancelled"), "BLACKLISTED", AND(P58>=100000, Q58>=4, O58<=10, V58="Completed"), "PLATINUM", AND( P58<=99999, P58>=50000, Q58>=3, V58= "Completed"), "GOLD", AND( P58<50000, V58="Completed"), "SILVER", TRUE, "UNCLASSIFIED")} -> #NAME? | X58: =PROPER(TRIM(F58)) -> Amit Sharma | Y58: =LEFT(X58,3)&RIGHT(A58,4)&LEFT(I58,2) -> Ami0057Be | Z58: =IF(IFERROR(FIND("@", T58), 0), TRIM(LOWER(T58)), "Invalid Email" ) -> Invalid Email
A59: ORD10058 | B59: C003 | C59: P303 | D59: 13/03/2026 | E59: 19/03/2026 | F59: Rohit Singh | G59: Male | H59: 15/04/1975 | I59: Delhi | J59: North | K59: Stationery | L59: Marker | M59: 18 | N59: 45 | O59: 5 | P59: 769.5 | Q59: 1 | R59: Card | S59: Aisha | T59: rohit.singh@company.com | U59: 9701988524 | V59: Pending | W59: {=_xlfn.IFS( OR(Q59<=2, V59="Cancelled"), "BLACKLISTED", AND(P59>=100000, Q59>=4, O59<=10, V59="Completed"), "PLATINUM", AND( P59<=99999, P59>=50000, Q59>=3, V59= "Completed"), "GOLD", AND( P59<50000, V59="Completed"), "SILVER", TRUE, "UNCLASSIFIED")} -> #NAME? | X59: =PROPER(TRIM(F59)) -> Rohit Singh | Y59: =LEFT(X59,3)&RIGHT(A59,4)&LEFT(I59,2) -> Roh0058De | Z59: =IF(IFERROR(FIND("@", T59), 0), TRIM(LOWER(T59)), "Invalid Email" ) -> rohit.singh@company.com
A60: ORD10059 | B60: C007 | C60: P302 | D60: 15/06/2025 | E60: 26/06/2025 | F60: Arjun Rao | G60: Male | H60: 19/12/1988 | I60: Jaipur | J60: North | K60: Stationery | L60: Pen | M60: 8 | N60: 20 | O60: 5 | P60: 152 | Q60: 1 | R60: Card | S60: Ritika | T60: arjun.rao@company.com | U60: 9836327649 | V60: completed | W60: {=_xlfn.IFS( OR(Q60<=2, V60="Cancelled"), "BLACKLISTED", AND(P60>=100000, Q60>=4, O60<=10, V60="Completed"), "PLATINUM", AND( P60<=99999, P60>=50000, Q60>=3, V60= "Completed"), "GOLD", AND( P60<50000, V60="Completed"), "SILVER", TRUE, "UNCLASSIFIED")} -> #NAME? | X60: =PROPER(TRIM(F60)) -> Arjun Rao | Y60: =LEFT(X60,3)&RIGHT(A60,4)&LEFT(I60,2) -> Arj0059Ja | Z60: =IF(IFERROR(FIND("@", T60), 0), TRIM(LOWER(T60)), "Invalid Email" ) -> arjun.rao@company.com
A61: ORD10060 | B61: C005 | C61: P102 | D61: 05/03/2025 | E61: 06/03/2025 | F61: Vikas Mehta | G61: Male | H61: 07/03/1979 | I61: Jaipur | J61: North | K61: Electronics | L61: Mouse | M61: 8 | N61: 700 | O61: 10 | P61: 5040 | Q61: 1 | R61: NetBanking | S61: Aisha | T61: Vikas.mehta@company.com | U61: 9261800516 | V61: Cancelled | W61: {=_xlfn.IFS( OR(Q61<=2, V61="Cancelled"), "BLACKLISTED", AND(P61>=100000, Q61>=4, O61<=10, V61="Completed"), "PLATINUM", AND( P61<=99999, P61>=50000, Q61>=3, V61= "Completed"), "GOLD", AND( P61<50000, V61="Completed"), "SILVER", TRUE, "UNCLASSIFIED")} -> #NAME? | X61: =PROPER(TRIM(F61)) -> Vikas Mehta | Y61: =LEFT(X61,3)&RIGHT(A61,4)&LEFT(I61,2) -> Vik0060Ja | Z61: =IF(IFERROR(FIND("@", T61), 0), TRIM(LOWER(T61)), "Invalid Email" ) -> vikas.mehta@company.com
A62: ORD10061 | B62: C008 | C62: P302 | D62: 09/04/2026 | E62: 19/04/2026 | F62: Kavya Nair | G62: Female | H62: 17/12/2003 | I62: Delhi | J62: North | K62: Stationery | L62: Pen | M62: 7 | N62: 20 | O62: 15 | P62: 119 | Q62: 5 | R62: Card | S62: Rahul | T62: kavya.nair@company.com | U62: 9950802015 | V62: Completed | W62: {=_xlfn.IFS( OR(Q62<=2, V62="Cancelled"), "BLACKLISTED", AND(P62>=100000, Q62>=4, O62<=10, V62="Completed"), "PLATINUM", AND( P62<=99999, P62>=50000, Q62>=3, V62= "Completed"), "GOLD", AND( P62<50000, V62="Completed"), "SILVER", TRUE, "UNCLASSIFIED")} -> #NAME? | X62: =PROPER(TRIM(F62)) -> Kavya Nair | Y62: =LEFT(X62,3)&RIGHT(A62,4)&LEFT(I62,2) -> Kav0061De | Z62: =IF(IFERROR(FIND("@", T62), 0), TRIM(LOWER(T62)), "Invalid Email" ) -> kavya.nair@company.com
... A74: ORD10073 | B74: C008 | C74: P103 | D74: 13/12/2025 | E74: 23/12/2025 | F74: Kavya Nair | G74: Female | H74: 22/09/1981 | I74: Jaipur | J74: North | K74: Electronics | L74: Keyboard | M74: 1 | N74: 1200 | O74: 5 | P74: 1140 | Q74: 3 | R74: UPI | S74: Aisha | T74: kavya.nair@company.com | U74: 9808988530 | V74: Cancelled | W74: {=_xlfn.IFS( OR(Q74<=2, V74="Cancelled"), "BLACKLISTED", AND(P74>=100000, Q74>=4, O74<=10, V74="Completed"), "PLATINUM", AND( P74<=99999, P74>=50000, Q74>=3, V74= "Completed"), "GOLD", AND( P74<50000, V74="Completed"), "SILVER", TRUE, "UNCLASSIFIED")} -> #NAME? | X74: =PROPER(TRIM(F74)) -> Kavya Nair | Y74: =LEFT(X74,3)&RIGHT(A74,4)&LEFT(I74,2) -> Kav0073Ja | Z74: =IF(IFERROR(FIND("@", T74), 0), TRIM(LOWER(T74)), "Invalid Email" ) -> kavya.nair@company.com
A75: ORD10074 | B75: C010 | C75: P202 | D75: 04/02/2026 | E75: 16/02/2026 | F75: Pooja Shah | G75: Female | H75: 20/06/1980 | J75: South | K75: Home Appliances | L75: Iron | M75: 1 | N75: 2200 | O75: 15 | P75: 1870 | Q75: 4 | R75: Card | S75: Aisha | T75: pooja.shah@company.com | U75: 9286410494 | V75: Completed | W75: {=_xlfn.IFS( OR(Q75<=2, V75="Cancelled"), "BLACKLISTED", AND(P75>=100000, Q75>=4, O75<=10, V75="Completed"), "PLATINUM", AND( P75<=99999, P75>=50000, Q75>=3, V75= "Completed"), "GOLD", AND( P75<50000, V75="Completed"), "SILVER", TRUE, "UNCLASSIFIED")} -> #NAME? | X75: =PROPER(TRIM(F75)) -> Pooja Shah | Y75: =LEFT(X75,3)&RIGHT(A75,4)&LEFT(I75,2) -> Poo0074 | Z75: =IF(IFERROR(FIND("@", T75), 0), TRIM(LOWER(T75)), "Invalid Email" ) -> pooja.shah@company.com
A76: ORD10075 | B76: C003 | C76: P103 | D76: 26/01/2026 | E76: 28/01/2026 | F76: Rohit Singh | G76: Male | H76: 02/11/1982 | I76: Pune | J76: West | K76: Electronics | L76: Keyboard | M76: 3 | N76: 1200 | O76: 10 | P76: 3240 | Q76: 5 | R76: Cash | S76: Rahul | T76: rohit.singh@company.com | U76: 9311555196 | V76: Completed | W76: {=_xlfn.IFS( OR(Q76<=2, V76="Cancelled"), "BLACKLISTED", AND(P76>=100000, Q76>=4, O76<=10, V76="Completed"), "PLATINUM", AND( P76<=99999, P76>=50000, Q76>=3, V76= "Completed"), "GOLD", AND( P76<50000, V76="Completed"), "SILVER", TRUE, "UNCLASSIFIED")} -> #NAME? | X76: =PROPER(TRIM(F76)) -> Rohit Singh | Y76: =LEFT(X76,3)&RIGHT(A76,4)&LEFT(I76,2) -> Roh0075Pu | Z76: =IF(IFERROR(FIND("@", T76), 0), TRIM(LOWER(T76)), "Invalid Email" ) -> rohit.singh@company.com
A77: ORD10076 | B77: C008 | C77: P201 | D77: 27/06/2025 | E77: 07/07/2025 | F77: Kavya Nair | G77: Female | H77: 10/01/1980 | I77: Bengaluru | J77: South | K77: Home Appliances | L77: Mixer | M77: 10 | N77: 3500 | O77: 20 | P77: 28000 | Q77: 5 | R77: Card | S77: Ritika | T77: kavya.nair@company.com | U77: 9101810266 | V77: Completed | W77: {=_xlfn.IFS( OR(Q77<=2, V77="Cancelled"), "BLACKLISTED", AND(P77>=100000, Q77>=4, O77<=10, V77="Completed"), "PLATINUM", AND( P77<=99999, P77>=50000, Q77>=3, V77= "Completed"), "GOLD", AND( P77<50000, V77="Completed"), "SILVER", TRUE, "UNCLASSIFIED")} -> #NAME? | X77: =PROPER(TRIM(F77)) -> Kavya Nair | Y77: =LEFT(X77,3)&RIGHT(A77,4)&LEFT(I77,2) -> Kav0076Be | Z77: =IF(IFERROR(FIND("@", T77), 0), TRIM(LOWER(T77)), "Invalid Email" ) -> kavya.nair@company.com
A78: ORD10077 | B78: C007 | C78: P102 | D78: 17/03/2026 | E78: 19/03/2026 | F78: Arjun Rao | G78: Male | H78: 27/04/1981 | I78: Delhi | J78: North | K78: Electronics | L78: Mouse | M78: 18 | N78: 700 | O78: 5 | P78: 11970 | Q78: 3 | R78: Card | S78: Neha | T78: arjun.rao@company.com | U78: 9464556593 | V78: Cancelled | W78: {=_xlfn.IFS( OR(Q78<=2, V78="Cancelled"), "BLACKLISTED", AND(P78>=100000, Q78>=4, O78<=10, V78="Completed"), "PLATINUM", AND( P78<=99999, P78>=50000, Q78>=3, V78= "Completed"), "GOLD", AND( P78<50000, V78="Completed"), "SILVER", TRUE, "UNCLASSIFIED")} -> #NAME? | X78: =PROPER(TRIM(F78)) -> Arjun Rao | Y78: =LEFT(X78,3)&RIGHT(A78,4)&LEFT(I78,2) -> Arj0077De | Z78: =IF(IFERROR(FIND("@", T78), 0), TRIM(LOWER(T78)), "Invalid Email" ) -> arjun.rao@company.com
A79: ORD10078 | B79: C005 | C79: P102 | D79: 09/06/2025 | E79: 18/06/2025 | F79: Vikas Mehta | G79: Male | H79: 12/03/1985 | I79: Bengaluru | J79: South | K79: Electronics | L79: Mouse | M79: 12 | N79: 700 | O79: 15 | P79: 7140 | Q79: 2 | R79: UPI | S79: Rahul | T79: vikas.mehta@company.com | U79: 9338278358 | V79: Completed | W79: {=_xlfn.IFS( OR(Q79<=2, V79="Cancelled"), "BLACKLISTED", AND(P79>=100000, Q79>=4, O79<=10, V79="Completed"), "PLATINUM", AND( P79<=99999, P79>=50000, Q79>=3, V79= "Completed"), "GOLD", AND( P79<50000, V79="Completed"), "SILVER", TRUE, "UNCLASSIFIED")} -> #NAME? | X79: =PROPER(TRIM(F79)) -> Vikas Mehta | Y79: =LEFT(X79,3)&RIGHT(A79,4)&LEFT(I79,2) -> Vik0078Be | Z79: =IF(IFERROR(FIND("@", T79), 0), TRIM(LOWER(T79)), "Invalid Email" ) -> vikas.mehta@company.com
A80: ORD10079 | B80: C009 | C80: P103 | D80: 15/11/2025 | E80: 16/11/2025 | F80: Mohit Verma | G80: Male | H80: 15/03/1999 | I80: Mumbai | J80: West | K80: Electronics | L80: Keyboard | M80: 8 | N80: 1200 | O80: 0 | P80: 9600 | Q80: 4 | R80: Card | S80: Rahul | T80: mohit.verma@company.com | U80: 9621410770 | V80: Pending | W80: {=_xlfn.IFS( OR(Q80<=2, V80="Cancelled"), "BLACKLISTED", AND(P80>=100000, Q80>=4, O80<=10, V80="Completed"), "PLATINUM", AND( P80<=99999, P80>=50000, Q80>=3, V80= "Completed"), "GOLD", AND( P80<50000, V80="Completed"), "SILVER", TRUE, "UNCLASSIFIED")} -> #NAME? | X80: =PROPER(TRIM(F80)) -> Mohit Verma | Y80: =LEFT(X80,3)&RIGHT(A80,4)&LEFT(I80,2) -> Moh0079Mu | Z80: =IF(IFERROR(FIND("@", T80), 0), TRIM(LOWER(T80)), "Invalid Email" ) -> mohit.verma@company.com
A81: ORD10080 | B81: C003 | C81: P301 | D81: 06/11/2025 | E81: 10/11/2025 | F81: Rohit Singh | G81: Male | H81: 07/07/1983 | I81: Pune | J81: West | K81: Stationery | L81: Notebook | M81: 2 | N81: 60 | O81: 0 | P81: 120 | Q81: 2 | R81: UPI | S81: Rahul | T81: rohit.singh@company.com | U81: 9981333189 | V81: Completed | W81: {=_xlfn.IFS( OR(Q81<=2, V81="Cancelled"), "BLACKLISTED", AND(P81>=100000, Q81>=4, O81<=10, V81="Completed"), "PLATINUM", AND( P81<=99999, P81>=50000, Q81>=3, V81= "Completed"), "GOLD", AND( P81<50000, V81="Completed"), "SILVER", TRUE, "UNCLASSIFIED")} -> #NAME? | X81: =PROPER(TRIM(F81)) -> Rohit Singh | Y81: =LEFT(X81,3)&RIGHT(A81,4)&LEFT(I81,2) -> Roh0080Pu | Z81: =IF(IFERROR(FIND("@", T81), 0), TRIM(LOWER(T81)), "Invalid Email" ) -> rohit.singh@company.com
A82: ORD10081 | B82: C001 | C82: P303 | D82: 01/01/2025 | E82: 07/01/2025 | F82: Amit Sharma | G82: Male | H82: 06/03/1989 | I82: Pune | J82: West | K82: Stationery | L82: Marker | M82: 10 | N82: 45 | O82: 15 | P82: 382.5 | Q82: 3 | R82: NetBanking | S82: Ritika | T82: amit.sharma@company.com | U82: 9723450355 | V82: Cancelled | W82: {=_xlfn.IFS( OR(Q82<=2, V82="Cancelled"), "BLACKLISTED", AND(P82>=100000, Q82>=4, O82<=10, V82="Completed"), "PLATINUM", AND( P82<=99999, P82>=50000, Q82>=3, V82= "Completed"), "GOLD", AND( P82<50000, V82="Completed"), "SILVER", TRUE, "UNCLASSIFIED")} -> #NAME? | X82: =PROPER(TRIM(F82)) -> Amit Sharma | Y82: =LEFT(X82,3)&RIGHT(A82,4)&LEFT(I82,2) -> Ami0081Pu | Z82: =IF(IFERROR(FIND("@", T82), 0), TRIM(LOWER(T82)), "Invalid Email" ) -> amit.sharma@company.com
A83: ORD10082 | B83: C005 | C83: P201 | D83: 25/04/2026 | E83: 03/05/2026 | F83: Vikas Mehta | G83: Male | H83: 20/06/1982 | I83: Kolkata | J83: East | K83: Home Appliances | L83: Mixer | M83: 12 | N83: 3500 | O83: 5 | P83: 39900 | Q83: 3 | R83: NetBanking | S83: Aisha | T83: vikas.mehta@company.com | U83: 9886243907 | V83: Pending | W83: {=_xlfn.IFS( OR(Q83<=2, V83="Cancelled"), "BLACKLISTED", AND(P83>=100000, Q83>=4, O83<=10, V83="Completed"), "PLATINUM", AND( P83<=99999, P83>=50000, Q83>=3, V83= "Completed"), "GOLD", AND( P83<50000, V83="Completed"), "SILVER", TRUE, "UNCLASSIFIED")} -> #NAME? | X83: =PROPER(TRIM(F83)) -> Vikas Mehta | Y83: =LEFT(X83,3)&RIGHT(A83,4)&LEFT(I83,2) -> Vik0082Ko | Z83: =IF(IFERROR(FIND("@", T83), 0), TRIM(LOWER(T83)), "Invalid Email" ) -> vikas.mehta@company.com
A84: ORD10083 | B84: C003 | C84: P301 | D84: 19/09/2025 | E84: 27/09/2025 | F84: Rohit Singh | G84: Male | H84: 23/06/2001 | I84: Mumbai | J84: West | K84: Stationery | L84: Notebook | M84: 2 | N84: 60 | O84: 15 | P84: 102 | Q84: 1 | R84: UPI | S84: Neha | T84: rohit.singh@company.com | U84: 9473931904 | V84: Completed | W84: {=_xlfn.IFS( OR(Q84<=2, V84="Cancelled"), "BLACKLISTED", AND(P84>=100000, Q84>=4, O84<=10, V84="Completed"), "PLATINUM", AND( P84<=99999, P84>=50000, Q84>=3, V84= "Completed"), "GOLD", AND( P84<50000, V84="Completed"), "SILVER", TRUE, "UNCLASSIFIED")} -> #NAME? | X84: =PROPER(TRIM(F84)) -> Rohit Singh | Y84: =LEFT(X84,3)&RIGHT(A84,4)&LEFT(I84,2) -> Roh0083Mu | Z84: =IF(IFERROR(FIND("@", T84), 0), TRIM(LOWER(T84)), "Invalid Email" ) -> rohit.singh@company.com
A85: ORD10084 | B85: C003 | C85: P103 | D85: 18/03/2025 | E85: 21/03/2025 | F85: Rohit Singh | G85: Male | H85: 19/07/1983 | I85: Hyderabad | J85: South | K85: Electronics | L85: Keyboard | M85: 18 | N85: 1200 | O85: 15 | P85: 18360 | Q85: 3 | R85: Card | S85: Neha | T85: rohit.singh@company.com | U85: 9287159610 | V85: Pending | W85: {=_xlfn.IFS( OR(Q85<=2, V85="Cancelled"), "BLACKLISTED", AND(P85>=100000, Q85>=4, O85<=10, V85="Completed"), "PLATINUM", AND( P85<=99999, P85>=50000, Q85>=3, V85= "Completed"), "GOLD", AND( P85<50000, V85="Completed"), "SILVER", TRUE, "UNCLASSIFIED")} -> #NAME? | X85: =PROPER(TRIM(F85)) -> Rohit Singh | Y85: =LEFT(X85,3)&RIGHT(A85,4)&LEFT(I85,2) -> Roh0084Hy | Z85: =IF(IFERROR(FIND("@", T85), 0), TRIM(LOWER(T85)), "Invalid Email" ) -> rohit.singh@company.com
A86: ORD10085 | B86: C008 | C86: P104 | D86: 30/10/2025 | E86: 31/10/2025 | F86: Kavya Nair | G86: Female | H86: 24/03/1993 | I86: Mumbai | J86: West | K86: Electronics | L86: Monitor | M86: 18 | N86: 12000 | O86: 15 | P86: 183600 | Q86: 2 | R86: Cash | S86: Rahul | T86: kavya.nair@company.com | U86: 9876513858 | V86: Completed | W86: {=_xlfn.IFS( OR(Q86<=2, V86="Cancelled"), "BLACKLISTED", AND(P86>=100000, Q86>=4, O86<=10, V86="Completed"), "PLATINUM", AND( P86<=99999, P86>=50000, Q86>=3, V86= "Completed"), "GOLD", AND( P86<50000, V86="Completed"), "SILVER", TRUE, "UNCLASSIFIED")} -> #NAME? | X86: =PROPER(TRIM(F86)) -> Kavya Nair | Y86: =LEFT(X86,3)&RIGHT(A86,4)&LEFT(I86,2) -> Kav0085Mu | Z86: =IF(IFERROR(FIND("@", T86), 0), TRIM(LOWER(T86)), "Invalid Email" ) -> kavya.nair@company.com
A87: ORD10086 | B87: C007 | C87: P302 | D87: 31/10/2025 | E87: 11/11/2025 | F87: Arjun Rao | G87: Male | H87: 10/05/1995 | I87: Ahmedabad | J87: West | K87: Stationery | L87: Pen | M87: 7 | N87: 20 | O87: 0 | P87: 140 | Q87: 2 | R87: Card | S87: Ritika | T87: arjun.rao@company.com | U87: 9237400853 | V87: Cancelled | W87: {=_xlfn.IFS( OR(Q87<=2, V87="Cancelled"), "BLACKLISTED", AND(P87>=100000, Q87>=4, O87<=10, V87="Completed"), "PLATINUM", AND( P87<=99999, P87>=50000, Q87>=3, V87= "Completed"), "GOLD", AND( P87<50000, V87="Completed"), "SILVER", TRUE, "UNCLASSIFIED")} -> #NAME? | X87: =PROPER(TRIM(F87)) -> Arjun Rao | Y87: =LEFT(X87,3)&RIGHT(A87,4)&LEFT(I87,2) -> Arj0086Ah | Z87: =IF(IFERROR(FIND("@", T87), 0), TRIM(LOWER(T87)), "Invalid Email" ) -> arjun.rao@company.com
... A119: ORD10118 | B119: C001 | C119: P303 | D119: 31/05/2025 | E119: 11/06/2025 | F119: Amit Sharma | G119: Male | H119: 07/09/1995 | I119: Pune | J119: West | K119: Stationery | L119: Marker | M119: 16 | N119: 45 | O119: 0 | P119: 720 | Q119: 1 | R119: NetBanking | S119: Aisha | T119: amit.sharma@company.com | U119: 9807154421 | V119: Completed | W119: {=_xlfn.IFS( OR(Q119<=2, V119="Cancelled"), "BLACKLISTED", AND(P119>=100000, Q119>=4, O119<=10, V119="Completed"), "PLATINUM", AND( P119<=99999, P119>=50000, Q119>=3, V119= "Completed"), "GOLD", AND( P119<50000, V119="Completed"), "SILVER", TRUE, "UNCLASSIFIED")} -> #NAME? | X119: =PROPER(TRIM(F119)) -> Amit Sharma | Y119: =LEFT(X119,3)&RIGHT(A119,4)&LEFT(I119,2) -> Ami0118Pu | Z119: =IF(IFERROR(FIND("@", T119), 0), TRIM(LOWER(T119)), "Invalid Email" ) -> amit.sharma@company.com
A120: ORD10119 | B120: C009 | C120: P103 | D120: 30/05/2025 | E120: 02/06/2025 | F120: Mohit Verma | G120: Male | H120: 08/03/1988 | I120: Ahmedabad | J120: West | K120: Electronics | L120: Keyboard | M120: Ten | N120: 1200 | O120: 15 | P120: 7140 | Q120: 4 | R120: UPI | S120: Karan | T120: mohit.verma@company.com | U120: 9919834000 | V120: Pending | W120: {=_xlfn.IFS( OR(Q120<=2, V120="Cancelled"), "BLACKLISTED", AND(P120>=100000, Q120>=4, O120<=10, V120="Completed"), "PLATINUM", AND( P120<=99999, P120>=50000, Q120>=3, V120= "Completed"), "GOLD", AND( P120<50000, V120="Completed"), "SILVER", TRUE, "UNCLASSIFIED")} -> #NAME? | X120: =PROPER(TRIM(F120)) -> Mohit Verma | Y120: =LEFT(X120,3)&RIGHT(A120,4)&LEFT(I120,2) -> Moh0119Ah | Z120: =IF(IFERROR(FIND("@", T120), 0), TRIM(LOWER(T120)), "Invalid Email" ) -> mohit.verma@company.com
A121: ORD10120 | B121: C002 | C121: P104 | D121: 19/08/2025 | E121: 30/08/2025 | F121: Priya Patel | G121: Female | H121: 07/07/1989 | I121: Jaipur | J121: North | K121: Electronics | L121: Monitor | M121: 14 | N121: 12000 | O121: 15 | P121: 142800 | Q121: 2 | R121: NetBanking | S121: Aisha | T121: priya.patel@company.com | U121: 9739798818 | V121: Pending | W121: {=_xlfn.IFS( OR(Q121<=2, V121="Cancelled"), "BLACKLISTED", AND(P121>=100000, Q121>=4, O121<=10, V121="Completed"), "PLATINUM", AND( P121<=99999, P121>=50000, Q121>=3, V121= "Completed"), "GOLD", AND( P121<50000, V121="Completed"), "SILVER", TRUE, "UNCLASSIFIED")} -> #NAME? | X121: =PROPER(TRIM(F121)) -> Priya Patel | Y121: =LEFT(X121,3)&RIGHT(A121,4)&LEFT(I121,2) -> Pri0120Ja | Z121: =IF(IFERROR(FIND("@", T121), 0), TRIM(LOWER(T121)), "Invalid Email" ) -> priya.patel@company.com
A122: ORD10121 | B122: C003 | C122: P203 | D122: 14/12/2025 | E122: 16/12/2025 | F122: Rohit Singh | G122: Male | H122: 11/11/1993 | I122: Pune | J122: West | K122: Home Appliances | L122: Microwave | M122: 8 | N122: 8500 | O122: 20 | P122: 54400 | Q122: 3 | R122: Card | S122: Rahul | T122: rohit.singh@company.com | U122: 9208625306 | V122: Completed | W122: {=_xlfn.IFS( OR(Q122<=2, V122="Cancelled"), "BLACKLISTED", AND(P122>=100000, Q122>=4, O122<=10, V122="Completed"), "PLATINUM", AND( P122<=99999, P122>=50000, Q122>=3, V122= "Completed"), "GOLD", AND( P122<50000, V122="Completed"), "SILVER", TRUE, "UNCLASSIFIED")} -> #NAME? | X122: =PROPER(TRIM(F122)) -> Rohit Singh | Y122: =LEFT(X122,3)&RIGHT(A122,4)&LEFT(I122,2) -> Roh0121Pu | Z122: =IF(IFERROR(FIND("@", T122), 0), TRIM(LOWER(T122)), "Invalid Email" ) -> rohit.singh@company.com
A123: ORD10122 | B123: C007 | C123: P303 | D123: 31/01/2026 | E123: 10/02/2026 | F123: Arjun Rao | G123: Male | H123: 01/02/2000 | I123: Bengaluru | J123: South | K123: Stationery | L123: Marker | M123: 3 | N123: 45 | O123: 0 | P123: 135 | Q123: 4 | R123: UPI | S123: Aisha | T123: arjun.rao@company.com | U123: 9970178536 | V123: Cancelled | W123: {=_xlfn.IFS( OR(Q123<=2, V123="Cancelled"), "BLACKLISTED", AND(P123>=100000, Q123>=4, O123<=10, V123="Completed"), "PLATINUM", AND( P123<=99999, P123>=50000, Q123>=3, V123= "Completed"), "GOLD", AND( P123<50000, V123="Completed"), "SILVER", TRUE, "UNCLASSIFIED")} -> #NAME? | X123: =PROPER(TRIM(F123)) -> Arjun Rao | Y123: =LEFT(X123,3)&RIGHT(A123,4)&LEFT(I123,2) -> Arj0122Be | Z123: =IF(IFERROR(FIND("@", T123), 0), TRIM(LOWER(T123)), "Invalid Email" ) -> arjun.rao@company.com
A124: ORD10123 | B124: C001 | C124: P102 | D124: 03/01/2026 | E124: 04/01/2026 | F124: Amit Sharma | G124: Male | H124: 22/06/1986 | I124: Jaipur | J124: North | K124: Electronics | L124: Mouse | M124: 13 | N124: 700 | O124: 5 | P124: 8645 | Q124: 3 | R124: Card | S124: Neha | T124: amit.sharma@company.com | U124: 9633745195 | V124: Pending | W124: {=_xlfn.IFS( OR(Q124<=2, V124="Cancelled"), "BLACKLISTED", AND(P124>=100000, Q124>=4, O124<=10, V124="Completed"), "PLATINUM", AND( P124<=99999, P124>=50000, Q124>=3, V124= "Completed"), "GOLD", AND( P124<50000, V124="Completed"), "SILVER", TRUE, "UNCLASSIFIED")} -> #NAME? | X124: =PROPER(TRIM(F124)) -> Amit Sharma | Y124: =LEFT(X124,3)&RIGHT(A124,4)&LEFT(I124,2) -> Ami0123Ja | Z124: =IF(IFERROR(FIND("@", T124), 0), TRIM(LOWER(T124)), "Invalid Email" ) -> amit.sharma@company.com
A125: ORD10124 | B125: C004 | C125: P103 | D125: 20/10/2025 | E125: 26/10/2025 | F125: Anita Gupta | G125: Female | H125: 16/02/1986 | I125: Mumbai | J125: West | K125: Electronics | L125: Keyboard | M125: 14 | N125: 1200 | O125: 20 | P125: 13440 | Q125: 5 | R125: NetBanking | S125: Aisha | T125: anita.gupta@company.com | U125: 9922102053 | V125: Completed | W125: {=_xlfn.IFS( OR(Q125<=2, V125="Cancelled"), "BLACKLISTED", AND(P125>=100000, Q125>=4, O125<=10, V125="Completed"), "PLATINUM", AND( P125<=99999, P125>=50000, Q125>=3, V125= "Completed"), "GOLD", AND( P125<50000, V125="Completed"), "SILVER", TRUE, "UNCLASSIFIED")} -> #NAME? | X125: =PROPER(TRIM(F125)) -> Anita Gupta | Y125: =LEFT(X125,3)&RIGHT(A125,4)&LEFT(I125,2) -> Ani0124Mu | Z125: =IF(IFERROR(FIND("@", T125), 0), TRIM(LOWER(T125)), "Invalid Email" ) -> anita.gupta@company.com
A126: ORD10125 | B126: C002 | C126: P303 | D126: 11/05/2025 | E126: 21/05/2025 | F126: Priya Patel | G126: Female | H126: 18/09/1991 | I126: Delhi | J126: North | K126: Stationery | L126: Marker | M126: 2 | N126: 45 | O126: 5 | P126: 85.5 | Q126: 3 | R126: UPI | S126: Ritika | T126: priya.patel@company.com | U126: 9135963930 | V126: Cancelled | W126: {=_xlfn.IFS( OR(Q126<=2, V126="Cancelled"), "BLACKLISTED", AND(P126>=100000, Q126>=4, O126<=10, V126="Completed"), "PLATINUM", AND( P126<=99999, P126>=50000, Q126>=3, V126= "Completed"), "GOLD", AND( P126<50000, V126="Completed"), "SILVER", TRUE, "UNCLASSIFIED")} -> #NAME? | X126: =PROPER(TRIM(F126)) -> Priya Patel | Y126: =LEFT(X126,3)&RIGHT(A126,4)&LEFT(I126,2) -> Pri0125De | Z126: =IF(IFERROR(FIND("@", T126), 0), TRIM(LOWER(T126)), "Invalid Email" ) -> priya.patel@company.com
A127: ORD10126 | B127: C004 | C127: P103 | D127: 02/01/2026 | E127: 06/01/2026 | F127: Anita Gupta | G127: Female | H127: 04/01/1981 | I127: Bengaluru | J127: South | K127: Electronics | L127: Keyboard | M127: 2 | N127: 1200 | O127: 20 | P127: 1920 | Q127: 3 | R127: Card | S127: Neha | T127: anita.gupta@company.com | U127: 9429405275 | V127: Completed | W127: {=_xlfn.IFS( OR(Q127<=2, V127="Cancelled"), "BLACKLISTED", AND(P127>=100000, Q127>=4, O127<=10, V127="Completed"), "PLATINUM", AND( P127<=99999, P127>=50000, Q127>=3, V127= "Completed"), "GOLD", AND( P127<50000, V127="Completed"), "SILVER", TRUE, "UNCLASSIFIED")} -> #NAME? | X127: =PROPER(TRIM(F127)) -> Anita Gupta | Y127: =LEFT(X127,3)&RIGHT(A127,4)&LEFT(I127,2) -> Ani0126Be | Z127: =IF(IFERROR(FIND("@", T127), 0), TRIM(LOWER(T127)), "Invalid Email" ) -> anita.gupta@company.com
A128: ORD10127 | B128: C003 | C128: P101 | D128: 20/04/2026 | E128: 26/04/2026 | F128: Rohit Singh | G128: Male | H128: 12/10/2004 | I128: Bengaluru | J128: South | K128: Electronics | L128: Laptop | M128: 10 | N128: 55000 | O128: 5 | P128: 522500 | Q128: 5 | R128: UPI | S128: Aisha | T128: rohit.singh@company.com | U128: 9521757571 | V128: Pending | W128: {=_xlfn.IFS( OR(Q128<=2, V128="Cancelled"), "BLACKLISTED", AND(P128>=100000, Q128>=4, O128<=10, V128="Completed"), "PLATINUM", AND( P128<=99999, P128>=50000, Q128>=3, V128= "Completed"), "GOLD", AND( P128<50000, V128="Completed"), "SILVER", TRUE, "UNCLASSIFIED")} -> #NAME? | X128: =PROPER(TRIM(F128)) -> Rohit Singh | Y128: =LEFT(X128,3)&RIGHT(A128,4)&LEFT(I128,2) -> Roh0127Be | Z128: =IF(IFERROR(FIND("@", T128), 0), TRIM(LOWER(T128)), "Invalid Email" ) -> rohit.singh@company.com
A129: ORD10128 | B129: C006 | C129: P201 | D129: 04/08/2025 | E129: 05/08/2025 | F129: Sneha Joshi | G129: Female | H129: 25/03/1984 | I129: Jaipur | J129: North | K129: Home Appliances | L129: Mixer | M129: 15 | N129: 3500 | O129: 10 | P129: 47250 | Q129: 3 | R129: NetBanking | S129: Neha | T129: sneha.joshi@company.com | U129: 9467375455 | V129: Completed | W129: {=_xlfn.IFS( OR(Q129<=2, V129="Cancelled"), "BLACKLISTED", AND(P129>=100000, Q129>=4, O129<=10, V129="Completed"), "PLATINUM", AND( P129<=99999, P129>=50000, Q129>=3, V129= "Completed"), "GOLD", AND( P129<50000, V129="Completed"), "SILVER", TRUE, "UNCLASSIFIED")} -> #NAME? | X129: =PROPER(TRIM(F129)) -> Sneha Joshi | Y129: =LEFT(X129,3)&RIGHT(A129,4)&LEFT(I129,2) -> Sne0128Ja | Z129: =IF(IFERROR(FIND("@", T129), 0), TRIM(LOWER(T129)), "Invalid Email" ) -> sneha.joshi@company.com
A130: ORD10129 | B130: C002 | C130: P202 | D130: 13/08/2025 | E130: 18/08/2025 | F130: Priya Patel | G130: Female | H130: 09/09/1982 | I130: Bengaluru | J130: South | K130: Home Appliances | L130: Iron | M130: 10 | N130: 2200 | O130: 15 | P130: 18700 | Q130: 4 | R130: Card | S130: Rahul | T130: priya.patel@company.com | U130: 9838809695 | V130: Pending | W130: {=_xlfn.IFS( OR(Q130<=2, V130="Cancelled"), "BLACKLISTED", AND(P130>=100000, Q130>=4, O130<=10, V130="Completed"), "PLATINUM", AND( P130<=99999, P130>=50000, Q130>=3, V130= "Completed"), "GOLD", AND( P130<50000, V130="Completed"), "SILVER", TRUE, "UNCLASSIFIED")} -> #NAME? | X130: =PROPER(TRIM(F130)) -> Priya Patel | Y130: =LEFT(X130,3)&RIGHT(A130,4)&LEFT(I130,2) -> Pri0129Be | Z130: =IF(IFERROR(FIND("@", T130), 0), TRIM(LOWER(T130)), "Invalid Email" ) -> priya.patel@company.com
A131: ORD10130 | B131: C006 | C131: P201 | D131: 16/06/2025 | E131: 24/06/2025 | F131: Sneha Joshi | G131: Female | H131: 15/02/1993 | I131: Pune | J131: West | K131: Home Appliances | L131: Mixer | M131: 11 | N131: 3500 | O131: 5 | P131: 36575 | Q131: 5 | R131: Cash | S131: Ritika | T131: sneha.joshi@company.com | U131: 9296609782 | V131: Cancelled | W131: {=_xlfn.IFS( OR(Q131<=2, V131="Cancelled"), "BLACKLISTED", AND(P131>=100000, Q131>=4, O131<=10, V131="Completed"), "PLATINUM", AND( P131<=99999, P131>=50000, Q131>=3, V131= "Completed"), "GOLD", AND( P131<50000, V131="Completed"), "SILVER", TRUE, "UNCLASSIFIED")} -> #NAME? | X131: =PROPER(TRIM(F131)) -> Sneha Joshi | Y131: =LEFT(X131,3)&RIGHT(A131,4)&LEFT(I131,2) -> Sne0130Pu | Z131: =IF(IFERROR(FIND("@", T131), 0), TRIM(LOWER(T131)), "Invalid Email" ) -> sneha.joshi@company.com
A132: ORD10131 | B132: C004 | C132: P103 | D132: 27/04/2026 | E132: 30/04/2026 | F132: Anita Gupta | G132: Female | H132: 08/04/2003 | I132: Bengaluru | J132: South | K132: Electronics | L132: Keyboard | M132: 14 | N132: 1200 | O132: 0 | P132: 16800 | Q132: 5 | R132: Cash | S132: Rahul | T132: anita.gupta@company.com | U132: 9848259992 | V132: Cancelled | W132: {=_xlfn.IFS( OR(Q132<=2, V132="Cancelled"), "BLACKLISTED", AND(P132>=100000, Q132>=4, O132<=10, V132="Completed"), "PLATINUM", AND( P132<=99999, P132>=50000, Q132>=3, V132= "Completed"), "GOLD", AND( P132<50000, V132="Completed"), "SILVER", TRUE, "UNCLASSIFIED")} -> #NAME? | X132: =PROPER(TRIM(F132)) -> Anita Gupta | Y132: =LEFT(X132,3)&RIGHT(A132,4)&LEFT(I132,2) -> Ani0131Be | Z132: =IF(IFERROR(FIND("@", T132), 0), TRIM(LOWER(T132)), "Invalid Email" ) -> anita.gupta@company.com
... A299: ORD10298 | B299: C003 | C299: P101 | D299: 13/01/2025 | E299: 16/01/2025 | F299: Rohit Singh | G299: Male | H299: 03/01/2004 | I299: Hyderabad | J299: South | K299: Electronics | L299: Laptop | M299: 11 | N299: 55000 | O299: 5 | P299: 574750 | Q299: 1 | R299: UPI | S299: Ritika | T299: rohit.singh@company.com | U299: 9482699727 | V299: Cancelled | W299: {=_xlfn.IFS( OR(Q299<=2, V299="Cancelled"), "BLACKLISTED", AND(P299>=100000, Q299>=4, O299<=10, V299="Completed"), "PLATINUM", AND( P299<=99999, P299>=50000, Q299>=3, V299= "Completed"), "GOLD", AND( P299<50000, V299="Completed"), "SILVER", TRUE, "UNCLASSIFIED")} -> #NAME? | X299: =PROPER(TRIM(F299)) -> Rohit Singh | Y299: =LEFT(X299,3)&RIGHT(A299,4)&LEFT(I299,2) -> Roh0298Hy | Z299: =IF(IFERROR(FIND("@", T299), 0), TRIM(LOWER(T299)), "Invalid Email" ) -> rohit.singh@company.com
A300: ORD10299 | B300: C007 | C300: P201 | D300: 05/10/2025 | E300: 17/10/2025 | F300: Arjun Rao | G300: Male | H300: 02/05/1992 | I300: Jaipur | J300: North | K300: Home Appliances | L300: Mixer | M300: 12 | N300: 3500 | O300: 0 | P300: 42000 | Q300: 2 | R300: NetBanking | T300: arjun.rao@company.com | U300: 9332473934 | V300: Pending | W300: {=_xlfn.IFS( OR(Q300<=2, V300="Cancelled"), "BLACKLISTED", AND(P300>=100000, Q300>=4, O300<=10, V300="Completed"), "PLATINUM", AND( P300<=99999, P300>=50000, Q300>=3, V300= "Completed"), "GOLD", AND( P300<50000, V300="Completed"), "SILVER", TRUE, "UNCLASSIFIED")} -> #NAME? | X300: =PROPER(TRIM(F300)) -> Arjun Rao | Y300: =LEFT(X300,3)&RIGHT(A300,4)&LEFT(I300,2) -> Arj0299Ja | Z300: =IF(IFERROR(FIND("@", T300), 0), TRIM(LOWER(T300)), "Invalid Email" ) -> arjun.rao@company.com
A301: ORD10300 | B301: C009 | C301: P303 | D301: 25/02/2026 | E301: 08/03/2026 | F301: Mohit Verma | G301: Male | H301: 26/01/2003 | I301: Hyderabad | J301: South | K301: Stationery | L301: Marker | M301: 15 | N301: 45 | O301: 10 | P301: 607.5 | Q301: 2 | R301: Cash | S301: Karan | T301: mohit.verma@company.com | U301: 9647657382 | V301: Pending | W301: {=_xlfn.IFS( OR(Q301<=2, V301="Cancelled"), "BLACKLISTED", AND(P301>=100000, Q301>=4, O301<=10, V301="Completed"), "PLATINUM", AND( P301<=99999, P301>=50000, Q301>=3, V301= "Completed"), "GOLD", AND( P301<50000, V301="Completed"), "SILVER", TRUE, "UNCLASSIFIED")} -> #NAME? | X301: =PROPER(TRIM(F301)) -> Mohit Verma | Y301: =LEFT(X301,3)&RIGHT(A301,4)&LEFT(I301,2) -> Moh0300Hy | Z301: =IF(IFERROR(FIND("@", T301), 0), TRIM(LOWER(T301)), "Invalid Email" ) -> mohit.verma@company.com
A302: ORD10301 | B302: C001 | C302: P303 | D302: 16/05/2025 | E302: 26/05/2025 | F302: Amit Sharma | G302: Male | H302: 20/05/1987 | I302: Bengaluru | J302: South | K302: Stationery | L302: Marker | M302: 13 | N302: 45 | O302: 0 | P302: 585 | Q302: 5 | R302: NetBanking | S302: Rahul | T302: amit.sharma@company.com | U302: 9736797776 | V302: Pending | W302: {=_xlfn.IFS( OR(Q302<=2, V302="Cancelled"), "BLACKLISTED", AND(P302>=100000, Q302>=4, O302<=10, V302="Completed"), "PLATINUM", AND( P302<=99999, P302>=50000, Q302>=3, V302= "Completed"), "GOLD", AND( P302<50000, V302="Completed"), "SILVER", TRUE, "UNCLASSIFIED")} -> #NAME? | X302: =PROPER(TRIM(F302)) -> Amit Sharma | Y302: =LEFT(X302,3)&RIGHT(A302,4)&LEFT(I302,2) -> Ami0301Be | Z302: =IF(IFERROR(FIND("@", T302), 0), TRIM(LOWER(T302)), "Invalid Email" ) -> amit.sharma@company.com
A303: ORD10302 | B303: C003 | C303: P101 | D303: 02/01/2026 | E303: 05/01/2026 | F303: Rohit Singh | G303: Male | H303: 07/09/1975 | I303: Bengaluru | J303: South | K303: Electronics | L303: Laptop | M303: 8 | N303: 55000 | O303: 0 | P303: 440000 | Q303: 2 | R303: UPI | S303: Karan | T303: rohit.singh@company.com | U303: 9745773533 | V303: Cancelled | W303: {=_xlfn.IFS( OR(Q303<=2, V303="Cancelled"), "BLACKLISTED", AND(P303>=100000, Q303>=4, O303<=10, V303="Completed"), "PLATINUM", AND( P303<=99999, P303>=50000, Q303>=3, V303= "Completed"), "GOLD", AND( P303<50000, V303="Completed"), "SILVER", TRUE, "UNCLASSIFIED")} -> #NAME? | X303: =PROPER(TRIM(F303)) -> Rohit Singh | Y303: =LEFT(X303,3)&RIGHT(A303,4)&LEFT(I303,2) -> Roh0302Be | Z303: =IF(IFERROR(FIND("@", T303), 0), TRIM(LOWER(T303)), "Invalid Email" ) -> rohit.singh@company.com
A304: ORD10303 | B304: C006 | C304: P101 | D304: 23/07/2025 | E304: 27/07/2025 | F304: Sneha Joshi | G304: Female | H304: 10/08/1980 | I304: Delhi | J304: North | K304: Electronics | L304: Laptop | M304: 4 | N304: 55000 | O304: 20 | P304: 176000 | Q304: 5 | R304: Cash | S304: Rahul | T304: sneha.joshi@company.com | U304: 9246715757 | V304: Pending | W304: {=_xlfn.IFS( OR(Q304<=2, V304="Cancelled"), "BLACKLISTED", AND(P304>=100000, Q304>=4, O304<=10, V304="Completed"), "PLATINUM", AND( P304<=99999, P304>=50000, Q304>=3, V304= "Completed"), "GOLD", AND( P304<50000, V304="Completed"), "SILVER", TRUE, "UNCLASSIFIED")} -> #NAME? | X304: =PROPER(TRIM(F304)) -> Sneha Joshi | Y304: =LEFT(X304,3)&RIGHT(A304,4)&LEFT(I304,2) -> Sne0303De | Z304: =IF(IFERROR(FIND("@", T304), 0), TRIM(LOWER(T304)), "Invalid Email" ) -> sneha.joshi@company.com
A305: ORD10304 | B305: C008 | C305: P201 | D305: 23/04/2026 | E305: 26/04/2026 | F305: Kavya Nair | G305: Female | H305: 07/04/1989 | I305: Ahmedabad | J305: West | K305: Home Appliances | L305: Mixer | M305: 19 | N305: 3500 | O305: 5 | P305: 63175 | Q305: 1 | R305: Card | S305: Neha | T305: kavya.nair@company.com | U305: 9904065774 | V305: Completed | W305: {=_xlfn.IFS( OR(Q305<=2, V305="Cancelled"), "BLACKLISTED", AND(P305>=100000, Q305>=4, O305<=10, V305="Completed"), "PLATINUM", AND( P305<=99999, P305>=50000, Q305>=3, V305= "Completed"), "GOLD", AND( P305<50000, V305="Completed"), "SILVER", TRUE, "UNCLASSIFIED")} -> #NAME? | X305: =PROPER(TRIM(F305)) -> Kavya Nair | Y305: =LEFT(X305,3)&RIGHT(A305,4)&LEFT(I305,2) -> Kav0304Ah | Z305: =IF(IFERROR(FIND("@", T305), 0), TRIM(LOWER(T305)), "Invalid Email" ) -> kavya.nair@company.com
A306: ORD10305 | B306: C005 | C306: P103 | D306: 02/03/2025 | E306: 06/03/2025 | F306: Vikas Mehta | G306: Male | H306: 20/08/1998 | I306: Jaipur | J306: North | K306: Electronics | L306: Keyboard | M306: 17 | N306: 1200 | O306: 15 | P306: 17340 | Q306: 2 | R306: NetBanking | S306: Rahul | T306: vikas.mehta@company.com | U306: 9652985385 | V306: Completed | W306: {=_xlfn.IFS( OR(Q306<=2, V306="Cancelled"), "BLACKLISTED", AND(P306>=100000, Q306>=4, O306<=10, V306="Completed"), "PLATINUM", AND( P306<=99999, P306>=50000, Q306>=3, V306= "Completed"), "GOLD", AND( P306<50000, V306="Completed"), "SILVER", TRUE, "UNCLASSIFIED")} -> #NAME? | X306: =PROPER(TRIM(F306)) -> Vikas Mehta | Y306: =LEFT(X306,3)&RIGHT(A306,4)&LEFT(I306,2) -> Vik0305Ja | Z306: =IF(IFERROR(FIND("@", T306), 0), TRIM(LOWER(T306)), "Invalid Email" ) -> vikas.mehta@company.com
A307: ORD10306 | B307: C008 | C307: P202 | D307: 09/02/2026 | E307: 17/02/2026 | F307: Kavya Nair | G307: Female | H307: 03/04/2001 | I307: Hyderabad | J307: South | K307: Home Appliances | L307: Iron | M307: 8 | N307: 2200 | O307: 5 | P307: 16720 | Q307: 3 | R307: Card | S307: Neha | T307: kavya.nair@company.com | U307: 9427001508 | V307: Pending | W307: {=_xlfn.IFS( OR(Q307<=2, V307="Cancelled"), "BLACKLISTED", AND(P307>=100000, Q307>=4, O307<=10, V307="Completed"), "PLATINUM", AND( P307<=99999, P307>=50000, Q307>=3, V307= "Completed"), "GOLD", AND( P307<50000, V307="Completed"), "SILVER", TRUE, "UNCLASSIFIED")} -> #NAME? | X307: =PROPER(TRIM(F307)) -> Kavya Nair | Y307: =LEFT(X307,3)&RIGHT(A307,4)&LEFT(I307,2) -> Kav0306Hy | Z307: =IF(IFERROR(FIND("@", T307), 0), TRIM(LOWER(T307)), "Invalid Email" ) -> kavya.nair@company.com
A308: ORD10307 | B308: C006 | C308: P102 | D308: 16/02/2025 | E308: 26/02/2025 | F308: Sneha Joshi | G308: Female | H308: 05/03/1992 | I308: Mumbai | J308: West | K308: Electronics | L308: Mouse | M308: 17 | N308: 700 | O308: 20 | P308: 9520 | Q308: 4 | R308: NetBanking | S308: Neha | T308: sneha.joshi@company.com | U308: 9666803655 | V308: Completed | W308: {=_xlfn.IFS( OR(Q308<=2, V308="Cancelled"), "BLACKLISTED", AND(P308>=100000, Q308>=4, O308<=10, V308="Completed"), "PLATINUM", AND( P308<=99999, P308>=50000, Q308>=3, V308= "Completed"), "GOLD", AND( P308<50000, V308="Completed"), "SILVER", TRUE, "UNCLASSIFIED")} -> #NAME? | X308: =PROPER(TRIM(F308)) -> Sneha Joshi | Y308: =LEFT(X308,3)&RIGHT(A308,4)&LEFT(I308,2) -> Sne0307Mu | Z308: =IF(IFERROR(FIND("@", T308), 0), TRIM(LOWER(T308)), "Invalid Email" ) -> sneha.joshi@company.com
A309: ORD10308 | B309: C006 | C309: P203 | D309: 28/08/2025 | E309: 08/09/2025 | F309: Sneha Joshi | G309: Female | H309: 28/12/1976 | I309: Pune | J309: West | K309: Home Appliances | L309: Microwave | M309: 6 | N309: 8500 | O309: 15 | P309: 43350 | Q309: 1 | R309: Cash | S309: Aisha | T309: sneha.joshi@company.com | U309: 9134878547 | V309: Completed | W309: {=_xlfn.IFS( OR(Q309<=2, V309="Cancelled"), "BLACKLISTED", AND(P309>=100000, Q309>=4, O309<=10, V309="Completed"), "PLATINUM", AND( P309<=99999, P309>=50000, Q309>=3, V309= "Completed"), "GOLD", AND( P309<50000, V309="Completed"), "SILVER", TRUE, "UNCLASSIFIED")} -> #NAME? | X309: =PROPER(TRIM(F309)) -> Sneha Joshi | Y309: =LEFT(X309,3)&RIGHT(A309,4)&LEFT(I309,2) -> Sne0308Pu | Z309: =IF(IFERROR(FIND("@", T309), 0), TRIM(LOWER(T309)), "Invalid Email" ) -> sneha.joshi@company.com
A310: ORD10309 | B310: C010 | C310: P201 | D310: 06/10/2025 | E310: 11/10/2025 | F310: Pooja Shah | G310: Female | H310: 04/09/1986 | I310: Hyderabad | J310: South | K310: Home Appliances | L310: Mixer | M310: 3 | N310: 3500 | O310: 10 | P310: 9450 | Q310: 1 | R310: NetBanking | S310: Rahul | T310: pooja.shah@company.com | U310: 9253593557 | V310: Completed | W310: {=_xlfn.IFS( OR(Q310<=2, V310="Cancelled"), "BLACKLISTED", AND(P310>=100000, Q310>=4, O310<=10, V310="Completed"), "PLATINUM", AND( P310<=99999, P310>=50000, Q310>=3, V310= "Completed"), "GOLD", AND( P310<50000, V310="Completed"), "SILVER", TRUE, "UNCLASSIFIED")} -> #NAME? | X310: =PROPER(TRIM(F310)) -> Pooja Shah | Y310: =LEFT(X310,3)&RIGHT(A310,4)&LEFT(I310,2) -> Poo0309Hy | Z310: =IF(IFERROR(FIND("@", T310), 0), TRIM(LOWER(T310)), "Invalid Email" ) -> pooja.shah@company.com
A311: ORD10310 | B311: C009 | C311: P104 | D311: 17/01/2025 | E311: 29/01/2025 | F311: Mohit Verma | G311: Male | H311: 14/08/1989 | I311: Ahmedabad | J311: West | K311: Electronics | L311: Monitor | M311: 2 | N311: 12000 | O311: 20 | P311: 19200 | Q311: 1 | R311: Card | S311: Aisha | T311: mohit.verma@company.com | U311: 9183094051 | V311: Completed | W311: {=_xlfn.IFS( OR(Q311<=2, V311="Cancelled"), "BLACKLISTED", AND(P311>=100000, Q311>=4, O311<=10, V311="Completed"), "PLATINUM", AND( P311<=99999, P311>=50000, Q311>=3, V311= "Completed"), "GOLD", AND( P311<50000, V311="Completed"), "SILVER", TRUE, "UNCLASSIFIED")} -> #NAME? | X311: =PROPER(TRIM(F311)) -> Mohit Verma | Y311: =LEFT(X311,3)&RIGHT(A311,4)&LEFT(I311,2) -> Moh0310Ah | Z311: =IF(IFERROR(FIND("@", T311), 0), TRIM(LOWER(T311)), "Invalid Email" ) -> mohit.verma@company.com
A312: ORD10311 | B312: C005 | C312: P302 | D312: 13/10/2025 | E312: 16/10/2025 | F312: Vikas Mehta | G312: Male | H312: 02/03/1991 | I312: Delhi | J312: North | K312: Stationery | L312: Pen | M312: 12 | N312: 20 | O312: 20 | P312: 192 | Q312: 2 | R312: Card | S312: Rahul | T312: vikas.mehta@company.com | U312: 9293147620 | V312: Completed | W312: {=_xlfn.IFS( OR(Q312<=2, V312="Cancelled"), "BLACKLISTED", AND(P312>=100000, Q312>=4, O312<=10, V312="Completed"), "PLATINUM", AND( P312<=99999, P312>=50000, Q312>=3, V312= "Completed"), "GOLD", AND( P312<50000, V312="Completed"), "SILVER", TRUE, "UNCLASSIFIED")} -> #NAME? | X312: =PROPER(TRIM(F312)) -> Vikas Mehta | Y312: =LEFT(X312,3)&RIGHT(A312,4)&LEFT(I312,2) -> Vik0311De | Z312: =IF(IFERROR(FIND("@", T312), 0), TRIM(LOWER(T312)), "Invalid Email" ) -> vikas.mehta@company.com
... A370: ORD10369 | B370: C010 | C370: P301 | D370: 01/04/2026 | E370: 05/04/2026 | F370: Pooja Shah | G370: Female | H370: 04/01/1987 | I370: Hyderabad | J370: South | K370: Stationery | L370: Notebook | M370: 19 | N370: 60 | O370: 15 | P370: 969 | Q370: 4 | R370: NetBanking | S370: Neha | T370: pooja.shah@company.com | U370: 9435947486 | V370: Cancelled | W370: {=_xlfn.IFS( OR(Q370<=2, V370="Cancelled"), "BLACKLISTED", AND(P370>=100000, Q370>=4, O370<=10, V370="Completed"), "PLATINUM", AND( P370<=99999, P370>=50000, Q370>=3, V370= "Completed"), "GOLD", AND( P370<50000, V370="Completed"), "SILVER", TRUE, "UNCLASSIFIED")} -> #NAME? | X370: =PROPER(TRIM(F370)) -> Pooja Shah | Y370: =LEFT(X370,3)&RIGHT(A370,4)&LEFT(I370,2) -> Poo0369Hy | Z370: =IF(IFERROR(FIND("@", T370), 0), TRIM(LOWER(T370)), "Invalid Email" ) -> pooja.shah@company.com
A371: ORD10370 | B371: C001 | C371: P101 | E371: 02/02/2025 | F371: Amit Sharma | G371: Male | H371: 14/05/1992 | I371: Delhi | J371: North | K371: Electronics | L371: Laptop | M371: 15 | N371: 55000 | O371: 0 | P371: 825000 | Q371: 5 | R371: Card | S371: Neha | T371: amit.sharma@company.com | U371: 9411668831 | V371: Cancelled | W371: {=_xlfn.IFS( OR(Q371<=2, V371="Cancelled"), "BLACKLISTED", AND(P371>=100000, Q371>=4, O371<=10, V371="Completed"), "PLATINUM", AND( P371<=99999, P371>=50000, Q371>=3, V371= "Completed"), "GOLD", AND( P371<50000, V371="Completed"), "SILVER", TRUE, "UNCLASSIFIED")} -> #NAME? | X371: =PROPER(TRIM(F371)) -> Amit Sharma | Y371: =LEFT(X371,3)&RIGHT(A371,4)&LEFT(I371,2) -> Ami0370De | Z371: =IF(IFERROR(FIND("@", T371), 0), TRIM(LOWER(T371)), "Invalid Email" ) -> amit.sharma@company.com
A372: ORD10371 | B372: C009 | C372: P303 | D372: 06/10/2025 | E372: 08/10/2025 | F372: Mohit Verma | G372: Male | H372: 03/05/1989 | I372: Bengaluru | J372: South | K372: Stationery | L372: Marker | M372: 11 | N372: 45 | O372: 5 | P372: 470.25 | Q372: 5 | R372: NetBanking | S372: Karan | T372: mohit.verma@company.com | U372: 9523682403 | V372: Completed | W372: {=_xlfn.IFS( OR(Q372<=2, V372="Cancelled"), "BLACKLISTED", AND(P372>=100000, Q372>=4, O372<=10, V372="Completed"), "PLATINUM", AND( P372<=99999, P372>=50000, Q372>=3, V372= "Completed"), "GOLD", AND( P372<50000, V372="Completed"), "SILVER", TRUE, "UNCLASSIFIED")} -> #NAME? | X372: =PROPER(TRIM(F372)) -> Mohit Verma | Y372: =LEFT(X372,3)&RIGHT(A372,4)&LEFT(I372,2) -> Moh0371Be | Z372: =IF(IFERROR(FIND("@", T372), 0), TRIM(LOWER(T372)), "Invalid Email" ) -> mohit.verma@company.com
A373: ORD10372 | B373: C006 | C373: P302 | D373: 12/06/2025 | E373: 17/06/2025 | F373: Sneha Joshi | G373: Female | H373: 19/12/1990 | I373: Jaipur | J373: North | K373: Stationery | L373: Pen | M373: 9 | N373: 20 | O373: 10 | P373: 162 | Q373: 1 | R373: Card | S373: Rahul | T373: sneha.joshi@company.com | U373: 9652936744 | V373: Cancelled | W373: {=_xlfn.IFS( OR(Q373<=2, V373="Cancelled"), "BLACKLISTED", AND(P373>=100000, Q373>=4, O373<=10, V373="Completed"), "PLATINUM", AND( P373<=99999, P373>=50000, Q373>=3, V373= "Completed"), "GOLD", AND( P373<50000, V373="Completed"), "SILVER", TRUE, "UNCLASSIFIED")} -> #NAME? | X373: =PROPER(TRIM(F373)) -> Sneha Joshi | Y373: =LEFT(X373,3)&RIGHT(A373,4)&LEFT(I373,2) -> Sne0372Ja | Z373: =IF(IFERROR(FIND("@", T373), 0), TRIM(LOWER(T373)), "Invalid Email" ) -> sneha.joshi@company.com
A374: ORD10373 | B374: C004 | C374: P303 | D374: 18/11/2025 | E374: 20/11/2025 | F374: Anita Gupta | G374: Female | H374: 09/07/1995 | I374: Bengaluru | J374: South | K374: Stationery | L374: Marker | M374: 5 | N374: 45 | O374: 5 | P374: 213.75 | Q374: 3 | R374: Card | S374: Neha | T374: anita.gupta@company.com | U374: 9726464733 | V374: Pending | W374: {=_xlfn.IFS( OR(Q374<=2, V374="Cancelled"), "BLACKLISTED", AND(P374>=100000, Q374>=4, O374<=10, V374="Completed"), "PLATINUM", AND( P374<=99999, P374>=50000, Q374>=3, V374= "Completed"), "GOLD", AND( P374<50000, V374="Completed"), "SILVER", TRUE, "UNCLASSIFIED")} -> #NAME? | X374: =PROPER(TRIM(F374)) -> Anita Gupta | Y374: =LEFT(X374,3)&RIGHT(A374,4)&LEFT(I374,2) -> Ani0373Be | Z374: =IF(IFERROR(FIND("@", T374), 0), TRIM(LOWER(T374)), "Invalid Email" ) -> anita.gupta@company.com
A375: ORD10374 | B375: C007 | C375: P102 | D375: 01/11/2025 | E375: 02/11/2025 | F375: Arjun Rao | G375: Male | H375: 23/12/1998 | I375: Hyderabad | J375: South | K375: Electronics | L375: Mouse | M375: 5 | N375: 700 | O375: 10 | P375: 3150 | Q375: 2 | R375: UPI | S375: Rahul | T375: arjun.rao@company.com | U375: 9273520544 | V375: Completed | W375: {=_xlfn.IFS( OR(Q375<=2, V375="Cancelled"), "BLACKLISTED", AND(P375>=100000, Q375>=4, O375<=10, V375="Completed"), "PLATINUM", AND( P375<=99999, P375>=50000, Q375>=3, V375= "Completed"), "GOLD", AND( P375<50000, V375="Completed"), "SILVER", TRUE, "UNCLASSIFIED")} -> #NAME? | X375: =PROPER(TRIM(F375)) -> Arjun Rao | Y375: =LEFT(X375,3)&RIGHT(A375,4)&LEFT(I375,2) -> Arj0374Hy | Z375: =IF(IFERROR(FIND("@", T375), 0), TRIM(LOWER(T375)), "Invalid Email" ) -> arjun.rao@company.com
A376: ORD10375 | B376: C005 | C376: P102 | D376: 24/01/2025 | E376: 31/01/2025 | F376: Vikas Mehta | G376: Male | H376: 23/12/1979 | I376: Kolkata | J376: East | K376: Electronics | L376: Mouse | M376: 1 | N376: 700 | O376: 0 | P376: 700 | Q376: 1 | R376: UPI | S376: Karan | T376: vikas.mehta@company.com | U376: 9374259988 | V376: Completed | W376: {=_xlfn.IFS( OR(Q376<=2, V376="Cancelled"), "BLACKLISTED", AND(P376>=100000, Q376>=4, O376<=10, V376="Completed"), "PLATINUM", AND( P376<=99999, P376>=50000, Q376>=3, V376= "Completed"), "GOLD", AND( P376<50000, V376="Completed"), "SILVER", TRUE, "UNCLASSIFIED")} -> #NAME? | X376: =PROPER(TRIM(F376)) -> Vikas Mehta | Y376: =LEFT(X376,3)&RIGHT(A376,4)&LEFT(I376,2) -> Vik0375Ko | Z376: =IF(IFERROR(FIND("@", T376), 0), TRIM(LOWER(T376)), "Invalid Email" ) -> vikas.mehta@company.com
A377: ORD10376 | B377: C008 | C377: P102 | D377: 13/02/2026 | E377: 21/02/2026 | F377: Kavya Nair | G377: Female | H377: 15/12/1975 | I377: Mumbai | J377: West | K377: Electronics | L377: Mouse | M377: 13 | N377: 700 | O377: 20 | P377: 7280 | Q377: 2 | R377: Card | S377: Ritika | T377: kavya.nair@company.com | U377: 9538129419 | V377: Completed | W377: {=_xlfn.IFS( OR(Q377<=2, V377="Cancelled"), "BLACKLISTED", AND(P377>=100000, Q377>=4, O377<=10, V377="Completed"), "PLATINUM", AND( P377<=99999, P377>=50000, Q377>=3, V377= "Completed"), "GOLD", AND( P377<50000, V377="Completed"), "SILVER", TRUE, "UNCLASSIFIED")} -> #NAME? | X377: =PROPER(TRIM(F377)) -> Kavya Nair | Y377: =LEFT(X377,3)&RIGHT(A377,4)&LEFT(I377,2) -> Kav0376Mu | Z377: =IF(IFERROR(FIND("@", T377), 0), TRIM(LOWER(T377)), "Invalid Email" ) -> kavya.nair@company.com
A378: ORD10377 | B378: C009 | C378: P104 | D378: 08/02/2025 | E378: 19/02/2025 | F378: Mohit Verma | G378: Male | H378: 17/05/1993 | I378: Pune | J378: West | K378: Electronics | L378: Monitor | M378: 20 | N378: 12000 | O378: 0 | P378: 240000 | Q378: 2 | R378: Card | S378: Neha | T378: mohit.verma@company.com | U378: 9382815686 | V378: Completed | W378: {=_xlfn.IFS( OR(Q378<=2, V378="Cancelled"), "BLACKLISTED", AND(P378>=100000, Q378>=4, O378<=10, V378="Completed"), "PLATINUM", AND( P378<=99999, P378>=50000, Q378>=3, V378= "Completed"), "GOLD", AND( P378<50000, V378="Completed"), "SILVER", TRUE, "UNCLASSIFIED")} -> #NAME? | X378: =PROPER(TRIM(F378)) -> Mohit Verma | Y378: =LEFT(X378,3)&RIGHT(A378,4)&LEFT(I378,2) -> Moh0377Pu | Z378: =IF(IFERROR(FIND("@", T378), 0), TRIM(LOWER(T378)), "Invalid Email" ) -> mohit.verma@company.com
A379: ORD10378 | B379: C007 | C379: P103 | D379: 28/12/2025 | E379: 06/01/2026 | F379: Arjun Rao | G379: Male | H379: 17/09/1976 | I379: Kolkata | J379: East | K379: Electronics | L379: Keyboard | M379: 9 | N379: 1200 | O379: 15 | P379: 9180 | Q379: 1 | R379: UPI | S379: Ritika | T379: arjun.rao@company.com | U379: 9450746157 | V379: Pending | W379: {=_xlfn.IFS( OR(Q379<=2, V379="Cancelled"), "BLACKLISTED", AND(P379>=100000, Q379>=4, O379<=10, V379="Completed"), "PLATINUM", AND( P379<=99999, P379>=50000, Q379>=3, V379= "Completed"), "GOLD", AND( P379<50000, V379="Completed"), "SILVER", TRUE, "UNCLASSIFIED")} -> #NAME? | X379: =PROPER(TRIM(F379)) -> Arjun Rao | Y379: =LEFT(X379,3)&RIGHT(A379,4)&LEFT(I379,2) -> Arj0378Ko | Z379: =IF(IFERROR(FIND("@", T379), 0), TRIM(LOWER(T379)), "Invalid Email" ) -> arjun.rao@company.com
A380: ORD10379 | B380: C007 | C380: P302 | D380: 01/10/2025 | E380: 03/10/2025 | F380: Arjun Rao | G380: Male | H380: 22/12/1996 | I380: Jaipur | J380: North | K380: Stationery | L380: Pen | M380: 3 | N380: 20 | O380: 15 | P380: 51 | Q380: 3 | R380: Cash | S380: Neha | T380: arjun.rao@company.com | U380: 9349012570 | V380: Pending | W380: {=_xlfn.IFS( OR(Q380<=2, V380="Cancelled"), "BLACKLISTED", AND(P380>=100000, Q380>=4, O380<=10, V380="Completed"), "PLATINUM", AND( P380<=99999, P380>=50000, Q380>=3, V380= "Completed"), "GOLD", AND( P380<50000, V380="Completed"), "SILVER", TRUE, "UNCLASSIFIED")} -> #NAME? | X380: =PROPER(TRIM(F380)) -> Arjun Rao | Y380: =LEFT(X380,3)&RIGHT(A380,4)&LEFT(I380,2) -> Arj0379Ja | Z380: =IF(IFERROR(FIND("@", T380), 0), TRIM(LOWER(T380)), "Invalid Email" ) -> arjun.rao@company.com
A381: ORD10380 | B381: C006 | C381: P101 | D381: 18/12/2025 | E381: 19/12/2025 | F381: Sneha Joshi | G381: Female | H381: 25/12/1995 | I381: Delhi | J381: North | K381: Electronics | L381: Laptop | M381: 8 | N381: 55000 | O381: 20 | P381: 352000 | Q381: 5 | R381: Card | S381: Karan | T381: sneha.joshi@company.com | U381: 9442163790 | V381: Pending | W381: {=_xlfn.IFS( OR(Q381<=2, V381="Cancelled"), "BLACKLISTED", AND(P381>=100000, Q381>=4, O381<=10, V381="Completed"), "PLATINUM", AND( P381<=99999, P381>=50000, Q381>=3, V381= "Completed"), "GOLD", AND( P381<50000, V381="Completed"), "SILVER", TRUE, "UNCLASSIFIED")} -> #NAME? | X381: =PROPER(TRIM(F381)) -> Sneha Joshi | Y381: =LEFT(X381,3)&RIGHT(A381,4)&LEFT(I381,2) -> Sne0380De | Z381: =IF(IFERROR(FIND("@", T381), 0), TRIM(LOWER(T381)), "Invalid Email" ) -> sneha.joshi@company.com
A382: ORD10381 | B382: C006 | C382: P301 | D382: 29/09/2025 | E382: 07/10/2025 | F382: Sneha Joshi | G382: Female | H382: 23/06/1985 | I382: Delhi | J382: North | K382: Stationery | L382: Notebook | M382: 17 | N382: 60 | O382: 20 | P382: 816 | Q382: 1 | R382: UPI | S382: Ritika | T382: sneha.joshi@company.com | U382: 9953329223 | V382: Pending | W382: {=_xlfn.IFS( OR(Q382<=2, V382="Cancelled"), "BLACKLISTED", AND(P382>=100000, Q382>=4, O382<=10, V382="Completed"), "PLATINUM", AND( P382<=99999, P382>=50000, Q382>=3, V382= "Completed"), "GOLD", AND( P382<50000, V382="Completed"), "SILVER", TRUE, "UNCLASSIFIED")} -> #NAME? | X382: =PROPER(TRIM(F382)) -> Sneha Joshi | Y382: =LEFT(X382,3)&RIGHT(A382,4)&LEFT(I382,2) -> Sne0381De | Z382: =IF(IFERROR(FIND("@", T382), 0), TRIM(LOWER(T382)), "Invalid Email" ) -> sneha.joshi@company.com
A383: ORD10382 | B383: C003 | C383: P302 | D383: 14/05/2025 | E383: 22/05/2025 | F383: Rohit Singh | G383: Male | H383: 10/02/1984 | I383: Bengaluru | J383: South | K383: Stationery | L383: Pen | M383: 4 | N383: 20 | O383: 15 | P383: 68 | Q383: 3 | R383: NetBanking | S383: Aisha | T383: rohit.singh@company.com | U383: 9202321359 | V383: Pending | W383: {=_xlfn.IFS( OR(Q383<=2, V383="Cancelled"), "BLACKLISTED", AND(P383>=100000, Q383>=4, O383<=10, V383="Completed"), "PLATINUM", AND( P383<=99999, P383>=50000, Q383>=3, V383= "Completed"), "GOLD", AND( P383<50000, V383="Completed"), "SILVER", TRUE, "UNCLASSIFIED")} -> #NAME? | X383: =PROPER(TRIM(F383)) -> Rohit Singh | Y383: =LEFT(X383,3)&RIGHT(A383,4)&LEFT(I383,2) -> Roh0382Be | Z383: =IF(IFERROR(FIND("@", T383), 0), TRIM(LOWER(T383)), "Invalid Email" ) -> rohit.singh@company.com
... A399: ORD10398 | B399: C007 | C399: P104 | D399: 31/01/2025 | E399: 04/02/2025 | F399: Arjun Rao | G399: Male | H399: 10/12/1978 | I399: Kolkata | J399: East | K399: Electronics | L399: Monitor | M399: 19 | N399: 12000 | O399: 0 | P399: 228000 | Q399: 4 | R399: UPI | S399: Aisha | T399: arjun.rao@company.com | U399: 9136906750 | V399: Pending | W399: {=_xlfn.IFS( OR(Q399<=2, V399="Cancelled"), "BLACKLISTED", AND(P399>=100000, Q399>=4, O399<=10, V399="Completed"), "PLATINUM", AND( P399<=99999, P399>=50000, Q399>=3, V399= "Completed"), "GOLD", AND( P399<50000, V399="Completed"), "SILVER", TRUE, "UNCLASSIFIED")} -> #NAME? | X399: =PROPER(TRIM(F399)) -> Arjun Rao | Y399: =LEFT(X399,3)&RIGHT(A399,4)&LEFT(I399,2) -> Arj0398Ko | Z399: =IF(IFERROR(FIND("@", T399), 0), TRIM(LOWER(T399)), "Invalid Email" ) -> arjun.rao@company.com
A400: ORD10399 | B400: C001 | C400: P102 | E400: 03/11/2025 | F400: Amit Sharma | G400: Male | H400: 01/09/1979 | I400: Bengaluru | J400: South | K400: Electronics | L400: Mouse | M400: 12 | N400: 700 | O400: 15 | P400: 7140 | Q400: 3 | R400: Card | S400: Ritika | T400: amit.sharma@company.com | U400: 9485286324 | V400: Completed | W400: {=_xlfn.IFS( OR(Q400<=2, V400="Cancelled"), "BLACKLISTED", AND(P400>=100000, Q400>=4, O400<=10, V400="Completed"), "PLATINUM", AND( P400<=99999, P400>=50000, Q400>=3, V400= "Completed"), "GOLD", AND( P400<50000, V400="Completed"), "SILVER", TRUE, "UNCLASSIFIED")} -> #NAME? | X400: =PROPER(TRIM(F400)) -> Amit Sharma | Y400: =LEFT(X400,3)&RIGHT(A400,4)&LEFT(I400,2) -> Ami0399Be | Z400: =IF(IFERROR(FIND("@", T400), 0), TRIM(LOWER(T400)), "Invalid Email" ) -> amit.sharma@company.com
A401: ORD10400 | B401: C008 | C401: P103 | D401: 13/05/2025 | E401: 21/05/2025 | F401: Kavya Nair | G401: Female | H401: 08/04/2001 | I401: Delhi | J401: North | K401: Electronics | L401: Keyboard | M401: 16 | N401: 1200 | O401: 20 | P401: 15360 | Q401: 1 | R401: Cash | S401: Rahul | T401: kavya.nair@company.com | U401: 9414633966 | V401: Pending | W401: {=_xlfn.IFS( OR(Q401<=2, V401="Cancelled"), "BLACKLISTED", AND(P401>=100000, Q401>=4, O401<=10, V401="Completed"), "PLATINUM", AND( P401<=99999, P401>=50000, Q401>=3, V401= "Completed"), "GOLD", AND( P401<50000, V401="Completed"), "SILVER", TRUE, "UNCLASSIFIED")} -> #NAME? | X401: =PROPER(TRIM(F401)) -> Kavya Nair | Y401: =LEFT(X401,3)&RIGHT(A401,4)&LEFT(I401,2) -> Kav0400De | Z401: =IF(IFERROR(FIND("@", T401), 0), TRIM(LOWER(T401)), "Invalid Email" ) -> kavya.nair@company.com
A402: ORD10401 | B402: C009 | C402: P203 | D402: 27/12/2025 | E402: 04/01/2026 | F402: Mohit Verma | G402: Male | H402: 01/01/1983 | I402: Hyderabad | J402: South | K402: Home Appliances | L402: Microwave | M402: 10 | N402: 8500 | O402: 5 | P402: 80750 | Q402: 5 | R402: NetBanking | S402: Ritika | T402: mohit.verma@company.com | U402: 9833735234 | V402: Completed | W402: {=_xlfn.IFS( OR(Q402<=2, V402="Cancelled"), "BLACKLISTED", AND(P402>=100000, Q402>=4, O402<=10, V402="Completed"), "PLATINUM", AND( P402<=99999, P402>=50000, Q402>=3, V402= "Completed"), "GOLD", AND( P402<50000, V402="Completed"), "SILVER", TRUE, "UNCLASSIFIED")} -> #NAME? | X402: =PROPER(TRIM(F402)) -> Mohit Verma | Y402: =LEFT(X402,3)&RIGHT(A402,4)&LEFT(I402,2) -> Moh0401Hy | Z402: =IF(IFERROR(FIND("@", T402), 0), TRIM(LOWER(T402)), "Invalid Email" ) -> mohit.verma@company.com
A403: ORD10402 | B403: C008 | C403: P302 | D403: 11/02/2025 | E403: 21/02/2025 | F403: Kavya Nair | G403: Female | H403: 09/08/1989 | I403: Ahmedabad | J403: West | K403: Stationery | L403: Pen | M403: 18 | N403: 20 | O403: 20 | P403: 288 | Q403: 1 | R403: UPI | S403: Ritika | T403: kavya.nair@company.com | U403: 9523689108 | V403: Pending | W403: {=_xlfn.IFS( OR(Q403<=2, V403="Cancelled"), "BLACKLISTED", AND(P403>=100000, Q403>=4, O403<=10, V403="Completed"), "PLATINUM", AND( P403<=99999, P403>=50000, Q403>=3, V403= "Completed"), "GOLD", AND( P403<50000, V403="Completed"), "SILVER", TRUE, "UNCLASSIFIED")} -> #NAME? | X403: =PROPER(TRIM(F403)) -> Kavya Nair | Y403: =LEFT(X403,3)&RIGHT(A403,4)&LEFT(I403,2) -> Kav0402Ah | Z403: =IF(IFERROR(FIND("@", T403), 0), TRIM(LOWER(T403)), "Invalid Email" ) -> kavya.nair@company.com
A404: ORD10403 | B404: C009 | C404: P203 | D404: 13/03/2026 | E404: 19/03/2026 | F404: Mohit Verma | G404: Male | H404: 22/10/1993 | I404: Mumbai | J404: West | K404: Home Appliances | L404: Microwave | M404: 9 | N404: 8500 | O404: 0 | P404: 76500 | Q404: 2 | R404: Card | S404: Ritika | T404: mohit.verma@company.com | U404: 9812909831 | V404: Pending | W404: {=_xlfn.IFS( OR(Q404<=2, V404="Cancelled"), "BLACKLISTED", AND(P404>=100000, Q404>=4, O404<=10, V404="Completed"), "PLATINUM", AND( P404<=99999, P404>=50000, Q404>=3, V404= "Completed"), "GOLD", AND( P404<50000, V404="Completed"), "SILVER", TRUE, "UNCLASSIFIED")} -> #NAME? | X404: =PROPER(TRIM(F404)) -> Mohit Verma | Y404: =LEFT(X404,3)&RIGHT(A404,4)&LEFT(I404,2) -> Moh0403Mu | Z404: =IF(IFERROR(FIND("@", T404), 0), TRIM(LOWER(T404)), "Invalid Email" ) -> mohit.verma@company.com
A405: ORD10404 | B405: C008 | C405: P203 | D405: 01/10/2025 | E405: 12/10/2025 | F405: Kavya Nair | G405: Female | H405: 05/05/2000 | I405: Mumbai | J405: West | K405: Home Appliances | L405: Microwave | M405: 8 | N405: 8500 | O405: 10 | P405: 61200 | Q405: 4 | R405: Cash | S405: Neha | T405: kavya.nair@company.com | U405: 9106290987 | V405: Cancelled | W405: {=_xlfn.IFS( OR(Q405<=2, V405="Cancelled"), "BLACKLISTED", AND(P405>=100000, Q405>=4, O405<=10, V405="Completed"), "PLATINUM", AND( P405<=99999, P405>=50000, Q405>=3, V405= "Completed"), "GOLD", AND( P405<50000, V405="Completed"), "SILVER", TRUE, "UNCLASSIFIED")} -> #NAME? | X405: =PROPER(TRIM(F405)) -> Kavya Nair | Y405: =LEFT(X405,3)&RIGHT(A405,4)&LEFT(I405,2) -> Kav0404Mu | Z405: =IF(IFERROR(FIND("@", T405), 0), TRIM(LOWER(T405)), "Invalid Email" ) -> kavya.nair@company.com
...

Sheet Q3
A1: Order_ID | B1: Customer_ID | C1: Product_ID | D1: Order_Date | E1: Delivery_Date | F1: Customer_Name | G1: Gender | H1: DOB | I1: City | J1: Region | K1: Category | L1: Product_Name | M1: Quantity | N1: Unit_Price | O1: Discount_% | P1: Sales | Q1: Rating | R1: Payment_Mode | S1: Salesperson | T1: Email | U1: Phone | V1: Order_Status | W1: proper customer name | X1: Customer Age | Y1: Delivery time(D) | Z1: Delivery status
A2: ORD10001 | B2: C008 | C2: P202 | D2: 18/09/2025 | E2: 22/09/2025 | F2: Kavya Nair | G2: Female | H2: 01/08/1976 | I2: Hyderabad | J2: South | K2: Home Appliances | L2: Iron | M2: 4 | N2: 2200 | O2: 10 | P2: 7920 | Q2: 4 | R2: Cash | S2: Ritika | T2: KAvya.nair@company.com | U2: 9431429797 | V2: Completed | W2: =PROPER(TRIM(F2)) -> Kavya Nair | X2: =IFERROR(DATEDIF(H2, TODAY(), "y"), " ") -> 49 | Y2: =IFERROR(DATEDIF(D2, E2, "D"), " ") -> 4 | Z2: {=_xlfn.IFS(Y2<=5, "On time", AND(Y2>5, Y2<>" "), "Delayed", Y2=" ", "pending" )} -> #NAME?
A3: ORD10002 | B3: C008 | C3: P104 | D3: 27/04/2025 | E3: 04/05/2025 | F3: Kavya Nair | G3: Female | H3: 16/10/2000 | I3: Delhi | J3: North | K3: Electronics | L3: Monitor | M3: 17 | N3: 12000 | O3: 10 | P3: 183600 | Q3: 1 | R3: NetBanking | S3: Rahul | T3: kavya.nair@company.com | U3: 9129865339 | V3: Completed | W3: =PROPER(TRIM(F3)) -> Kavya Nair | X3: =IFERROR(DATEDIF(H3, TODAY(), "y"), " ") -> 25 | Y3: =IFERROR(DATEDIF(D3, E3, "D"), " ") -> 7 | Z3: {=_xlfn.IFS(Y3<=5, "On time", AND(Y3>5, Y3<>" "), "Delayed", Y3=" ", "pending" )} -> #NAME?
A4: ORD10003 | B4: C010 | C4: P101 | D4: 03/09/2025 | E4: 14/09/2025 | F4: pooja shah | G4: Female | H4: 16/09/1994 | I4: Bengaluru | J4: South | K4: Electronics | L4: Laptop | M4: 5 | N4: 55000 | O4: 5 | P4: 261250 | Q4: 3 | R4: NetBanking | S4: Aisha | T4: pooja.shah@company.com | U4: 9380975626 | V4: Pending | W4: =PROPER(TRIM(F4)) -> Pooja Shah | X4: =IFERROR(DATEDIF(H4, TODAY(), "y"), " ") -> 31 | Y4: =IFERROR(DATEDIF(D4, E4, "D"), " ") -> 11 | Z4: {=_xlfn.IFS(Y4<=5, "On time", AND(Y4>5, Y4<>" "), "Delayed", Y4=" ", "pending" )} -> #NAME?
A5: ORD10002 | B5: C008 | C5: P202 | D5: 21/03/2026 | E5: 02/04/2026 | F5: Kavya Nair | G5: Female | H5: 07/03/2004 | I5: Bengaluru | J5: South | K5: Home Appliances | L5: Iron | M5: 5 | N5: 2200 | O5: 5 | P5: 10450 | Q5: 5 | R5: NetBanking | S5: Aisha | T5: kavya.nair@company.com | U5: 9600261125 | V5: Cancelled | W5: =PROPER(TRIM(F5)) -> Kavya Nair | X5: =IFERROR(DATEDIF(H5, TODAY(), "y"), " ") -> 22 | Y5: =IFERROR(DATEDIF(D5, E5, "D"), " ") -> 12 | Z5: {=_xlfn.IFS(Y5<=5, "On time", AND(Y5>5, Y5<>" "), "Delayed", Y5=" ", "pending" )} -> #NAME?
A6: ORD10005 | B6: C009 | C6: P103 | D6: 27/09/2025 | E6: 07/10/2025 | F6: Mohit Verma | G6: Male | H6: 13/04/1976 | I6: Delhi | J6: North | K6: Electronics | L6: Keyboard | M6: 8 | N6: 1200 | O6: 5 | P6: 9120 | Q6: 2 | R6: Card | S6: Aisha | T6: mohit.verma@company.com | U6: 9724635978 | V6: Pending | W6: =PROPER(TRIM(F6)) -> Mohit Verma | X6: =IFERROR(DATEDIF(H6, TODAY(), "y"), " ") -> 50 | Y6: =IFERROR(DATEDIF(D6, E6, "D"), " ") -> 10 | Z6: {=_xlfn.IFS(Y6<=5, "On time", AND(Y6>5, Y6<>" "), "Delayed", Y6=" ", "pending" )} -> #NAME?
A7: ORD10006 | B7: C007 | C7: P202 | D7: 04/01/2026 | E7: 12/01/2026 | F7: arjun Rao | G7: Male | H7: 07/02/1988 | I7: Hyderabad | J7: South | K7: Home Appliances | L7: Iron | M7: 4 | N7: 2200 | O7: 0 | P7: 8800 | Q7: 1 | R7: UPI | S7: Ritika | T7: arjun.rao@company.com | U7: 9780584905 | V7: Completed | W7: =PROPER(TRIM(F7)) -> Arjun Rao | X7: =IFERROR(DATEDIF(H7, TODAY(), "y"), " ") -> 38 | Y7: =IFERROR(DATEDIF(D7, E7, "D"), " ") -> 8 | Z7: {=_xlfn.IFS(Y7<=5, "On time", AND(Y7>5, Y7<>" "), "Delayed", Y7=" ", "pending" )} -> #NAME?
A8: ORD10007 | B8: C008 | C8: P201 | D8: 31/02/2025 | E8: 25/02/2026 | F8: Kavya Nair | G8: Female | H8: 20/03/2003 | I8: Hyderabad | J8: South | K8: Home Appliances | L8: Mixer | M8: 2 | N8: 3500 | O8: 5 | P8: 6650 | Q8: 1 | R8: UPI | S8: Ritika | T8: kavya.nair@company.com | U8: 9958252176 | V8: Completed | W8: =PROPER(TRIM(F8)) -> Kavya Nair | X8: =IFERROR(DATEDIF(H8, TODAY(), "y"), " ") -> 23 | Y8: =IFERROR(DATEDIF(D8, E8, "D"), " ") | Z8: {=_xlfn.IFS(Y8<=5, "On time", AND(Y8>5, Y8<>" "), "Delayed", Y8=" ", "pending" )} -> #NAME?
A9: ORD10008 | B9: C002 | C9: P104 | D9: 13/04/2025 | E9: 19/04/2025 | F9: Priya Patel | G9: Female | H9: 07/03/1995 | I9: Mumbai | J9: West | K9: Electronics | L9: Monitor | M9: 14 | N9: 12000 | O9: 15 | P9: 142800 | Q9: 4 | R9: NetBanking | S9: Ritika | T9: priYa.patel@company.com | U9: 9705521654 | V9: Completed | W9: =PROPER(TRIM(F9)) -> Priya Patel | X9: =IFERROR(DATEDIF(H9, TODAY(), "y"), " ") -> 31 | Y9: =IFERROR(DATEDIF(D9, E9, "D"), " ") -> 6 | Z9: {=_xlfn.IFS(Y9<=5, "On time", AND(Y9>5, Y9<>" "), "Delayed", Y9=" ", "pending" )} -> #NAME?
A10: ORD10009 | B10: C008 | C10: P104 | D10: 31/01/2026 | E10: 02/02/2026 | F10: kavya Nair | G10: Female | H10: 06/04/1997 | I10: Pune | J10: West | K10: Electronics | L10: Monitor | M10: 4 | N10: 12000 | O10: 15 | P10: 40800 | Q10: 4 | R10: UPI | S10: Neha | T10: kavya.nair@company.com | U10: 9588041011 | V10: Completed | W10: =PROPER(TRIM(F10)) -> Kavya Nair | X10: =IFERROR(DATEDIF(H10, TODAY(), "y"), " ") -> 29 | Y10: =IFERROR(DATEDIF(D10, E10, "D"), " ") -> 2 | Z10: {=_xlfn.IFS(Y10<=5, "On time", AND(Y10>5, Y10<>" "), "Delayed", Y10=" ", "pending" )} -> #NAME?
A11: ORD10010 | B11: C002 | C11: P301 | D11: 25/03/2025 | E11: 27/03/2025 | F11: Priya Patel | G11: Female | H11: 07/01/1990 | I11: Mumbai | J11: West | K11: Stationery | L11: Notebook | M11: 6 | N11: 60 | O11: 0 | P11: 360 | Q11: 4 | R11: Card | S11: Neha | T11: PRiya.patel@company.com | U11: 9340540608 | V11: Completed | W11: =PROPER(TRIM(F11)) -> Priya Patel | X11: =IFERROR(DATEDIF(H11, TODAY(), "y"), " ") -> 36 | Y11: =IFERROR(DATEDIF(D11, E11, "D"), " ") -> 2 | Z11: {=_xlfn.IFS(Y11<=5, "On time", AND(Y11>5, Y11<>" "), "Delayed", Y11=" ", "pending" )} -> #NAME?
A12: ORD10011 | B12: C003 | C12: P202 | D12: 19/09/2025 | E12: 23/09/2025 | F12: Rohit Singh | G12: Male | H12: 10/05/1982 | I12: Delhi | J12: North | K12: Home Appliances | L12: Iron | M12: -3 | N12: 2200 | O12: 0 | P12: 35200 | Q12: 2 | R12: Card | S12: Rahul | T12: rohit.singh@company.com | U12: 9521710321 | V12: Pending | W12: =PROPER(TRIM(F12)) -> Rohit Singh | X12: =IFERROR(DATEDIF(H12, TODAY(), "y"), " ") -> 44 | Y12: =IFERROR(DATEDIF(D12, E12, "D"), " ") -> 4 | Z12: {=_xlfn.IFS(Y12<=5, "On time", AND(Y12>5, Y12<>" "), "Delayed", Y12=" ", "pending" )} -> #NAME?
A13: ORD10012 | B13: C008 | C13: P201 | D13: 08/03/2025 | E13: 15/03/2025 | F13: Kavya Nair | G13: Female | H13: 23/01/1982 | I13: Ahmedabad | J13: West | K13: Home Appliances | L13: Mixer | M13: 10 | N13: 3500 | O13: 5 | P13: 33250 | Q13: 5 | R13: Card | S13: Aisha | T13: kavya.nair@company.com | U13: 9123535241 | V13: Cancelled | W13: =PROPER(TRIM(F13)) -> Kavya Nair | X13: =IFERROR(DATEDIF(H13, TODAY(), "y"), " ") -> 44 | Y13: =IFERROR(DATEDIF(D13, E13, "D"), " ") -> 7 | Z13: {=_xlfn.IFS(Y13<=5, "On time", AND(Y13>5, Y13<>" "), "Delayed", Y13=" ", "pending" )} -> #NAME?
... A39: ORD10038 | B39: C006 | C39: P201 | D39: 08/03/2026 | E39: 20/03/2026 | F39: Sneha Joshi | G39: Female | H39: 21/06/1980 | I39: Delhi | J39: North | K39: Home Appliances | L39: Mixer | M39: 20 | N39: 3500 | O39: 10 | P39: 63000 | Q39: 3 | R39: Card | S39: Rahul | T39: sneha.joshi@company.com | U39: 9283578533 | V39: Cancelled | W39: =PROPER(TRIM(F39)) -> Sneha Joshi | X39: =IFERROR(DATEDIF(H39, TODAY(), "y"), " ") -> 46 | Y39: =IFERROR(DATEDIF(D39, E39, "D"), " ") -> 12 | Z39: {=_xlfn.IFS(Y39<=5, "On time", AND(Y39>5, Y39<>" "), "Delayed", Y39=" ", "pending" )} -> #NAME?
A40: ORD10039 | B40: C008 | C40: P302 | D40: 13/02/2025 | E40: 19/02/2025 | F40: Kavya Nair | G40: Female | H40: 17/06/1979 | I40: Pune | J40: West | K40: Stationery | L40: Pen | M40: 5 | N40: 1200 | O40: 0 | P40: 100 | Q40: 1 | R40: Cash | S40: Rahul | T40: kavya.nair@company.com | U40: 9963005771 | V40: Cancelled | W40: =PROPER(TRIM(F40)) -> Kavya Nair | X40: =IFERROR(DATEDIF(H40, TODAY(), "y"), " ") -> 47 | Y40: =IFERROR(DATEDIF(D40, E40, "D"), " ") -> 6 | Z40: {=_xlfn.IFS(Y40<=5, "On time", AND(Y40>5, Y40<>" "), "Delayed", Y40=" ", "pending" )} -> #NAME?
A41: ORD10040 | B41: C010 | C41: P203 | D41: 05/10/2025 | E41: 15/10/2025 | F41: Pooja Shah | G41: Female | H41: 18/06/1992 | I41: Mumbai | J41: West | K41: Home Appliances | L41: Microwave | M41: 20 | N41: 8500 | O41: 0 | P41: 170000 | Q41: 1 | R41: UPI | S41: Neha | T41: pooja.shah@company.com | U41: 9484632635 | V41: Cancelled | W41: =PROPER(TRIM(F41)) -> Pooja Shah | X41: =IFERROR(DATEDIF(H41, TODAY(), "y"), " ") -> 34 | Y41: =IFERROR(DATEDIF(D41, E41, "D"), " ") -> 10 | Z41: {=_xlfn.IFS(Y41<=5, "On time", AND(Y41>5, Y41<>" "), "Delayed", Y41=" ", "pending" )} -> #NAME?
A42: ORD10041 | B42: C007 | C42: P301 | D42: 10/02/2026 | E42: 12/02/2026 | F42: Arjun Rao | G42: Male | H42: 06/06/1994 | I42: Bengaluru | J42: South | K42: Stationery | L42: Notebook | M42: 8 | N42: 60 | O42: 15 | P42: 408 | Q42: 5 | R42: UPI | S42: Rahul | T42: arjun.rao@company.com | U42: 9276319484 | V42: Pending | W42: =PROPER(TRIM(F42)) -> Arjun Rao | X42: =IFERROR(DATEDIF(H42, TODAY(), "y"), " ") -> 32 | Y42: =IFERROR(DATEDIF(D42, E42, "D"), " ") -> 2 | Z42: {=_xlfn.IFS(Y42<=5, "On time", AND(Y42>5, Y42<>" "), "Delayed", Y42=" ", "pending" )} -> #NAME?
A43: ORD10042 | B43: C010 | C43: P201 | D43: 04/06/2025 | E43: 16/06/2025 | F43: Pooja Shah | G43: Female | H43: 22/09/1988 | I43: Pune | J43: West | K43: Home Appliances | L43: Mixer | M43: 8 | N43: 3500 | O43: 5 | P43: 26600 | Q43: 1 | R43: Card | S43: Neha | T43: pooja.shah@company.com | U43: 9619034852 | V43: Pending | W43: =PROPER(TRIM(F43)) -> Pooja Shah | X43: =IFERROR(DATEDIF(H43, TODAY(), "y"), " ") -> 37 | Y43: =IFERROR(DATEDIF(D43, E43, "D"), " ") -> 12 | Z43: {=_xlfn.IFS(Y43<=5, "On time", AND(Y43>5, Y43<>" "), "Delayed", Y43=" ", "pending" )} -> #NAME?
A44: ORD10043 | B44: C009 | C44: P203 | D44: 08/02/2026 | E44: 14/02/2026 | F44: Mohit Verma | G44: Male | H44: 14/07/2001 | I44: Jaipur | J44: North | K44: Home Appliances | L44: Microwave | M44: 1 | N44: 8500 | O44: 0 | P44: 8500 | Q44: 2 | R44: Card | S44: Neha | T44: mohit.verma@company.com | U44: 9636416962 | V44: Pending | W44: =PROPER(TRIM(F44)) -> Mohit Verma | X44: =IFERROR(DATEDIF(H44, TODAY(), "y"), " ") -> 25 | Y44: =IFERROR(DATEDIF(D44, E44, "D"), " ") -> 6 | Z44: {=_xlfn.IFS(Y44<=5, "On time", AND(Y44>5, Y44<>" "), "Delayed", Y44=" ", "pending" )} -> #NAME?
A45: ORD10044 | B45: C001 | C45: P303 | D45: 30/03/2025 | E45: 31/03/2025 | F45: amit Sharma | G45: Male | H45: 09/08/1991 | I45: Pune | J45: West | K45: Stationery | L45: Marker | M45: 8 | N45: 45 | O45: 15 | P45: 306 | Q45: 2 | R45: Card | S45: Aisha | T45: amit.sharma@company.com | U45: 9357133880 | V45: Completed | W45: =PROPER(TRIM(F45)) -> Amit Sharma | X45: =IFERROR(DATEDIF(H45, TODAY(), "y"), " ") -> 34 | Y45: =IFERROR(DATEDIF(D45, E45, "D"), " ") -> 1 | Z45: {=_xlfn.IFS(Y45<=5, "On time", AND(Y45>5, Y45<>" "), "Delayed", Y45=" ", "pending" )} -> #NAME?
A46: ORD10045 | B46: C006 | C46: P202 | D46: 25/04/2025 | E46: 28/04/2025 | F46: Sneha Joshi | G46: Female | H46: 21/10/1988 | I46: Pune | J46: West | K46: Home Appliances | L46: Iron | M46: 16 | N46: 2200 | O46: 5 | P46: 33440 | Q46: 5 | R46: Card | S46: Aisha | T46: sneha.joshi@company.com | U46: 9575210324 | V46: Cancelled | W46: =PROPER(TRIM(F46)) -> Sneha Joshi | X46: =IFERROR(DATEDIF(H46, TODAY(), "y"), " ") -> 37 | Y46: =IFERROR(DATEDIF(D46, E46, "D"), " ") -> 3 | Z46: {=_xlfn.IFS(Y46<=5, "On time", AND(Y46>5, Y46<>" "), "Delayed", Y46=" ", "pending" )} -> #NAME?
A47: ORD10046 | B47: C009 | C47: P201 | D47: 13/10/2025 | E47: 23/10/2025 | F47: Mohit Verma | G47: Male | H47: 19/11/2002 | I47: Bengaluru | J47: South | K47: Home Appliances | L47: Mixer | M47: 19 | N47: 3500 | O47: 20 | P47: 53200 | Q47: 3 | R47: Cash | S47: Karan | T47: mohit.verma@company.com | U47: 9276080204 | V47: Cancelled | W47: =PROPER(TRIM(F47)) -> Mohit Verma | X47: =IFERROR(DATEDIF(H47, TODAY(), "y"), " ") -> 23 | Y47: =IFERROR(DATEDIF(D47, E47, "D"), " ") -> 10 | Z47: {=_xlfn.IFS(Y47<=5, "On time", AND(Y47>5, Y47<>" "), "Delayed", Y47=" ", "pending" )} -> #NAME?
A48: ORD10047 | B48: C006 | C48: P102 | D48: 11/10/2025 | E48: 14/10/2025 | F48: Sneha Joshi | G48: Female | H48: 06/07/2000 | I48: Pune | J48: West | K48: Electronics | L48: Mouse | M48: 15 | N48: 700 | O48: 15 | P48: 8925 | Q48: 4 | R48: UPI | S48: Neha | T48: sneha.joshicompany.com | U48: 9856624471 | V48: Completed | W48: =PROPER(TRIM(F48)) -> Sneha Joshi | X48: =IFERROR(DATEDIF(H48, TODAY(), "y"), " ") -> 26 | Y48: =IFERROR(DATEDIF(D48, E48, "D"), " ") -> 3 | Z48: {=_xlfn.IFS(Y48<=5, "On time", AND(Y48>5, Y48<>" "), "Delayed", Y48=" ", "pending" )} -> #NAME?
A49: ORD10048 | B49: C006 | C49: P102 | D49: 27/11/2025 | E49: 03/12/2025 | F49: Sneha Joshi | G49: Female | H49: 26/11/1998 | I49: Jaipur | J49: North | K49: Electronics | L49: Mouse | M49: 19 | N49: 700 | O49: 20 | P49: 10640 | Q49: 1 | R49: Cash | S49: Neha | T49: sneha.joshi@company.com | U49: 9238141322 | V49: Completed | W49: =PROPER(TRIM(F49)) -> Sneha Joshi | X49: =IFERROR(DATEDIF(H49, TODAY(), "y"), " ") -> 27 | Y49: =IFERROR(DATEDIF(D49, E49, "D"), " ") -> 6 | Z49: {=_xlfn.IFS(Y49<=5, "On time", AND(Y49>5, Y49<>" "), "Delayed", Y49=" ", "pending" )} -> #NAME?
A50: ORD10049 | B50: C009 | C50: P104 | D50: 19/04/2026 | F50: Mohit Verma | G50: Male | H50: 03/06/1996 | I50: Delhi | J50: North | K50: Electronics | L50: Monitor | M50: 19 | N50: 12000 | O50: 0 | P50: 228000 | Q50: 1 | R50: NetBanking | S50: Aisha | T50: mohit.verma@company.com | U50: 9890380030 | V50: Completed | W50: =PROPER(TRIM(F50)) -> Mohit Verma | X50: =IFERROR(DATEDIF(H50, TODAY(), "y"), " ") -> 30 | Y50: =IFERROR(DATEDIF(D50, E50, "D"), " ") | Z50: {=_xlfn.IFS(Y50<=5, "On time", AND(Y50>5, Y50<>" "), "Delayed", Y50=" ", "pending" )} -> #NAME?
A51: ORD10050 | B51: C004 | C51: P103 | D51: 19/04/2026 | E51: 21/04/2026 | F51: Anita Gupta | G51: Female | H51: 15/03/1987 | I51: Pune | J51: West | K51: Electronics | L51: Keyboard | M51: 6 | N51: 1200 | O51: 5 | P51: 6840 | Q51: 2 | R51: Cash | S51: Ritika | T51: anita.gupta@company.com | U51: 9495893170 | V51: Pending | W51: =PROPER(TRIM(F51)) -> Anita Gupta | X51: =IFERROR(DATEDIF(H51, TODAY(), "y"), " ") -> 39 | Y51: =IFERROR(DATEDIF(D51, E51, "D"), " ") -> 2 | Z51: {=_xlfn.IFS(Y51<=5, "On time", AND(Y51>5, Y51<>" "), "Delayed", Y51=" ", "pending" )} -> #NAME?
A52: ORD10051 | B52: C010 | C52: P202 | D52: 28/03/2025 | E52: 07/04/2025 | F52: POoja Shah | G52: Female | H52: 20/02/1979 | I52: Bengaluru | J52: South | K52: Home Appliances | L52: Iron | M52: 7 | N52: 2200 | O52: 15 | P52: 13090 | Q52: 1 | R52: UPI | S52: Aisha | T52: pooja.shah@company.com | U52: 9485166307 | V52: Completed | W52: =PROPER(TRIM(F52)) -> Pooja Shah | X52: =IFERROR(DATEDIF(H52, TODAY(), "y"), " ") -> 47 | Y52: =IFERROR(DATEDIF(D52, E52, "D"), " ") -> 10 | Z52: {=_xlfn.IFS(Y52<=5, "On time", AND(Y52>5, Y52<>" "), "Delayed", Y52=" ", "pending" )} -> #NAME?
A53: ORD10052 | B53: C002 | C53: P301 | D53: 25/08/2025 | E53: 28/08/2025 | F53: Priya Patel | G53: Female | H53: 09/08/2000 | I53: Jaipur | J53: North | K53: Stationery | L53: Notebook | M53: 8 | N53: 60 | O53: 10 | P53: 432 | Q53: 5 | R53: Card | S53: Aisha | T53: priya.patel@company.com | U53: 9924709648 | V53: Cancelled | W53: =PROPER(TRIM(F53)) -> Priya Patel | X53: =IFERROR(DATEDIF(H53, TODAY(), "y"), " ") -> 25 | Y53: =IFERROR(DATEDIF(D53, E53, "D"), " ") -> 3 | Z53: {=_xlfn.IFS(Y53<=5, "On time", AND(Y53>5, Y53<>" "), "Delayed", Y53=" ", "pending" )} -> #NAME?
A54: ORD10053 | B54: C005 | C54: P101 | D54: 19/08/2025 | E54: 23/08/2025 | F54: Vikas Mehta | G54: Male | H54: 17/01/1976 | I54: Kolkata | J54: East | K54: Electronics | L54: Laptop | M54: 12 | N54: 55000 | O54: 5 | P54: 627000 | Q54: 2 | R54: UPI | S54: Rahul | T54: vikas.mehta@company.com | U54: 9350554626 | V54: Pending | W54: =PROPER(TRIM(F54)) -> Vikas Mehta | X54: =IFERROR(DATEDIF(H54, TODAY(), "y"), " ") -> 50 | Y54: =IFERROR(DATEDIF(D54, E54, "D"), " ") -> 4 | Z54: {=_xlfn.IFS(Y54<=5, "On time", AND(Y54>5, Y54<>" "), "Delayed", Y54=" ", "pending" )} -> #NAME?
A55: ORD10054 | B55: C008 | C55: P102 | D55: 27/07/2025 | E55: 05/08/2025 | F55: Kavya Nair | G55: Female | H55: 04/04/1975 | I55: Jaipur | J55: North | K55: Electronics | L55: Mouse | M55: 3 | N55: 700 | O55: 0 | P55: 2100 | Q55: 3 | R55: Card | S55: Karan | T55: kavya.nair@company.com | U55: 9743295580 | V55: Cancelled | W55: =PROPER(TRIM(F55)) -> Kavya Nair | X55: =IFERROR(DATEDIF(H55, TODAY(), "y"), " ") -> 51 | Y55: =IFERROR(DATEDIF(D55, E55, "D"), " ") -> 9 | Z55: {=_xlfn.IFS(Y55<=5, "On time", AND(Y55>5, Y55<>" "), "Delayed", Y55=" ", "pending" )} -> #NAME?
A56: ORD10055 | B56: C003 | C56: P301 | D56: 21/02/2025 | E56: 26/02/2025 | F56: RoHit Singh | G56: Male | H56: 11/12/1976 | I56: Ahmedabad | J56: West | K56: Stationery | L56: Notebook | M56: 19 | N56: 60 | O56: 15 | P56: 969 | Q56: 4 | R56: Card | S56: Rahul | T56: rohit.singh@company.com | U56: 9822926495 | V56: Cancelled | W56: =PROPER(TRIM(F56)) -> Rohit Singh | X56: =IFERROR(DATEDIF(H56, TODAY(), "y"), " ") -> 49 | Y56: =IFERROR(DATEDIF(D56, E56, "D"), " ") -> 5 | Z56: {=_xlfn.IFS(Y56<=5, "On time", AND(Y56>5, Y56<>" "), "Delayed", Y56=" ", "pending" )} -> #NAME?
A57: ORD10056 | B57: C001 | C57: P301 | D57: 10/08/2025 | E57: 11/08/2025 | F57: Amit Sharma | G57: Male | H57: 03/12/1979 | I57: Jaipur | J57: North | K57: Stationery | L57: Notebook | M57: 9 | N57: 60 | O57: 20 | P57: 432 | Q57: 1 | R57: NetBanking | S57: Neha | T57: amit.sharma@company.com | U57: 9518298190 | V57: Pending | W57: =PROPER(TRIM(F57)) -> Amit Sharma | X57: =IFERROR(DATEDIF(H57, TODAY(), "y"), " ") -> 46 | Y57: =IFERROR(DATEDIF(D57, E57, "D"), " ") -> 1 | Z57: {=_xlfn.IFS(Y57<=5, "On time", AND(Y57>5, Y57<>" "), "Delayed", Y57=" ", "pending" )} -> #NAME?
A58: ORD10057 | B58: C001 | C58: P102 | D58: 24/03/2026 | E58: 30/03/2026 | F58: Amit Sharma | G58: Male | H58: 27/12/1978 | I58: Bengaluru | J58: South | K58: Electronics | L58: Mouse | M58: 6 | N58: 700 | O58: 0 | P58: 4200 | Q58: 4 | R58: UPI | S58: Rahul | T58: amit.sharmcompany.com | U58: 9366223547 | V58: Cancelled | W58: =PROPER(TRIM(F58)) -> Amit Sharma | X58: =IFERROR(DATEDIF(H58, TODAY(), "y"), " ") -> 47 | Y58: =IFERROR(DATEDIF(D58, E58, "D"), " ") -> 6 | Z58: {=_xlfn.IFS(Y58<=5, "On time", AND(Y58>5, Y58<>" "), "Delayed", Y58=" ", "pending" )} -> #NAME?
A59: ORD10058 | B59: C003 | C59: P303 | D59: 13/03/2026 | E59: 19/03/2026 | F59: Rohit Singh | G59: Male | H59: 15/04/1975 | I59: Delhi | J59: North | K59: Stationery | L59: Marker | M59: 18 | N59: 45 | O59: 5 | P59: 769.5 | Q59: 1 | R59: Card | S59: Aisha | T59: rohit.singh@company.com | U59: 9701988524 | V59: Pending | W59: =PROPER(TRIM(F59)) -> Rohit Singh | X59: =IFERROR(DATEDIF(H59, TODAY(), "y"), " ") -> 51 | Y59: =IFERROR(DATEDIF(D59, E59, "D"), " ") -> 6 | Z59: {=_xlfn.IFS(Y59<=5, "On time", AND(Y59>5, Y59<>" "), "Delayed", Y59=" ", "pending" )} -> #NAME?
A60: ORD10059 | B60: C007 | C60: P302 | D60: 15/06/2025 | E60: 26/06/2025 | F60: Arjun Rao | G60: Male | H60: 19/12/1988 | I60: Jaipur | J60: North | K60: Stationery | L60: Pen | M60: 8 | N60: 20 | O60: 5 | P60: 152 | Q60: 1 | R60: Card | S60: Ritika | T60: arjun.rao@company.com | U60: 9836327649 | V60: completed | W60: =PROPER(TRIM(F60)) -> Arjun Rao | X60: =IFERROR(DATEDIF(H60, TODAY(), "y"), " ") -> 37 | Y60: =IFERROR(DATEDIF(D60, E60, "D"), " ") -> 11 | Z60: {=_xlfn.IFS(Y60<=5, "On time", AND(Y60>5, Y60<>" "), "Delayed", Y60=" ", "pending" )} -> #NAME?
A61: ORD10060 | B61: C005 | C61: P102 | D61: 05/03/2025 | E61: 06/03/2025 | F61: Vikas Mehta | G61: Male | H61: 07/03/1979 | I61: Jaipur | J61: North | K61: Electronics | L61: Mouse | M61: 8 | N61: 700 | O61: 10 | P61: 5040 | Q61: 1 | R61: NetBanking | S61: Aisha | T61: Vikas.mehta@company.com | U61: 9261800516 | V61: Cancelled | W61: =PROPER(TRIM(F61)) -> Vikas Mehta | X61: =IFERROR(DATEDIF(H61, TODAY(), "y"), " ") -> 47 | Y61: =IFERROR(DATEDIF(D61, E61, "D"), " ") -> 1 | Z61: {=_xlfn.IFS(Y61<=5, "On time", AND(Y61>5, Y61<>" "), "Delayed", Y61=" ", "pending" )} -> #NAME?
A62: ORD10061 | B62: C008 | C62: P302 | D62: 09/04/2026 | E62: 19/04/2026 | F62: Kavya Nair | G62: Female | H62: 17/12/2003 | I62: Delhi | J62: North | K62: Stationery | L62: Pen | M62: 7 | N62: 20 | O62: 15 | P62: 119 | Q62: 5 | R62: Card | S62: Rahul | T62: kavya.nair@company.com | U62: 9950802015 | V62: Completed | W62: =PROPER(TRIM(F62)) -> Kavya Nair | X62: =IFERROR(DATEDIF(H62, TODAY(), "y"), " ") -> 22 | Y62: =IFERROR(DATEDIF(D62, E62, "D"), " ") -> 10 | Z62: {=_xlfn.IFS(Y62<=5, "On time", AND(Y62>5, Y62<>" "), "Delayed", Y62=" ", "pending" )} -> #NAME?
... A74: ORD10073 | B74: C008 | C74: P103 | D74: 13/12/2025 | E74: 23/12/2025 | F74: Kavya Nair | G74: Female | H74: 22/09/1981 | I74: Jaipur | J74: North | K74: Electronics | L74: Keyboard | M74: 1 | N74: 1200 | O74: 5 | P74: 1140 | Q74: 3 | R74: UPI | S74: Aisha | T74: kavya.nair@company.com | U74: 9808988530 | V74: Cancelled | W74: =PROPER(TRIM(F74)) -> Kavya Nair | X74: =IFERROR(DATEDIF(H74, TODAY(), "y"), " ") -> 44 | Y74: =IFERROR(DATEDIF(D74, E74, "D"), " ") -> 10 | Z74: {=_xlfn.IFS(Y74<=5, "On time", AND(Y74>5, Y74<>" "), "Delayed", Y74=" ", "pending" )} -> #NAME?
A75: ORD10074 | B75: C010 | C75: P202 | D75: 04/02/2026 | E75: 16/02/2026 | F75: Pooja Shah | G75: Female | H75: 20/06/1980 | J75: South | K75: Home Appliances | L75: Iron | M75: 1 | N75: 2200 | O75: 15 | P75: 1870 | Q75: 4 | R75: Card | S75: Aisha | T75: pooja.shah@company.com | U75: 9286410494 | V75: Completed | W75: =PROPER(TRIM(F75)) -> Pooja Shah | X75: =IFERROR(DATEDIF(H75, TODAY(), "y"), " ") -> 46 | Y75: =IFERROR(DATEDIF(D75, E75, "D"), " ") -> 12 | Z75: {=_xlfn.IFS(Y75<=5, "On time", AND(Y75>5, Y75<>" "), "Delayed", Y75=" ", "pending" )} -> #NAME?
A76: ORD10075 | B76: C003 | C76: P103 | D76: 26/01/2026 | E76: 28/01/2026 | F76: Rohit Singh | G76: Male | H76: 02/11/1982 | I76: Pune | J76: West | K76: Electronics | L76: Keyboard | M76: 3 | N76: 1200 | O76: 10 | P76: 3240 | Q76: 5 | R76: Cash | S76: Rahul | T76: rohit.singh@company.com | U76: 9311555196 | V76: Completed | W76: =PROPER(TRIM(F76)) -> Rohit Singh | X76: =IFERROR(DATEDIF(H76, TODAY(), "y"), " ") -> 43 | Y76: =IFERROR(DATEDIF(D76, E76, "D"), " ") -> 2 | Z76: {=_xlfn.IFS(Y76<=5, "On time", AND(Y76>5, Y76<>" "), "Delayed", Y76=" ", "pending" )} -> #NAME?
A77: ORD10076 | B77: C008 | C77: P201 | D77: 27/06/2025 | E77: 07/07/2025 | F77: Kavya Nair | G77: Female | H77: 10/01/1980 | I77: Bengaluru | J77: South | K77: Home Appliances | L77: Mixer | M77: 10 | N77: 3500 | O77: 20 | P77: 28000 | Q77: 5 | R77: Card | S77: Ritika | T77: kavya.nair@company.com | U77: 9101810266 | V77: Completed | W77: =PROPER(TRIM(F77)) -> Kavya Nair | X77: =IFERROR(DATEDIF(H77, TODAY(), "y"), " ") -> 46 | Y77: =IFERROR(DATEDIF(D77, E77, "D"), " ") -> 10 | Z77: {=_xlfn.IFS(Y77<=5, "On time", AND(Y77>5, Y77<>" "), "Delayed", Y77=" ", "pending" )} -> #NAME?
A78: ORD10077 | B78: C007 | C78: P102 | D78: 17/03/2026 | E78: 19/03/2026 | F78: Arjun Rao | G78: Male | H78: 27/04/1981 | I78: Delhi | J78: North | K78: Electronics | L78: Mouse | M78: 18 | N78: 700 | O78: 5 | P78: 11970 | Q78: 3 | R78: Card | S78: Neha | T78: arjun.rao@company.com | U78: 9464556593 | V78: Cancelled | W78: =PROPER(TRIM(F78)) -> Arjun Rao | X78: =IFERROR(DATEDIF(H78, TODAY(), "y"), " ") -> 45 | Y78: =IFERROR(DATEDIF(D78, E78, "D"), " ") -> 2 | Z78: {=_xlfn.IFS(Y78<=5, "On time", AND(Y78>5, Y78<>" "), "Delayed", Y78=" ", "pending" )} -> #NAME?
A79: ORD10078 | B79: C005 | C79: P102 | D79: 09/06/2025 | E79: 18/06/2025 | F79: Vikas Mehta | G79: Male | H79: 12/03/1985 | I79: Bengaluru | J79: South | K79: Electronics | L79: Mouse | M79: 12 | N79: 700 | O79: 15 | P79: 7140 | Q79: 2 | R79: UPI | S79: Rahul | T79: vikas.mehta@company.com | U79: 9338278358 | V79: Completed | W79: =PROPER(TRIM(F79)) -> Vikas Mehta | X79: =IFERROR(DATEDIF(H79, TODAY(), "y"), " ") -> 41 | Y79: =IFERROR(DATEDIF(D79, E79, "D"), " ") -> 9 | Z79: {=_xlfn.IFS(Y79<=5, "On time", AND(Y79>5, Y79<>" "), "Delayed", Y79=" ", "pending" )} -> #NAME?
A80: ORD10079 | B80: C009 | C80: P103 | D80: 15/11/2025 | E80: 16/11/2025 | F80: Mohit Verma | G80: Male | H80: 15/03/1999 | I80: Mumbai | J80: West | K80: Electronics | L80: Keyboard | M80: 8 | N80: 1200 | O80: 0 | P80: 9600 | Q80: 4 | R80: Card | S80: Rahul | T80: mohit.verma@company.com | U80: 9621410770 | V80: Pending | W80: =PROPER(TRIM(F80)) -> Mohit Verma | X80: =IFERROR(DATEDIF(H80, TODAY(), "y"), " ") -> 27 | Y80: =IFERROR(DATEDIF(D80, E80, "D"), " ") -> 1 | Z80: {=_xlfn.IFS(Y80<=5, "On time", AND(Y80>5, Y80<>" "), "Delayed", Y80=" ", "pending" )} -> #NAME?
A81: ORD10080 | B81: C003 | C81: P301 | D81: 06/11/2025 | E81: 10/11/2025 | F81: Rohit Singh | G81: Male | H81: 07/07/1983 | I81: Pune | J81: West | K81: Stationery | L81: Notebook | M81: 2 | N81: 60 | O81: 0 | P81: 120 | Q81: 2 | R81: UPI | S81: Rahul | T81: rohit.singh@company.com | U81: 9981333189 | V81: Completed | W81: =PROPER(TRIM(F81)) -> Rohit Singh | X81: =IFERROR(DATEDIF(H81, TODAY(), "y"), " ") -> 43 | Y81: =IFERROR(DATEDIF(D81, E81, "D"), " ") -> 4 | Z81: {=_xlfn.IFS(Y81<=5, "On time", AND(Y81>5, Y81<>" "), "Delayed", Y81=" ", "pending" )} -> #NAME?
A82: ORD10081 | B82: C001 | C82: P303 | D82: 01/01/2025 | E82: 07/01/2025 | F82: Amit Sharma | G82: Male | H82: 06/03/1989 | I82: Pune | J82: West | K82: Stationery | L82: Marker | M82: 10 | N82: 45 | O82: 15 | P82: 382.5 | Q82: 3 | R82: NetBanking | S82: Ritika | T82: amit.sharma@company.com | U82: 9723450355 | V82: Cancelled | W82: =PROPER(TRIM(F82)) -> Amit Sharma | X82: =IFERROR(DATEDIF(H82, TODAY(), "y"), " ") -> 37 | Y82: =IFERROR(DATEDIF(D82, E82, "D"), " ") -> 6 | Z82: {=_xlfn.IFS(Y82<=5, "On time", AND(Y82>5, Y82<>" "), "Delayed", Y82=" ", "pending" )} -> #NAME?
A83: ORD10082 | B83: C005 | C83: P201 | D83: 25/04/2026 | E83: 03/05/2026 | F83: Vikas Mehta | G83: Male | H83: 20/06/1982 | I83: Kolkata | J83: East | K83: Home Appliances | L83: Mixer | M83: 12 | N83: 3500 | O83: 5 | P83: 39900 | Q83: 3 | R83: NetBanking | S83: Aisha | T83: vikas.mehta@company.com | U83: 9886243907 | V83: Pending | W83: =PROPER(TRIM(F83)) -> Vikas Mehta | X83: =IFERROR(DATEDIF(H83, TODAY(), "y"), " ") -> 44 | Y83: =IFERROR(DATEDIF(D83, E83, "D"), " ") -> 8 | Z83: {=_xlfn.IFS(Y83<=5, "On time", AND(Y83>5, Y83<>" "), "Delayed", Y83=" ", "pending" )} -> #NAME?
A84: ORD10083 | B84: C003 | C84: P301 | D84: 19/09/2025 | E84: 27/09/2025 | F84: Rohit Singh | G84: Male | H84: 23/06/2001 | I84: Mumbai | J84: West | K84: Stationery | L84: Notebook | M84: 2 | N84: 60 | O84: 15 | P84: 102 | Q84: 1 | R84: UPI | S84: Neha | T84: rohit.singh@company.com | U84: 9473931904 | V84: Completed | W84: =PROPER(TRIM(F84)) -> Rohit Singh | X84: =IFERROR(DATEDIF(H84, TODAY(), "y"), " ") -> 25 | Y84: =IFERROR(DATEDIF(D84, E84, "D"), " ") -> 8 | Z84: {=_xlfn.IFS(Y84<=5, "On time", AND(Y84>5, Y84<>" "), "Delayed", Y84=" ", "pending" )} -> #NAME?
A85: ORD10084 | B85: C003 | C85: P103 | D85: 18/03/2025 | E85: 21/03/2025 | F85: Rohit Singh | G85: Male | H85: 19/07/1983 | I85: Hyderabad | J85: South | K85: Electronics | L85: Keyboard | M85: 18 | N85: 1200 | O85: 15 | P85: 18360 | Q85: 3 | R85: Card | S85: Neha | T85: rohit.singh@company.com | U85: 9287159610 | V85: Pending | W85: =PROPER(TRIM(F85)) -> Rohit Singh | X85: =IFERROR(DATEDIF(H85, TODAY(), "y"), " ") -> 43 | Y85: =IFERROR(DATEDIF(D85, E85, "D"), " ") -> 3 | Z85: {=_xlfn.IFS(Y85<=5, "On time", AND(Y85>5, Y85<>" "), "Delayed", Y85=" ", "pending" )} -> #NAME?
A86: ORD10085 | B86: C008 | C86: P104 | D86: 30/10/2025 | E86: 31/10/2025 | F86: Kavya Nair | G86: Female | H86: 24/03/1993 | I86: Mumbai | J86: West | K86: Electronics | L86: Monitor | M86: 18 | N86: 12000 | O86: 15 | P86: 183600 | Q86: 2 | R86: Cash | S86: Rahul | T86: kavya.nair@company.com | U86: 9876513858 | V86: Completed | W86: =PROPER(TRIM(F86)) -> Kavya Nair | X86: =IFERROR(DATEDIF(H86, TODAY(), "y"), " ") -> 33 | Y86: =IFERROR(DATEDIF(D86, E86, "D"), " ") -> 1 | Z86: {=_xlfn.IFS(Y86<=5, "On time", AND(Y86>5, Y86<>" "), "Delayed", Y86=" ", "pending" )} -> #NAME?
A87: ORD10086 | B87: C007 | C87: P302 | D87: 31/10/2025 | E87: 11/11/2025 | F87: Arjun Rao | G87: Male | H87: 10/05/1995 | I87: Ahmedabad | J87: West | K87: Stationery | L87: Pen | M87: 7 | N87: 20 | O87: 0 | P87: 140 | Q87: 2 | R87: Card | S87: Ritika | T87: arjun.rao@company.com | U87: 9237400853 | V87: Cancelled | W87: =PROPER(TRIM(F87)) -> Arjun Rao | X87: =IFERROR(DATEDIF(H87, TODAY(), "y"), " ") -> 31 | Y87: =IFERROR(DATEDIF(D87, E87, "D"), " ") -> 11 | Z87: {=_xlfn.IFS(Y87<=5, "On time", AND(Y87>5, Y87<>" "), "Delayed", Y87=" ", "pending" )} -> #NAME?
... A119: ORD10118 | B119: C001 | C119: P303 | D119: 31/05/2025 | E119: 11/06/2025 | F119: Amit Sharma | G119: Male | H119: 07/09/1995 | I119: Pune | J119: West | K119: Stationery | L119: Marker | M119: 16 | N119: 45 | O119: 0 | P119: 720 | Q119: 1 | R119: NetBanking | S119: Aisha | T119: amit.sharma@company.com | U119: 9807154421 | V119: Completed | W119: =PROPER(TRIM(F119)) -> Amit Sharma | X119: =IFERROR(DATEDIF(H119, TODAY(), "y"), " ") -> 30 | Y119: =IFERROR(DATEDIF(D119, E119, "D"), " ") -> 11 | Z119: {=_xlfn.IFS(Y119<=5, "On time", AND(Y119>5, Y119<>" "), "Delayed", Y119=" ", "pending" )} -> #NAME?
A120: ORD10119 | B120: C009 | C120: P103 | D120: 30/05/2025 | E120: 02/06/2025 | F120: Mohit Verma | G120: Male | H120: 08/03/1988 | I120: Ahmedabad | J120: West | K120: Electronics | L120: Keyboard | M120: Ten | N120: 1200 | O120: 15 | P120: 7140 | Q120: 4 | R120: UPI | S120: Karan | T120: mohit.verma@company.com | U120: 9919834000 | V120: Pending | W120: =PROPER(TRIM(F120)) -> Mohit Verma | X120: =IFERROR(DATEDIF(H120, TODAY(), "y"), " ") -> 38 | Y120: =IFERROR(DATEDIF(D120, E120, "D"), " ") -> 3 | Z120: {=_xlfn.IFS(Y120<=5, "On time", AND(Y120>5, Y120<>" "), "Delayed", Y120=" ", "pending" )} -> #NAME?
A121: ORD10120 | B121: C002 | C121: P104 | D121: 19/08/2025 | E121: 30/08/2025 | F121: Priya Patel | G121: Female | H121: 07/07/1989 | I121: Jaipur | J121: North | K121: Electronics | L121: Monitor | M121: 14 | N121: 12000 | O121: 15 | P121: 142800 | Q121: 2 | R121: NetBanking | S121: Aisha | T121: priya.patel@company.com | U121: 9739798818 | V121: Pending | W121: =PROPER(TRIM(F121)) -> Priya Patel | X121: =IFERROR(DATEDIF(H121, TODAY(), "y"), " ") -> 37 | Y121: =IFERROR(DATEDIF(D121, E121, "D"), " ") -> 11 | Z121: {=_xlfn.IFS(Y121<=5, "On time", AND(Y121>5, Y121<>" "), "Delayed", Y121=" ", "pending" )} -> #NAME?
A122: ORD10121 | B122: C003 | C122: P203 | D122: 14/12/2025 | E122: 16/12/2025 | F122: Rohit Singh | G122: Male | H122: 11/11/1993 | I122: Pune | J122: West | K122: Home Appliances | L122: Microwave | M122: 8 | N122: 8500 | O122: 20 | P122: 54400 | Q122: 3 | R122: Card | S122: Rahul | T122: rohit.singh@company.com | U122: 9208625306 | V122: Completed | W122: =PROPER(TRIM(F122)) -> Rohit Singh | X122: =IFERROR(DATEDIF(H122, TODAY(), "y"), " ") -> 32 | Y122: =IFERROR(DATEDIF(D122, E122, "D"), " ") -> 2 | Z122: {=_xlfn.IFS(Y122<=5, "On time", AND(Y122>5, Y122<>" "), "Delayed", Y122=" ", "pending" )} -> #NAME?
A123: ORD10122 | B123: C007 | C123: P303 | D123: 31/01/2026 | E123: 10/02/2026 | F123: Arjun Rao | G123: Male | H123: 01/02/2000 | I123: Bengaluru | J123: South | K123: Stationery | L123: Marker | M123: 3 | N123: 45 | O123: 0 | P123: 135 | Q123: 4 | R123: UPI | S123: Aisha | T123: arjun.rao@company.com | U123: 9970178536 | V123: Cancelled | W123: =PROPER(TRIM(F123)) -> Arjun Rao | X123: =IFERROR(DATEDIF(H123, TODAY(), "y"), " ") -> 26 | Y123: =IFERROR(DATEDIF(D123, E123, "D"), " ") -> 10 | Z123: {=_xlfn.IFS(Y123<=5, "On time", AND(Y123>5, Y123<>" "), "Delayed", Y123=" ", "pending" )} -> #NAME?
A124: ORD10123 | B124: C001 | C124: P102 | D124: 03/01/2026 | E124: 04/01/2026 | F124: Amit Sharma | G124: Male | H124: 22/06/1986 | I124: Jaipur | J124: North | K124: Electronics | L124: Mouse | M124: 13 | N124: 700 | O124: 5 | P124: 8645 | Q124: 3 | R124: Card | S124: Neha | T124: amit.sharma@company.com | U124: 9633745195 | V124: Pending | W124: =PROPER(TRIM(F124)) -> Amit Sharma | X124: =IFERROR(DATEDIF(H124, TODAY(), "y"), " ") -> 40 | Y124: =IFERROR(DATEDIF(D124, E124, "D"), " ") -> 1 | Z124: {=_xlfn.IFS(Y124<=5, "On time", AND(Y124>5, Y124<>" "), "Delayed", Y124=" ", "pending" )} -> #NAME?
A125: ORD10124 | B125: C004 | C125: P103 | D125: 20/10/2025 | E125: 26/10/2025 | F125: Anita Gupta | G125: Female | H125: 16/02/1986 | I125: Mumbai | J125: West | K125: Electronics | L125: Keyboard | M125: 14 | N125: 1200 | O125: 20 | P125: 13440 | Q125: 5 | R125: NetBanking | S125: Aisha | T125: anita.gupta@company.com | U125: 9922102053 | V125: Completed | W125: =PROPER(TRIM(F125)) -> Anita Gupta | X125: =IFERROR(DATEDIF(H125, TODAY(), "y"), " ") -> 40 | Y125: =IFERROR(DATEDIF(D125, E125, "D"), " ") -> 6 | Z125: {=_xlfn.IFS(Y125<=5, "On time", AND(Y125>5, Y125<>" "), "Delayed", Y125=" ", "pending" )} -> #NAME?
A126: ORD10125 | B126: C002 | C126: P303 | D126: 11/05/2025 | E126: 21/05/2025 | F126: Priya Patel | G126: Female | H126: 18/09/1991 | I126: Delhi | J126: North | K126: Stationery | L126: Marker | M126: 2 | N126: 45 | O126: 5 | P126: 85.5 | Q126: 3 | R126: UPI | S126: Ritika | T126: priya.patel@company.com | U126: 9135963930 | V126: Cancelled | W126: =PROPER(TRIM(F126)) -> Priya Patel | X126: =IFERROR(DATEDIF(H126, TODAY(), "y"), " ") -> 34 | Y126: =IFERROR(DATEDIF(D126, E126, "D"), " ") -> 10 | Z126: {=_xlfn.IFS(Y126<=5, "On time", AND(Y126>5, Y126<>" "), "Delayed", Y126=" ", "pending" )} -> #NAME?
A127: ORD10126 | B127: C004 | C127: P103 | D127: 02/01/2026 | E127: 06/01/2026 | F127: Anita Gupta | G127: Female | H127: 04/01/1981 | I127: Bengaluru | J127: South | K127: Electronics | L127: Keyboard | M127: 2 | N127: 1200 | O127: 20 | P127: 1920 | Q127: 3 | R127: Card | S127: Neha | T127: anita.gupta@company.com | U127: 9429405275 | V127: Completed | W127: =PROPER(TRIM(F127)) -> Anita Gupta | X127: =IFERROR(DATEDIF(H127, TODAY(), "y"), " ") -> 45 | Y127: =IFERROR(DATEDIF(D127, E127, "D"), " ") -> 4 | Z127: {=_xlfn.IFS(Y127<=5, "On time", AND(Y127>5, Y127<>" "), "Delayed", Y127=" ", "pending" )} -> #NAME?
A128: ORD10127 | B128: C003 | C128: P101 | D128: 20/04/2026 | E128: 26/04/2026 | F128: Rohit Singh | G128: Male | H128: 12/10/2004 | I128: Bengaluru | J128: South | K128: Electronics | L128: Laptop | M128: 10 | N128: 55000 | O128: 5 | P128: 522500 | Q128: 5 | R128: UPI | S128: Aisha | T128: rohit.singh@company.com | U128: 9521757571 | V128: Pending | W128: =PROPER(TRIM(F128)) -> Rohit Singh | X128: =IFERROR(DATEDIF(H128, TODAY(), "y"), " ") -> 21 | Y128: =IFERROR(DATEDIF(D128, E128, "D"), " ") -> 6 | Z128: {=_xlfn.IFS(Y128<=5, "On time", AND(Y128>5, Y128<>" "), "Delayed", Y128=" ", "pending" )} -> #NAME?
A129: ORD10128 | B129: C006 | C129: P201 | D129: 04/08/2025 | E129: 05/08/2025 | F129: Sneha Joshi | G129: Female | H129: 25/03/1984 | I129: Jaipur | J129: North | K129: Home Appliances | L129: Mixer | M129: 15 | N129: 3500 | O129: 10 | P129: 47250 | Q129: 3 | R129: NetBanking | S129: Neha | T129: sneha.joshi@company.com | U129: 9467375455 | V129: Completed | W129: =PROPER(TRIM(F129)) -> Sneha Joshi | X129: =IFERROR(DATEDIF(H129, TODAY(), "y"), " ") -> 42 | Y129: =IFERROR(DATEDIF(D129, E129, "D"), " ") -> 1 | Z129: {=_xlfn.IFS(Y129<=5, "On time", AND(Y129>5, Y129<>" "), "Delayed", Y129=" ", "pending" )} -> #NAME?
A130: ORD10129 | B130: C002 | C130: P202 | D130: 13/08/2025 | E130: 18/08/2025 | F130: Priya Patel | G130: Female | H130: 09/09/1982 | I130: Bengaluru | J130: South | K130: Home Appliances | L130: Iron | M130: 10 | N130: 2200 | O130: 15 | P130: 18700 | Q130: 4 | R130: Card | S130: Rahul | T130: priya.patel@company.com | U130: 9838809695 | V130: Pending | W130: =PROPER(TRIM(F130)) -> Priya Patel | X130: =IFERROR(DATEDIF(H130, TODAY(), "y"), " ") -> 43 | Y130: =IFERROR(DATEDIF(D130, E130, "D"), " ") -> 5 | Z130: {=_xlfn.IFS(Y130<=5, "On time", AND(Y130>5, Y130<>" "), "Delayed", Y130=" ", "pending" )} -> #NAME?
A131: ORD10130 | B131: C006 | C131: P201 | D131: 16/06/2025 | E131: 24/06/2025 | F131: Sneha Joshi | G131: Female | H131: 15/02/1993 | I131: Pune | J131: West | K131: Home Appliances | L131: Mixer | M131: 11 | N131: 3500 | O131: 5 | P131: 36575 | Q131: 5 | R131: Cash | S131: Ritika | T131: sneha.joshi@company.com | U131: 9296609782 | V131: Cancelled | W131: =PROPER(TRIM(F131)) -> Sneha Joshi | X131: =IFERROR(DATEDIF(H131, TODAY(), "y"), " ") -> 33 | Y131: =IFERROR(DATEDIF(D131, E131, "D"), " ") -> 8 | Z131: {=_xlfn.IFS(Y131<=5, "On time", AND(Y131>5, Y131<>" "), "Delayed", Y131=" ", "pending" )} -> #NAME?
A132: ORD10131 | B132: C004 | C132: P103 | D132: 27/04/2026 | E132: 30/04/2026 | F132: Anita Gupta | G132: Female | H132: 08/04/2003 | I132: Bengaluru | J132: South | K132: Electronics | L132: Keyboard | M132: 14 | N132: 1200 | O132: 0 | P132: 16800 | Q132: 5 | R132: Cash | S132: Rahul | T132: anita.gupta@company.com | U132: 9848259992 | V132: Cancelled | W132: =PROPER(TRIM(F132)) -> Anita Gupta | X132: =IFERROR(DATEDIF(H132, TODAY(), "y"), " ") -> 23 | Y132: =IFERROR(DATEDIF(D132, E132, "D"), " ") -> 3 | Z132: {=_xlfn.IFS(Y132<=5, "On time", AND(Y132>5, Y132<>" "), "Delayed", Y132=" ", "pending" )} -> #NAME?
... A299: ORD10298 | B299: C003 | C299: P101 | D299: 13/01/2025 | E299: 16/01/2025 | F299: Rohit Singh | G299: Male | H299: 03/01/2004 | I299: Hyderabad | J299: South | K299: Electronics | L299: Laptop | M299: 11 | N299: 55000 | O299: 5 | P299: 574750 | Q299: 1 | R299: UPI | S299: Ritika | T299: rohit.singh@company.com | U299: 9482699727 | V299: Cancelled | W299: =PROPER(TRIM(F299)) -> Rohit Singh | X299: =IFERROR(DATEDIF(H299, TODAY(), "y"), " ") -> 22 | Y299: =IFERROR(DATEDIF(D299, E299, "D"), " ") -> 3 | Z299: {=_xlfn.IFS(Y299<=5, "On time", AND(Y299>5, Y299<>" "), "Delayed", Y299=" ", "pending" )} -> #NAME?
A300: ORD10299 | B300: C007 | C300: P201 | D300: 05/10/2025 | E300: 17/10/2025 | F300: Arjun Rao | G300: Male | H300: 02/05/1992 | I300: Jaipur | J300: North | K300: Home Appliances | L300: Mixer | M300: 12 | N300: 3500 | O300: 0 | P300: 42000 | Q300: 2 | R300: NetBanking | T300: arjun.rao@company.com | U300: 9332473934 | V300: Pending | W300: =PROPER(TRIM(F300)) -> Arjun Rao | X300: =IFERROR(DATEDIF(H300, TODAY(), "y"), " ") -> 34 | Y300: =IFERROR(DATEDIF(D300, E300, "D"), " ") -> 12 | Z300: {=_xlfn.IFS(Y300<=5, "On time", AND(Y300>5, Y300<>" "), "Delayed", Y300=" ", "pending" )} -> #NAME?
A301: ORD10300 | B301: C009 | C301: P303 | D301: 25/02/2026 | E301: 08/03/2026 | F301: Mohit Verma | G301: Male | H301: 26/01/2003 | I301: Hyderabad | J301: South | K301: Stationery | L301: Marker | M301: 15 | N301: 45 | O301: 10 | P301: 607.5 | Q301: 2 | R301: Cash | S301: Karan | T301: mohit.verma@company.com | U301: 9647657382 | V301: Pending | W301: =PROPER(TRIM(F301)) -> Mohit Verma | X301: =IFERROR(DATEDIF(H301, TODAY(), "y"), " ") -> 23 | Y301: =IFERROR(DATEDIF(D301, E301, "D"), " ") -> 11 | Z301: {=_xlfn.IFS(Y301<=5, "On time", AND(Y301>5, Y301<>" "), "Delayed", Y301=" ", "pending" )} -> #NAME?
A302: ORD10301 | B302: C001 | C302: P303 | D302: 16/05/2025 | E302: 26/05/2025 | F302: Amit Sharma | G302: Male | H302: 20/05/1987 | I302: Bengaluru | J302: South | K302: Stationery | L302: Marker | M302: 13 | N302: 45 | O302: 0 | P302: 585 | Q302: 5 | R302: NetBanking | S302: Rahul | T302: amit.sharma@company.com | U302: 9736797776 | V302: Pending | W302: =PROPER(TRIM(F302)) -> Amit Sharma | X302: =IFERROR(DATEDIF(H302, TODAY(), "y"), " ") -> 39 | Y302: =IFERROR(DATEDIF(D302, E302, "D"), " ") -> 10 | Z302: {=_xlfn.IFS(Y302<=5, "On time", AND(Y302>5, Y302<>" "), "Delayed", Y302=" ", "pending" )} -> #NAME?
A303: ORD10302 | B303: C003 | C303: P101 | D303: 02/01/2026 | E303: 05/01/2026 | F303: Rohit Singh | G303: Male | H303: 07/09/1975 | I303: Bengaluru | J303: South | K303: Electronics | L303: Laptop | M303: 8 | N303: 55000 | O303: 0 | P303: 440000 | Q303: 2 | R303: UPI | S303: Karan | T303: rohit.singh@company.com | U303: 9745773533 | V303: Cancelled | W303: =PROPER(TRIM(F303)) -> Rohit Singh | X303: =IFERROR(DATEDIF(H303, TODAY(), "y"), " ") -> 50 | Y303: =IFERROR(DATEDIF(D303, E303, "D"), " ") -> 3 | Z303: {=_xlfn.IFS(Y303<=5, "On time", AND(Y303>5, Y303<>" "), "Delayed", Y303=" ", "pending" )} -> #NAME?
A304: ORD10303 | B304: C006 | C304: P101 | D304: 23/07/2025 | E304: 27/07/2025 | F304: Sneha Joshi | G304: Female | H304: 10/08/1980 | I304: Delhi | J304: North | K304: Electronics | L304: Laptop | M304: 4 | N304: 55000 | O304: 20 | P304: 176000 | Q304: 5 | R304: Cash | S304: Rahul | T304: sneha.joshi@company.com | U304: 9246715757 | V304: Pending | W304: =PROPER(TRIM(F304)) -> Sneha Joshi | X304: =IFERROR(DATEDIF(H304, TODAY(), "y"), " ") -> 45 | Y304: =IFERROR(DATEDIF(D304, E304, "D"), " ") -> 4 | Z304: {=_xlfn.IFS(Y304<=5, "On time", AND(Y304>5, Y304<>" "), "Delayed", Y304=" ", "pending" )} -> #NAME?
A305: ORD10304 | B305: C008 | C305: P201 | D305: 23/04/2026 | E305: 26/04/2026 | F305: Kavya Nair | G305: Female | H305: 07/04/1989 | I305: Ahmedabad | J305: West | K305: Home Appliances | L305: Mixer | M305: 19 | N305: 3500 | O305: 5 | P305: 63175 | Q305: 1 | R305: Card | S305: Neha | T305: kavya.nair@company.com | U305: 9904065774 | V305: Completed | W305: =PROPER(TRIM(F305)) -> Kavya Nair | X305: =IFERROR(DATEDIF(H305, TODAY(), "y"), " ") -> 37 | Y305: =IFERROR(DATEDIF(D305, E305, "D"), " ") -> 3 | Z305: {=_xlfn.IFS(Y305<=5, "On time", AND(Y305>5, Y305<>" "), "Delayed", Y305=" ", "pending" )} -> #NAME?
A306: ORD10305 | B306: C005 | C306: P103 | D306: 02/03/2025 | E306: 06/03/2025 | F306: Vikas Mehta | G306: Male | H306: 20/08/1998 | I306: Jaipur | J306: North | K306: Electronics | L306: Keyboard | M306: 17 | N306: 1200 | O306: 15 | P306: 17340 | Q306: 2 | R306: NetBanking | S306: Rahul | T306: vikas.mehta@company.com | U306: 9652985385 | V306: Completed | W306: =PROPER(TRIM(F306)) -> Vikas Mehta | X306: =IFERROR(DATEDIF(H306, TODAY(), "y"), " ") -> 27 | Y306: =IFERROR(DATEDIF(D306, E306, "D"), " ") -> 4 | Z306: {=_xlfn.IFS(Y306<=5, "On time", AND(Y306>5, Y306<>" "), "Delayed", Y306=" ", "pending" )} -> #NAME?
A307: ORD10306 | B307: C008 | C307: P202 | D307: 09/02/2026 | E307: 17/02/2026 | F307: Kavya Nair | G307: Female | H307: 03/04/2001 | I307: Hyderabad | J307: South | K307: Home Appliances | L307: Iron | M307: 8 | N307: 2200 | O307: 5 | P307: 16720 | Q307: 3 | R307: Card | S307: Neha | T307: kavya.nair@company.com | U307: 9427001508 | V307: Pending | W307: =PROPER(TRIM(F307)) -> Kavya Nair | X307: =IFERROR(DATEDIF(H307, TODAY(), "y"), " ") -> 25 | Y307: =IFERROR(DATEDIF(D307, E307, "D"), " ") -> 8 | Z307: {=_xlfn.IFS(Y307<=5, "On time", AND(Y307>5, Y307<>" "), "Delayed", Y307=" ", "pending" )} -> #NAME?
A308: ORD10307 | B308: C006 | C308: P102 | D308: 16/02/2025 | E308: 26/02/2025 | F308: Sneha Joshi | G308: Female | H308: 05/03/1992 | I308: Mumbai | J308: West | K308: Electronics | L308: Mouse | M308: 17 | N308: 700 | O308: 20 | P308: 9520 | Q308: 4 | R308: NetBanking | S308: Neha | T308: sneha.joshi@company.com | U308: 9666803655 | V308: Completed | W308: =PROPER(TRIM(F308)) -> Sneha Joshi | X308: =IFERROR(DATEDIF(H308, TODAY(), "y"), " ") -> 34 | Y308: =IFERROR(DATEDIF(D308, E308, "D"), " ") -> 10 | Z308: {=_xlfn.IFS(Y308<=5, "On time", AND(Y308>5, Y308<>" "), "Delayed", Y308=" ", "pending" )} -> #NAME?
A309: ORD10308 | B309: C006 | C309: P203 | D309: 28/08/2025 | E309: 08/09/2025 | F309: Sneha Joshi | G309: Female | H309: 28/12/1976 | I309: Pune | J309: West | K309: Home Appliances | L309: Microwave | M309: 6 | N309: 8500 | O309: 15 | P309: 43350 | Q309: 1 | R309: Cash | S309: Aisha | T309: sneha.joshi@company.com | U309: 9134878547 | V309: Completed | W309: =PROPER(TRIM(F309)) -> Sneha Joshi | X309: =IFERROR(DATEDIF(H309, TODAY(), "y"), " ") -> 49 | Y309: =IFERROR(DATEDIF(D309, E309, "D"), " ") -> 11 | Z309: {=_xlfn.IFS(Y309<=5, "On time", AND(Y309>5, Y309<>" "), "Delayed", Y309=" ", "pending" )} -> #NAME?
A310: ORD10309 | B310: C010 | C310: P201 | D310: 06/10/2025 | E310: 11/10/2025 | F310: Pooja Shah | G310: Female | H310: 04/09/1986 | I310: Hyderabad | J310: South | K310: Home Appliances | L310: Mixer | M310: 3 | N310: 3500 | O310: 10 | P310: 9450 | Q310: 1 | R310: NetBanking | S310: Rahul | T310: pooja.shah@company.com | U310: 9253593557 | V310: Completed | W310: =PROPER(TRIM(F310)) -> Pooja Shah | X310: =IFERROR(DATEDIF(H310, TODAY(), "y"), " ") -> 39 | Y310: =IFERROR(DATEDIF(D310, E310, "D"), " ") -> 5 | Z310: {=_xlfn.IFS(Y310<=5, "On time", AND(Y310>5, Y310<>" "), "Delayed", Y310=" ", "pending" )} -> #NAME?
A311: ORD10310 | B311: C009 | C311: P104 | D311: 17/01/2025 | E311: 29/01/2025 | F311: Mohit Verma | G311: Male | H311: 14/08/1989 | I311: Ahmedabad | J311: West | K311: Electronics | L311: Monitor | M311: 2 | N311: 12000 | O311: 20 | P311: 19200 | Q311: 1 | R311: Card | S311: Aisha | T311: mohit.verma@company.com | U311: 9183094051 | V311: Completed | W311: =PROPER(TRIM(F311)) -> Mohit Verma | X311: =IFERROR(DATEDIF(H311, TODAY(), "y"), " ") -> 36 | Y311: =IFERROR(DATEDIF(D311, E311, "D"), " ") -> 12 | Z311: {=_xlfn.IFS(Y311<=5, "On time", AND(Y311>5, Y311<>" "), "Delayed", Y311=" ", "pending" )} -> #NAME?
A312: ORD10311 | B312: C005 | C312: P302 | D312: 13/10/2025 | E312: 16/10/2025 | F312: Vikas Mehta | G312: Male | H312: 02/03/1991 | I312: Delhi | J312: North | K312: Stationery | L312: Pen | M312: 12 | N312: 20 | O312: 20 | P312: 192 | Q312: 2 | R312: Card | S312: Rahul | T312: vikas.mehta@company.com | U312: 9293147620 | V312: Completed | W312: =PROPER(TRIM(F312)) -> Vikas Mehta | X312: =IFERROR(DATEDIF(H312, TODAY(), "y"), " ") -> 35 | Y312: =IFERROR(DATEDIF(D312, E312, "D"), " ") -> 3 | Z312: {=_xlfn.IFS(Y312<=5, "On time", AND(Y312>5, Y312<>" "), "Delayed", Y312=" ", "pending" )} -> #NAME?
... A370: ORD10369 | B370: C010 | C370: P301 | D370: 01/04/2026 | E370: 05/04/2026 | F370: Pooja Shah | G370: Female | H370: 04/01/1987 | I370: Hyderabad | J370: South | K370: Stationery | L370: Notebook | M370: 19 | N370: 60 | O370: 15 | P370: 969 | Q370: 4 | R370: NetBanking | S370: Neha | T370: pooja.shah@company.com | U370: 9435947486 | V370: Cancelled | W370: =PROPER(TRIM(F370)) -> Pooja Shah | X370: =IFERROR(DATEDIF(H370, TODAY(), "y"), " ") -> 39 | Y370: =IFERROR(DATEDIF(D370, E370, "D"), " ") -> 4 | Z370: {=_xlfn.IFS(Y370<=5, "On time", AND(Y370>5, Y370<>" "), "Delayed", Y370=" ", "pending" )} -> #NAME?
A371: ORD10370 | B371: C001 | C371: P101 | E371: 02/02/2025 | F371: Amit Sharma | G371: Male | H371: 14/05/1992 | I371: Delhi | J371: North | K371: Electronics | L371: Laptop | M371: 15 | N371: 55000 | O371: 0 | P371: 825000 | Q371: 5 | R371: Card | S371: Neha | T371: amit.sharma@company.com | U371: 9411668831 | V371: Cancelled | W371: =PROPER(TRIM(F371)) -> Amit Sharma | X371: =IFERROR(DATEDIF(H371, TODAY(), "y"), " ") -> 34 | Y371: =IFERROR(DATEDIF(D371, E371, "D"), " ") -> 45690 | Z371: {=_xlfn.IFS(Y371<=5, "On time", AND(Y371>5, Y371<>" "), "Delayed", Y371=" ", "pending" )} -> #NAME?
A372: ORD10371 | B372: C009 | C372: P303 | D372: 06/10/2025 | E372: 08/10/2025 | F372: Mohit Verma | G372: Male | H372: 03/05/1989 | I372: Bengaluru | J372: South | K372: Stationery | L372: Marker | M372: 11 | N372: 45 | O372: 5 | P372: 470.25 | Q372: 5 | R372: NetBanking | S372: Karan | T372: mohit.verma@company.com | U372: 9523682403 | V372: Completed | W372: =PROPER(TRIM(F372)) -> Mohit Verma | X372: =IFERROR(DATEDIF(H372, TODAY(), "y"), " ") -> 37 | Y372: =IFERROR(DATEDIF(D372, E372, "D"), " ") -> 2 | Z372: {=_xlfn.IFS(Y372<=5, "On time", AND(Y372>5, Y372<>" "), "Delayed", Y372=" ", "pending" )} -> #NAME?
A373: ORD10372 | B373: C006 | C373: P302 | D373: 12/06/2025 | E373: 17/06/2025 | F373: Sneha Joshi | G373: Female | H373: 19/12/1990 | I373: Jaipur | J373: North | K373: Stationery | L373: Pen | M373: 9 | N373: 20 | O373: 10 | P373: 162 | Q373: 1 | R373: Card | S373: Rahul | T373: sneha.joshi@company.com | U373: 9652936744 | V373: Cancelled | W373: =PROPER(TRIM(F373)) -> Sneha Joshi | X373: =IFERROR(DATEDIF(H373, TODAY(), "y"), " ") -> 35 | Y373: =IFERROR(DATEDIF(D373, E373, "D"), " ") -> 5 | Z373: {=_xlfn.IFS(Y373<=5, "On time", AND(Y373>5, Y373<>" "), "Delayed", Y373=" ", "pending" )} -> #NAME?
A374: ORD10373 | B374: C004 | C374: P303 | D374: 18/11/2025 | E374: 20/11/2025 | F374: Anita Gupta | G374: Female | H374: 09/07/1995 | I374: Bengaluru | J374: South | K374: Stationery | L374: Marker | M374: 5 | N374: 45 | O374: 5 | P374: 213.75 | Q374: 3 | R374: Card | S374: Neha | T374: anita.gupta@company.com | U374: 9726464733 | V374: Pending | W374: =PROPER(TRIM(F374)) -> Anita Gupta | X374: =IFERROR(DATEDIF(H374, TODAY(), "y"), " ") -> 31 | Y374: =IFERROR(DATEDIF(D374, E374, "D"), " ") -> 2 | Z374: {=_xlfn.IFS(Y374<=5, "On time", AND(Y374>5, Y374<>" "), "Delayed", Y374=" ", "pending" )} -> #NAME?
A375: ORD10374 | B375: C007 | C375: P102 | D375: 01/11/2025 | E375: 02/11/2025 | F375: Arjun Rao | G375: Male | H375: 23/12/1998 | I375: Hyderabad | J375: South | K375: Electronics | L375: Mouse | M375: 5 | N375: 700 | O375: 10 | P375: 3150 | Q375: 2 | R375: UPI | S375: Rahul | T375: arjun.rao@company.com | U375: 9273520544 | V375: Completed | W375: =PROPER(TRIM(F375)) -> Arjun Rao | X375: =IFERROR(DATEDIF(H375, TODAY(), "y"), " ") -> 27 | Y375: =IFERROR(DATEDIF(D375, E375, "D"), " ") -> 1 | Z375: {=_xlfn.IFS(Y375<=5, "On time", AND(Y375>5, Y375<>" "), "Delayed", Y375=" ", "pending" )} -> #NAME?
A376: ORD10375 | B376: C005 | C376: P102 | D376: 24/01/2025 | E376: 31/01/2025 | F376: Vikas Mehta | G376: Male | H376: 23/12/1979 | I376: Kolkata | J376: East | K376: Electronics | L376: Mouse | M376: 1 | N376: 700 | O376: 0 | P376: 700 | Q376: 1 | R376: UPI | S376: Karan | T376: vikas.mehta@company.com | U376: 9374259988 | V376: Completed | W376: =PROPER(TRIM(F376)) -> Vikas Mehta | X376: =IFERROR(DATEDIF(H376, TODAY(), "y"), " ") -> 46 | Y376: =IFERROR(DATEDIF(D376, E376, "D"), " ") -> 7 | Z376: {=_xlfn.IFS(Y376<=5, "On time", AND(Y376>5, Y376<>" "), "Delayed", Y376=" ", "pending" )} -> #NAME?
A377: ORD10376 | B377: C008 | C377: P102 | D377: 13/02/2026 | E377: 21/02/2026 | F377: Kavya Nair | G377: Female | H377: 15/12/1975 | I377: Mumbai | J377: West | K377: Electronics | L377: Mouse | M377: 13 | N377: 700 | O377: 20 | P377: 7280 | Q377: 2 | R377: Card | S377: Ritika | T377: kavya.nair@company.com | U377: 9538129419 | V377: Completed | W377: =PROPER(TRIM(F377)) -> Kavya Nair | X377: =IFERROR(DATEDIF(H377, TODAY(), "y"), " ") -> 50 | Y377: =IFERROR(DATEDIF(D377, E377, "D"), " ") -> 8 | Z377: {=_xlfn.IFS(Y377<=5, "On time", AND(Y377>5, Y377<>" "), "Delayed", Y377=" ", "pending" )} -> #NAME?
A378: ORD10377 | B378: C009 | C378: P104 | D378: 08/02/2025 | E378: 19/02/2025 | F378: Mohit Verma | G378: Male | H378: 17/05/1993 | I378: Pune | J378: West | K378: Electronics | L378: Monitor | M378: 20 | N378: 12000 | O378: 0 | P378: 240000 | Q378: 2 | R378: Card | S378: Neha | T378: mohit.verma@company.com | U378: 9382815686 | V378: Completed | W378: =PROPER(TRIM(F378)) -> Mohit Verma | X378: =IFERROR(DATEDIF(H378, TODAY(), "y"), " ") -> 33 | Y378: =IFERROR(DATEDIF(D378, E378, "D"), " ") -> 11 | Z378: {=_xlfn.IFS(Y378<=5, "On time", AND(Y378>5, Y378<>" "), "Delayed", Y378=" ", "pending" )} -> #NAME?
A379: ORD10378 | B379: C007 | C379: P103 | D379: 28/12/2025 | E379: 06/01/2026 | F379: Arjun Rao | G379: Male | H379: 17/09/1976 | I379: Kolkata | J379: East | K379: Electronics | L379: Keyboard | M379: 9 | N379: 1200 | O379: 15 | P379: 9180 | Q379: 1 | R379: UPI | S379: Ritika | T379: arjun.rao@company.com | U379: 9450746157 | V379: Pending | W379: =PROPER(TRIM(F379)) -> Arjun Rao | X379: =IFERROR(DATEDIF(H379, TODAY(), "y"), " ") -> 49 | Y379: =IFERROR(DATEDIF(D379, E379, "D"), " ") -> 9 | Z379: {=_xlfn.IFS(Y379<=5, "On time", AND(Y379>5, Y379<>" "), "Delayed", Y379=" ", "pending" )} -> #NAME?
A380: ORD10379 | B380: C007 | C380: P302 | D380: 01/10/2025 | E380: 03/10/2025 | F380: Arjun Rao | G380: Male | H380: 22/12/1996 | I380: Jaipur | J380: North | K380: Stationery | L380: Pen | M380: 3 | N380: 20 | O380: 15 | P380: 51 | Q380: 3 | R380: Cash | S380: Neha | T380: arjun.rao@company.com | U380: 9349012570 | V380: Pending | W380: =PROPER(TRIM(F380)) -> Arjun Rao | X380: =IFERROR(DATEDIF(H380, TODAY(), "y"), " ") -> 29 | Y380: =IFERROR(DATEDIF(D380, E380, "D"), " ") -> 2 | Z380: {=_xlfn.IFS(Y380<=5, "On time", AND(Y380>5, Y380<>" "), "Delayed", Y380=" ", "pending" )} -> #NAME?
A381: ORD10380 | B381: C006 | C381: P101 | D381: 18/12/2025 | E381: 19/12/2025 | F381: Sneha Joshi | G381: Female | H381: 25/12/1995 | I381: Delhi | J381: North | K381: Electronics | L381: Laptop | M381: 8 | N381: 55000 | O381: 20 | P381: 352000 | Q381: 5 | R381: Card | S381: Karan | T381: sneha.joshi@company.com | U381: 9442163790 | V381: Pending | W381: =PROPER(TRIM(F381)) -> Sneha Joshi | X381: =IFERROR(DATEDIF(H381, TODAY(), "y"), " ") -> 30 | Y381: =IFERROR(DATEDIF(D381, E381, "D"), " ") -> 1 | Z381: {=_xlfn.IFS(Y381<=5, "On time", AND(Y381>5, Y381<>" "), "Delayed", Y381=" ", "pending" )} -> #NAME?
A382: ORD10381 | B382: C006 | C382: P301 | D382: 29/09/2025 | E382: 07/10/2025 | F382: Sneha Joshi | G382: Female | H382: 23/06/1985 | I382: Delhi | J382: North | K382: Stationery | L382: Notebook | M382: 17 | N382: 60 | O382: 20 | P382: 816 | Q382: 1 | R382: UPI | S382: Ritika | T382: sneha.joshi@company.com | U382: 9953329223 | V382: Pending | W382: =PROPER(TRIM(F382)) -> Sneha Joshi | X382: =IFERROR(DATEDIF(H382, TODAY(), "y"), " ") -> 41 | Y382: =IFERROR(DATEDIF(D382, E382, "D"), " ") -> 8 | Z382: {=_xlfn.IFS(Y382<=5, "On time", AND(Y382>5, Y382<>" "), "Delayed", Y382=" ", "pending" )} -> #NAME?
A383: ORD10382 | B383: C003 | C383: P302 | D383: 14/05/2025 | E383: 22/05/2025 | F383: Rohit Singh | G383: Male | H383: 10/02/1984 | I383: Bengaluru | J383: South | K383: Stationery | L383: Pen | M383: 4 | N383: 20 | O383: 15 | P383: 68 | Q383: 3 | R383: NetBanking | S383: Aisha | T383: rohit.singh@company.com | U383: 9202321359 | V383: Pending | W383: =PROPER(TRIM(F383)) -> Rohit Singh | X383: =IFERROR(DATEDIF(H383, TODAY(), "y"), " ") -> 42 | Y383: =IFERROR(DATEDIF(D383, E383, "D"), " ") -> 8 | Z383: {=_xlfn.IFS(Y383<=5, "On time", AND(Y383>5, Y383<>" "), "Delayed", Y383=" ", "pending" )} -> #NAME?
... A399: ORD10398 | B399: C007 | C399: P104 | D399: 31/01/2025 | E399: 04/02/2025 | F399: Arjun Rao | G399: Male | H399: 10/12/1978 | I399: Kolkata | J399: East | K399: Electronics | L399: Monitor | M399: 19 | N399: 12000 | O399: 0 | P399: 228000 | Q399: 4 | R399: UPI | S399: Aisha | T399: arjun.rao@company.com | U399: 9136906750 | V399: Pending | W399: =PROPER(TRIM(F399)) -> Arjun Rao | X399: =IFERROR(DATEDIF(H399, TODAY(), "y"), " ") -> 47 | Y399: =IFERROR(DATEDIF(D399, E399, "D"), " ") -> 4 | Z399: {=_xlfn.IFS(Y399<=5, "On time", AND(Y399>5, Y399<>" "), "Delayed", Y399=" ", "pending" )} -> #NAME?
A400: ORD10399 | B400: C001 | C400: P102 | E400: 03/11/2025 | F400: Amit Sharma | G400: Male | H400: 01/09/1979 | I400: Bengaluru | J400: South | K400: Electronics | L400: Mouse | M400: 12 | N400: 700 | O400: 15 | P400: 7140 | Q400: 3 | R400: Card | S400: Ritika | T400: amit.sharma@company.com | U400: 9485286324 | V400: Completed | W400: =PROPER(TRIM(F400)) -> Amit Sharma | X400: =IFERROR(DATEDIF(H400, TODAY(), "y"), " ") -> 46 | Y400: =IFERROR(DATEDIF(D400, E400, "D"), " ") -> 45964 | Z400: {=_xlfn.IFS(Y400<=5, "On time", AND(Y400>5, Y400<>" "), "Delayed", Y400=" ", "pending" )} -> #NAME?
A401: ORD10400 | B401: C008 | C401: P103 | D401: 13/05/2025 | E401: 21/05/2025 | F401: Kavya Nair | G401: Female | H401: 08/04/2001 | I401: Delhi | J401: North | K401: Electronics | L401: Keyboard | M401: 16 | N401: 1200 | O401: 20 | P401: 15360 | Q401: 1 | R401: Cash | S401: Rahul | T401: kavya.nair@company.com | U401: 9414633966 | V401: Pending | W401: =PROPER(TRIM(F401)) -> Kavya Nair | X401: =IFERROR(DATEDIF(H401, TODAY(), "y"), " ") -> 25 | Y401: =IFERROR(DATEDIF(D401, E401, "D"), " ") -> 8 | Z401: {=_xlfn.IFS(Y401<=5, "On time", AND(Y401>5, Y401<>" "), "Delayed", Y401=" ", "pending" )} -> #NAME?
A402: ORD10401 | B402: C009 | C402: P203 | D402: 27/12/2025 | E402: 04/01/2026 | F402: Mohit Verma | G402: Male | H402: 01/01/1983 | I402: Hyderabad | J402: South | K402: Home Appliances | L402: Microwave | M402: 10 | N402: 8500 | O402: 5 | P402: 80750 | Q402: 5 | R402: NetBanking | S402: Ritika | T402: mohit.verma@company.com | U402: 9833735234 | V402: Completed | W402: =PROPER(TRIM(F402)) -> Mohit Verma | X402: =IFERROR(DATEDIF(H402, TODAY(), "y"), " ") -> 43 | Y402: =IFERROR(DATEDIF(D402, E402, "D"), " ") -> 8 | Z402: {=_xlfn.IFS(Y402<=5, "On time", AND(Y402>5, Y402<>" "), "Delayed", Y402=" ", "pending" )} -> #NAME?
A403: ORD10402 | B403: C008 | C403: P302 | D403: 11/02/2025 | E403: 21/02/2025 | F403: Kavya Nair | G403: Female | H403: 09/08/1989 | I403: Ahmedabad | J403: West | K403: Stationery | L403: Pen | M403: 18 | N403: 20 | O403: 20 | P403: 288 | Q403: 1 | R403: UPI | S403: Ritika | T403: kavya.nair@company.com | U403: 9523689108 | V403: Pending | W403: =PROPER(TRIM(F403)) -> Kavya Nair | X403: =IFERROR(DATEDIF(H403, TODAY(), "y"), " ") -> 36 | Y403: =IFERROR(DATEDIF(D403, E403, "D"), " ") -> 10 | Z403: {=_xlfn.IFS(Y403<=5, "On time", AND(Y403>5, Y403<>" "), "Delayed", Y403=" ", "pending" )} -> #NAME?
A404: ORD10403 | B404: C009 | C404: P203 | D404: 13/03/2026 | E404: 19/03/2026 | F404: Mohit Verma | G404: Male | H404: 22/10/1993 | I404: Mumbai | J404: West | K404: Home Appliances | L404: Microwave | M404: 9 | N404: 8500 | O404: 0 | P404: 76500 | Q404: 2 | R404: Card | S404: Ritika | T404: mohit.verma@company.com | U404: 9812909831 | V404: Pending | W404: =PROPER(TRIM(F404)) -> Mohit Verma | X404: =IFERROR(DATEDIF(H404, TODAY(), "y"), " ") -> 32 | Y404: =IFERROR(DATEDIF(D404, E404, "D"), " ") -> 6 | Z404: {=_xlfn.IFS(Y404<=5, "On time", AND(Y404>5, Y404<>" "), "Delayed", Y404=" ", "pending" )} -> #NAME?
A405: ORD10404 | B405: C008 | C405: P203 | D405: 01/10/2025 | E405: 12/10/2025 | F405: Kavya Nair | G405: Female | H405: 05/05/2000 | I405: Mumbai | J405: West | K405: Home Appliances | L405: Microwave | M405: 8 | N405: 8500 | O405: 10 | P405: 61200 | Q405: 4 | R405: Cash | S405: Neha | T405: kavya.nair@company.com | U405: 9106290987 | V405: Cancelled | W405: =PROPER(TRIM(F405)) -> Kavya Nair | X405: =IFERROR(DATEDIF(H405, TODAY(), "y"), " ") -> 26 | Y405: =IFERROR(DATEDIF(D405, E405, "D"), " ") -> 11 | Z405: {=_xlfn.IFS(Y405<=5, "On time", AND(Y405>5, Y405<>" "), "Delayed", Y405=" ", "pending" )} -> #NAME?
...

Sheet Q4)Product_lookup_report
A1: Order_ID | B1: Customer_ID | C1: Product_ID | D1: Order_Date | E1: Delivery_Date | F1: Customer_Name | G1: Gender | H1: DOB | I1: City | J1: Region | K1: Category | L1: Product_Name | M1: Quantity | N1: Unit_Price | O1: Discount_% | P1: Sales | Q1: Rating | R1: Payment_Mode | S1: Salesperson | T1: Email | U1: Phone | V1: Order_Status | W1: Product_ID | X1: Product_ID | Y1: Category | Z1: Supplier | AA1: Cost_price | AB1: Warranty
A2: ORD10001 | B2: C008 | C2: P202 | D2: 18/09/2025 | E2: 22/09/2025 | F2: Kavya Nair | G2: Female | H2: 01/08/1976 | I2: Hyderabad | J2: South | K2: Home Appliances | L2: Iron | M2: 4 | N2: 2200 | O2: 10 | P2: 7920 | Q2: 4 | R2: Cash | S2: Ritika | T2: KAvya.nair@company.com | U2: 9431429797 | V2: Completed | W2: =C2 -> P202 | X2: {=_xlfn.XLOOKUP(C2,C:C, _xlfn.HSTACK(L:L,K:K,S:S,Product_master!E:E,Product_master!F:F))} -> #NAME? | Y2: #NAME? | Z2: #NAME? | AA2: #NAME? | AB2: #NAME?
A3: ORD10002 | B3: C008 | C3: P104 | D3: 27/04/2025 | E3: 04/05/2025 | F3: Kavya Nair | G3: Female | H3: 16/10/2000 | I3: Delhi | J3: North | K3: Electronics | L3: Monitor | M3: 17 | N3: 12000 | O3: 10 | P3: 183600 | Q3: 1 | R3: NetBanking | S3: Rahul | T3: kavya.nair@company.com | U3: 9129865339 | V3: Completed | W3: =C3 -> P104 | X3: {=_xlfn.XLOOKUP(C3,C:C, _xlfn.HSTACK(L:L,K:K,S:S,Product_master!E:E,Product_master!F:F ))} -> #NAME? | Y3: #NAME? | Z3: #NAME? | AA3: #NAME? | AB3: #NAME?
A4: ORD10003 | B4: C010 | C4: P101 | D4: 03/09/2025 | E4: 14/09/2025 | F4: pooja shah | G4: Female | H4: 16/09/1994 | I4: Bengaluru | J4: South | K4: Electronics | L4: Laptop | M4: 5 | N4: 55000 | O4: 5 | P4: 261250 | Q4: 3 | R4: NetBanking | S4: Aisha | T4: pooja.shah@company.com | U4: 9380975626 | V4: Pending | W4: =C4 -> P101 | X4: {=_xlfn.XLOOKUP(C4,C:C, _xlfn.HSTACK(L:L,K:K,S:S,Product_master!E:E,Product_master!F:F ))} -> #NAME? | Y4: #NAME? | Z4: #NAME? | AA4: #NAME? | AB4: #NAME?
A5: ORD10002 | B5: C008 | C5: P202 | D5: 21/03/2026 | E5: 02/04/2026 | F5: Kavya Nair | G5: Female | H5: 07/03/2004 | I5: Bengaluru | J5: South | K5: Home Appliances | L5: Iron | M5: 5 | N5: 2200 | O5: 5 | P5: 10450 | Q5: 5 | R5: NetBanking | S5: Aisha | T5: kavya.nair@company.com | U5: 9600261125 | V5: Cancelled | W5: =C5 -> P202 | X5: {=_xlfn.XLOOKUP(C5,C:C, _xlfn.HSTACK(L:L,K:K,S:S,Product_master!E:E,Product_master!F:F ))} -> #NAME? | Y5: #NAME? | Z5: #NAME? | AA5: #NAME? | AB5: #NAME?
A6: ORD10005 | B6: C009 | C6: P103 | D6: 27/09/2025 | E6: 07/10/2025 | F6: Mohit Verma | G6: Male | H6: 13/04/1976 | I6: Delhi | J6: North | K6: Electronics | L6: Keyboard | M6: 8 | N6: 1200 | O6: 5 | P6: 9120 | Q6: 2 | R6: Card | S6: Aisha | T6: mohit.verma@company.com | U6: 9724635978 | V6: Pending | W6: =C6 -> P103 | X6: {=_xlfn.XLOOKUP(C6,C:C, _xlfn.HSTACK(L:L,K:K,S:S,Product_master!E:E,Product_master!F:F ))} -> #NAME? | Y6: #NAME? | Z6: #NAME? | AA6: #NAME? | AB6: #NAME?
A7: ORD10006 | B7: C007 | C7: P202 | D7: 04/01/2026 | E7: 12/01/2026 | F7: arjun Rao | G7: Male | H7: 07/02/1988 | I7: Hyderabad | J7: South | K7: Home Appliances | L7: Iron | M7: 4 | N7: 2200 | O7: 0 | P7: 8800 | Q7: 1 | R7: UPI | S7: Ritika | T7: arjun.rao@company.com | U7: 9780584905 | V7: Completed | W7: =C7 -> P202 | X7: {=_xlfn.XLOOKUP(C7,C:C, _xlfn.HSTACK(L:L,K:K,S:S,Product_master!E:E,Product_master!F:F ))} -> #NAME? | Y7: #NAME? | Z7: #NAME? | AA7: #NAME? | AB7: #NAME?
A8: ORD10007 | B8: C008 | C8: P201 | D8: 31/02/2025 | E8: 25/02/2026 | F8: Kavya Nair | G8: Female | H8: 20/03/2003 | I8: Hyderabad | J8: South | K8: Home Appliances | L8: Mixer | M8: 2 | N8: 3500 | O8: 5 | P8: 6650 | Q8: 1 | R8: UPI | S8: Ritika | T8: kavya.nair@company.com | U8: 9958252176 | V8: Completed | W8: =C8 -> P201 | X8: {=_xlfn.XLOOKUP(C8,C:C, _xlfn.HSTACK(L:L,K:K,S:S,Product_master!E:E,Product_master!F:F ))} -> #NAME? | Y8: #NAME? | Z8: #NAME? | AA8: #NAME? | AB8: #NAME?
A9: ORD10008 | B9: C002 | C9: P104 | D9: 13/04/2025 | E9: 19/04/2025 | F9: Priya Patel | G9: Female | H9: 07/03/1995 | I9: Mumbai | J9: West | K9: Electronics | L9: Monitor | M9: 14 | N9: 12000 | O9: 15 | P9: 142800 | Q9: 4 | R9: NetBanking | S9: Ritika | T9: priYa.patel@company.com | U9: 9705521654 | V9: Completed | W9: =C9 -> P104 | X9: {=_xlfn.XLOOKUP(C9,C:C, _xlfn.HSTACK(L:L,K:K,S:S,Product_master!E:E,Product_master!F:F ))} -> #NAME? | Y9: #NAME? | Z9: #NAME? | AA9: #NAME? | AB9: #NAME?
A10: ORD10009 | B10: C008 | C10: P104 | D10: 31/01/2026 | E10: 02/02/2026 | F10: kavya Nair | G10: Female | H10: 06/04/1997 | I10: Pune | J10: West | K10: Electronics | L10: Monitor | M10: 4 | N10: 12000 | O10: 15 | P10: 40800 | Q10: 4 | R10: UPI | S10: Neha | T10: kavya.nair@company.com | U10: 9588041011 | V10: Completed | W10: =C10 -> P104 | X10: {=_xlfn.XLOOKUP(C10,C:C, _xlfn.HSTACK(L:L,K:K,S:S,Product_master!E:E,Product_master!F:F ))} -> #NAME? | Y10: #NAME? | Z10: #NAME? | AA10: #NAME? | AB10: #NAME?
A11: ORD10010 | B11: C002 | C11: P301 | D11: 25/03/2025 | E11: 27/03/2025 | F11: Priya Patel | G11: Female | H11: 07/01/1990 | I11: Mumbai | J11: West | K11: Stationery | L11: Notebook | M11: 6 | N11: 60 | O11: 0 | P11: 360 | Q11: 4 | R11: Card | S11: Neha | T11: PRiya.patel@company.com | U11: 9340540608 | V11: Completed | W11: =C11 -> P301 | X11: {=_xlfn.XLOOKUP(C11,C:C, _xlfn.HSTACK(L:L,K:K,S:S,Product_master!E:E,Product_master!F:F ))} -> #NAME? | Y11: #NAME? | Z11: #NAME? | AA11: #NAME? | AB11: #NAME?
A12: ORD10011 | B12: C003 | C12: P202 | D12: 19/09/2025 | E12: 23/09/2025 | F12: Rohit Singh | G12: Male | H12: 10/05/1982 | I12: Delhi | J12: North | K12: Home Appliances | L12: Iron | M12: -3 | N12: 2200 | O12: 0 | P12: 35200 | Q12: 2 | R12: Card | S12: Rahul | T12: rohit.singh@company.com | U12: 9521710321 | V12: Pending | W12: =C12 -> P202 | X12: {=_xlfn.XLOOKUP(C12,C:C, _xlfn.HSTACK(L:L,K:K,S:S,Product_master!E:E,Product_master!F:F ))} -> #NAME? | Y12: #NAME? | Z12: #NAME? | AA12: #NAME? | AB12: #NAME?
A13: ORD10012 | B13: C008 | C13: P201 | D13: 08/03/2025 | E13: 15/03/2025 | F13: Kavya Nair | G13: Female | H13: 23/01/1982 | I13: Ahmedabad | J13: West | K13: Home Appliances | L13: Mixer | M13: 10 | N13: 3500 | O13: 5 | P13: 33250 | Q13: 5 | R13: Card | S13: Aisha | T13: kavya.nair@company.com | U13: 9123535241 | V13: Cancelled | W13: =C13 -> P201 | X13: {=_xlfn.XLOOKUP(C13,C:C, _xlfn.HSTACK(L:L,K:K,S:S,Product_master!E:E,Product_master!F:F ))} -> #NAME? | Y13: #NAME? | Z13: #NAME? | AA13: #NAME? | AB13: #NAME?
A14: ORD10013 | B14: C002 | C14: P202 | D14: 10/01/2025 | E14: 15/01/2025 | F14: Priya Patel | G14: Female | H14: 06/07/1992 | I14: Pune | J14: West | K14: Home Appliances | L14: Iron | M14: 15 | N14: 2200 | O14: 10 | P14: 29700 | Q14: 1 | R14: UPI | S14: Neha | T14: priya.patel@company.com | U14: 9367316892 | V14: Pending | W14: =C14 -> P202 | X14: {=_xlfn.XLOOKUP(C14,C:C, _xlfn.HSTACK(L:L,K:K,S:S,Product_master!E:E,Product_master!F:F ))} -> #NAME? | Y14: #NAME? | Z14: #NAME? | AA14: #NAME? | AB14: #NAME?
... A39: ORD10038 | B39: C006 | C39: P201 | D39: 08/03/2026 | E39: 20/03/2026 | F39: Sneha Joshi | G39: Female | H39: 21/06/1980 | I39: Delhi | J39: North | K39: Home Appliances | L39: Mixer | M39: 20 | N39: 3500 | O39: 10 | P39: 63000 | Q39: 3 | R39: Card | S39: Rahul | T39: sneha.joshi@company.com | U39: 9283578533 | V39: Cancelled | W39: =C39 -> P201 | X39: {=_xlfn.XLOOKUP(C39,C:C, _xlfn.HSTACK(L:L,K:K,S:S,Product_master!E:E,Product_master!F:F ))} -> #NAME? | Y39: #NAME? | Z39: #NAME? | AA39: #NAME? | AB39: #NAME?
A40: ORD10039 | B40: C008 | C40: P302 | D40: 13/02/2025 | E40: 19/02/2025 | F40: Kavya Nair | G40: Female | H40: 17/06/1979 | I40: Pune | J40: West | K40: Stationery | L40: Pen | M40: 5 | N40: 1200 | O40: 0 | P40: 100 | Q40: 1 | R40: Cash | S40: Rahul | T40: kavya.nair@company.com | U40: 9963005771 | V40: Cancelled | W40: =C40 -> P302 | X40: {=_xlfn.XLOOKUP(C40,C:C, _xlfn.HSTACK(L:L,K:K,S:S,Product_master!E:E,Product_master!F:F ))} -> #NAME? | Y40: #NAME? | Z40: #NAME? | AA40: #NAME? | AB40: #NAME?
A41: ORD10040 | B41: C010 | C41: P203 | D41: 05/10/2025 | E41: 15/10/2025 | F41: Pooja Shah | G41: Female | H41: 18/06/1992 | I41: Mumbai | J41: West | K41: Home Appliances | L41: Microwave | M41: 20 | N41: 8500 | O41: 0 | P41: 170000 | Q41: 1 | R41: UPI | S41: Neha | T41: pooja.shah@company.com | U41: 9484632635 | V41: Cancelled | W41: =C41 -> P203 | X41: {=_xlfn.XLOOKUP(C41,C:C, _xlfn.HSTACK(L:L,K:K,S:S,Product_master!E:E,Product_master!F:F ))} -> #NAME? | Y41: #NAME? | Z41: #NAME? | AA41: #NAME? | AB41: #NAME?
A42: ORD10041 | B42: C007 | C42: P301 | D42: 10/02/2026 | E42: 12/02/2026 | F42: Arjun Rao | G42: Male | H42: 06/06/1994 | I42: Bengaluru | J42: South | K42: Stationery | L42: Notebook | M42: 8 | N42: 60 | O42: 15 | P42: 408 | Q42: 5 | R42: UPI | S42: Rahul | T42: arjun.rao@company.com | U42: 9276319484 | V42: Pending | W42: =C42 -> P301 | X42: {=_xlfn.XLOOKUP(C42,C:C, _xlfn.HSTACK(L:L,K:K,S:S,Product_master!E:E,Product_master!F:F ))} -> #NAME? | Y42: #NAME? | Z42: #NAME? | AA42: #NAME? | AB42: #NAME?
A43: ORD10042 | B43: C010 | C43: P201 | D43: 04/06/2025 | E43: 16/06/2025 | F43: Pooja Shah | G43: Female | H43: 22/09/1988 | I43: Pune | J43: West | K43: Home Appliances | L43: Mixer | M43: 8 | N43: 3500 | O43: 5 | P43: 26600 | Q43: 1 | R43: Card | S43: Neha | T43: pooja.shah@company.com | U43: 9619034852 | V43: Pending | W43: =C43 -> P201 | X43: {=_xlfn.XLOOKUP(C43,C:C, _xlfn.HSTACK(L:L,K:K,S:S,Product_master!E:E,Product_master!F:F ))} -> #NAME? | Y43: #NAME? | Z43: #NAME? | AA43: #NAME? | AB43: #NAME?
A44: ORD10043 | B44: C009 | C44: P203 | D44: 08/02/2026 | E44: 14/02/2026 | F44: Mohit Verma | G44: Male | H44: 14/07/2001 | I44: Jaipur | J44: North | K44: Home Appliances | L44: Microwave | M44: 1 | N44: 8500 | O44: 0 | P44: 8500 | Q44: 2 | R44: Card | S44: Neha | T44: mohit.verma@company.com | U44: 9636416962 | V44: Pending | W44: =C44 -> P203 | X44: {=_xlfn.XLOOKUP(C44,C:C, _xlfn.HSTACK(L:L,K:K,S:S,Product_master!E:E,Product_master!F:F ))} -> #NAME? | Y44: #NAME? | Z44: #NAME? | AA44: #NAME? | AB44: #NAME?
A45: ORD10044 | B45: C001 | C45: P303 | D45: 30/03/2025 | E45: 31/03/2025 | F45: amit Sharma | G45: Male | H45: 09/08/1991 | I45: Pune | J45: West | K45: Stationery | L45: Marker | M45: 8 | N45: 45 | O45: 15 | P45: 306 | Q45: 2 | R45: Card | S45: Aisha | T45: amit.sharma@company.com | U45: 9357133880 | V45: Completed | W45: =C45 -> P303 | X45: {=_xlfn.XLOOKUP(C45,C:C, _xlfn.HSTACK(L:L,K:K,S:S,Product_master!E:E,Product_master!F:F ))} -> #NAME? | Y45: #NAME? | Z45: #NAME? | AA45: #NAME? | AB45: #NAME?
A46: ORD10045 | B46: C006 | C46: P202 | D46: 25/04/2025 | E46: 28/04/2025 | F46: Sneha Joshi | G46: Female | H46: 21/10/1988 | I46: Pune | J46: West | K46: Home Appliances | L46: Iron | M46: 16 | N46: 2200 | O46: 5 | P46: 33440 | Q46: 5 | R46: Card | S46: Aisha | T46: sneha.joshi@company.com | U46: 9575210324 | V46: Cancelled | W46: =C46 -> P202 | X46: {=_xlfn.XLOOKUP(C46,C:C, _xlfn.HSTACK(L:L,K:K,S:S,Product_master!E:E,Product_master!F:F ))} -> #NAME? | Y46: #NAME? | Z46: #NAME? | AA46: #NAME? | AB46: #NAME?
A47: ORD10046 | B47: C009 | C47: P201 | D47: 13/10/2025 | E47: 23/10/2025 | F47: Mohit Verma | G47: Male | H47: 19/11/2002 | I47: Bengaluru | J47: South | K47: Home Appliances | L47: Mixer | M47: 19 | N47: 3500 | O47: 20 | P47: 53200 | Q47: 3 | R47: Cash | S47: Karan | T47: mohit.verma@company.com | U47: 9276080204 | V47: Cancelled | W47: =C47 -> P201 | X47: {=_xlfn.XLOOKUP(C47,C:C, _xlfn.HSTACK(L:L,K:K,S:S,Product_master!E:E,Product_master!F:F ))} -> #NAME? | Y47: #NAME? | Z47: #NAME? | AA47: #NAME? | AB47: #NAME?
A48: ORD10047 | B48: C006 | C48: P102 | D48: 11/10/2025 | E48: 14/10/2025 | F48: Sneha Joshi | G48: Female | H48: 06/07/2000 | I48: Pune | J48: West | K48: Electronics | L48: Mouse | M48: 15 | N48: 700 | O48: 15 | P48: 8925 | Q48: 4 | R48: UPI | S48: Neha | T48: sneha.joshicompany.com | U48: 9856624471 | V48: Completed | W48: =C48 -> P102 | X48: {=_xlfn.XLOOKUP(C48,C:C, _xlfn.HSTACK(L:L,K:K,S:S,Product_master!E:E,Product_master!F:F ))} -> #NAME? | Y48: #NAME? | Z48: #NAME? | AA48: #NAME? | AB48: #NAME?
A49: ORD10048 | B49: C006 | C49: P102 | D49: 27/11/2025 | E49: 03/12/2025 | F49: Sneha Joshi | G49: Female | H49: 26/11/1998 | I49: Jaipur | J49: North | K49: Electronics | L49: Mouse | M49: 19 | N49: 700 | O49: 20 | P49: 10640 | Q49: 1 | R49: Cash | S49: Neha | T49: sneha.joshi@company.com | U49: 9238141322 | V49: Completed | W49: =C49 -> P102 | X49: {=_xlfn.XLOOKUP(C49,C:C, _xlfn.HSTACK(L:L,K:K,S:S,Product_master!E:E,Product_master!F:F ))} -> #NAME? | Y49: #NAME? | Z49: #NAME? | AA49: #NAME? | AB49: #NAME?
A50: ORD10049 | B50: C009 | C50: P104 | D50: 19/04/2026 | F50: Mohit Verma | G50: Male | H50: 03/06/1996 | I50: Delhi | J50: North | K50: Electronics | L50: Monitor | M50: 19 | N50: 12000 | O50: 0 | P50: 228000 | Q50: 1 | R50: NetBanking | S50: Aisha | T50: mohit.verma@company.com | U50: 9890380030 | V50: Completed | W50: =C50 -> P104 | X50: {=_xlfn.XLOOKUP(C50,C:C, _xlfn.HSTACK(L:L,K:K,S:S,Product_master!E:E,Product_master!F:F ))} -> #NAME? | Y50: #NAME? | Z50: #NAME? | AA50: #NAME? | AB50: #NAME?
A51: ORD10050 | B51: C004 | C51: P103 | D51: 19/04/2026 | E51: 21/04/2026 | F51: Anita Gupta | G51: Female | H51: 15/03/1987 | I51: Pune | J51: West | K51: Electronics | L51: Keyboard | M51: 6 | N51: 1200 | O51: 5 | P51: 6840 | Q51: 2 | R51: Cash | S51: Ritika | T51: anita.gupta@company.com | U51: 9495893170 | V51: Pending | W51: =C51 -> P103 | X51: {=_xlfn.XLOOKUP(C51,C:C, _xlfn.HSTACK(L:L,K:K,S:S,Product_master!E:E,Product_master!F:F ))} -> #NAME? | Y51: #NAME? | Z51: #NAME? | AA51: #NAME? | AB51: #NAME?
A52: ORD10051 | B52: C010 | C52: P202 | D52: 28/03/2025 | E52: 07/04/2025 | F52: POoja Shah | G52: Female | H52: 20/02/1979 | I52: Bengaluru | J52: South | K52: Home Appliances | L52: Iron | M52: 7 | N52: 2200 | O52: 15 | P52: 13090 | Q52: 1 | R52: UPI | S52: Aisha | T52: pooja.shah@company.com | U52: 9485166307 | V52: Completed | W52: =C52 -> P202 | X52: {=_xlfn.XLOOKUP(C52,C:C, _xlfn.HSTACK(L:L,K:K,S:S,Product_master!E:E,Product_master!F:F ))} -> #NAME? | Y52: #NAME? | Z52: #NAME? | AA52: #NAME? | AB52: #NAME?
A53: ORD10052 | B53: C002 | C53: P301 | D53: 25/08/2025 | E53: 28/08/2025 | F53: Priya Patel | G53: Female | H53: 09/08/2000 | I53: Jaipur | J53: North | K53: Stationery | L53: Notebook | M53: 8 | N53: 60 | O53: 10 | P53: 432 | Q53: 5 | R53: Card | S53: Aisha | T53: priya.patel@company.com | U53: 9924709648 | V53: Cancelled | W53: =C53 -> P301 | X53: {=_xlfn.XLOOKUP(C53,C:C, _xlfn.HSTACK(L:L,K:K,S:S,Product_master!E:E,Product_master!F:F ))} -> #NAME? | Y53: #NAME? | Z53: #NAME? | AA53: #NAME? | AB53: #NAME?
A54: ORD10053 | B54: C005 | C54: P101 | D54: 19/08/2025 | E54: 23/08/2025 | F54: Vikas Mehta | G54: Male | H54: 17/01/1976 | I54: Kolkata | J54: East | K54: Electronics | L54: Laptop | M54: 12 | N54: 55000 | O54: 5 | P54: 627000 | Q54: 2 | R54: UPI | S54: Rahul | T54: vikas.mehta@company.com | U54: 9350554626 | V54: Pending | W54: =C54 -> P101 | X54: {=_xlfn.XLOOKUP(C54,C:C, _xlfn.HSTACK(L:L,K:K,S:S,Product_master!E:E,Product_master!F:F ))} -> #NAME? | Y54: #NAME? | Z54: #NAME? | AA54: #NAME? | AB54: #NAME?
A55: ORD10054 | B55: C008 | C55: P102 | D55: 27/07/2025 | E55: 05/08/2025 | F55: Kavya Nair | G55: Female | H55: 04/04/1975 | I55: Jaipur | J55: North | K55: Electronics | L55: Mouse | M55: 3 | N55: 700 | O55: 0 | P55: 2100 | Q55: 3 | R55: Card | S55: Karan | T55: kavya.nair@company.com | U55: 9743295580 | V55: Cancelled | W55: =C55 -> P102 | X55: {=_xlfn.XLOOKUP(C55,C:C, _xlfn.HSTACK(L:L,K:K,S:S,Product_master!E:E,Product_master!F:F ))} -> #NAME? | Y55: #NAME? | Z55: #NAME? | AA55: #NAME? | AB55: #NAME?
A56: ORD10055 | B56: C003 | C56: P301 | D56: 21/02/2025 | E56: 26/02/2025 | F56: RoHit Singh | G56: Male | H56: 11/12/1976 | I56: Ahmedabad | J56: West | K56: Stationery | L56: Notebook | M56: 19 | N56: 60 | O56: 15 | P56: 969 | Q56: 4 | R56: Card | S56: Rahul | T56: rohit.singh@company.com | U56: 9822926495 | V56: Cancelled | W56: =C56 -> P301 | X56: {=_xlfn.XLOOKUP(C56,C:C, _xlfn.HSTACK(L:L,K:K,S:S,Product_master!E:E,Product_master!F:F ))} -> #NAME? | Y56: #NAME? | Z56: #NAME? | AA56: #NAME? | AB56: #NAME?
A57: ORD10056 | B57: C001 | C57: P301 | D57: 10/08/2025 | E57: 11/08/2025 | F57: Amit Sharma | G57: Male | H57: 03/12/1979 | I57: Jaipur | J57: North | K57: Stationery | L57: Notebook | M57: 9 | N57: 60 | O57: 20 | P57: 432 | Q57: 1 | R57: NetBanking | S57: Neha | T57: amit.sharma@company.com | U57: 9518298190 | V57: Pending | W57: =C57 -> P301 | X57: {=_xlfn.XLOOKUP(C57,C:C, _xlfn.HSTACK(L:L,K:K,S:S,Product_master!E:E,Product_master!F:F ))} -> #NAME? | Y57: #NAME? | Z57: #NAME? | AA57: #NAME? | AB57: #NAME?
A58: ORD10057 | B58: C001 | C58: P102 | D58: 24/03/2026 | E58: 30/03/2026 | F58: Amit Sharma | G58: Male | H58: 27/12/1978 | I58: Bengaluru | J58: South | K58: Electronics | L58: Mouse | M58: 6 | N58: 700 | O58: 0 | P58: 4200 | Q58: 4 | R58: UPI | S58: Rahul | T58: amit.sharmcompany.com | U58: 9366223547 | V58: Cancelled | W58: =C58 -> P102 | X58: {=_xlfn.XLOOKUP(C58,C:C, _xlfn.HSTACK(L:L,K:K,S:S,Product_master!E:E,Product_master!F:F ))} -> #NAME? | Y58: #NAME? | Z58: #NAME? | AA58: #NAME? | AB58: #NAME?
A59: ORD10058 | B59: C003 | C59: P303 | D59: 13/03/2026 | E59: 19/03/2026 | F59: Rohit Singh | G59: Male | H59: 15/04/1975 | I59: Delhi | J59: North | K59: Stationery | L59: Marker | M59: 18 | N59: 45 | O59: 5 | P59: 769.5 | Q59: 1 | R59: Card | S59: Aisha | T59: rohit.singh@company.com | U59: 9701988524 | V59: Pending | W59: =C59 -> P303 | X59: {=_xlfn.XLOOKUP(C59,C:C, _xlfn.HSTACK(L:L,K:K,S:S,Product_master!E:E,Product_master!F:F ))} -> #NAME? | Y59: #NAME? | Z59: #NAME? | AA59: #NAME? | AB59: #NAME?
A60: ORD10059 | B60: C007 | C60: P302 | D60: 15/06/2025 | E60: 26/06/2025 | F60: Arjun Rao | G60: Male | H60: 19/12/1988 | I60: Jaipur | J60: North | K60: Stationery | L60: Pen | M60: 8 | N60: 20 | O60: 5 | P60: 152 | Q60: 1 | R60: Card | S60: Ritika | T60: arjun.rao@company.com | U60: 9836327649 | V60: completed | W60: =C60 -> P302 | X60: {=_xlfn.XLOOKUP(C60,C:C, _xlfn.HSTACK(L:L,K:K,S:S,Product_master!E:E,Product_master!F:F ))} -> #NAME? | Y60: #NAME? | Z60: #NAME? | AA60: #NAME? | AB60: #NAME?
A61: ORD10060 | B61: C005 | C61: P102 | D61: 05/03/2025 | E61: 06/03/2025 | F61: Vikas Mehta | G61: Male | H61: 07/03/1979 | I61: Jaipur | J61: North | K61: Electronics | L61: Mouse | M61: 8 | N61: 700 | O61: 10 | P61: 5040 | Q61: 1 | R61: NetBanking | S61: Aisha | T61: Vikas.mehta@company.com | U61: 9261800516 | V61: Cancelled | W61: =C61 -> P102 | X61: {=_xlfn.XLOOKUP(C61,C:C, _xlfn.HSTACK(L:L,K:K,S:S,Product_master!E:E,Product_master!F:F ))} -> #NAME? | Y61: #NAME? | Z61: #NAME? | AA61: #NAME? | AB61: #NAME?
A62: ORD10061 | B62: C008 | C62: P302 | D62: 09/04/2026 | E62: 19/04/2026 | F62: Kavya Nair | G62: Female | H62: 17/12/2003 | I62: Delhi | J62: North | K62: Stationery | L62: Pen | M62: 7 | N62: 20 | O62: 15 | P62: 119 | Q62: 5 | R62: Card | S62: Rahul | T62: kavya.nair@company.com | U62: 9950802015 | V62: Completed | W62: =C62 -> P302 | X62: {=_xlfn.XLOOKUP(C62,C:C, _xlfn.HSTACK(L:L,K:K,S:S,Product_master!E:E,Product_master!F:F ))} -> #NAME? | Y62: #NAME? | Z62: #NAME? | AA62: #NAME? | AB62: #NAME?
... A74: ORD10073 | B74: C008 | C74: P103 | D74: 13/12/2025 | E74: 23/12/2025 | F74: Kavya Nair | G74: Female | H74: 22/09/1981 | I74: Jaipur | J74: North | K74: Electronics | L74: Keyboard | M74: 1 | N74: 1200 | O74: 5 | P74: 1140 | Q74: 3 | R74: UPI | S74: Aisha | T74: kavya.nair@company.com | U74: 9808988530 | V74: Cancelled | W74: =C74 -> P103 | X74: {=_xlfn.XLOOKUP(C74,C:C, _xlfn.HSTACK(L:L,K:K,S:S,Product_master!E:E,Product_master!F:F ))} -> #NAME? | Y74: #NAME? | Z74: #NAME? | AA74: #NAME? | AB74: #NAME?
A75: ORD10074 | B75: C010 | C75: P202 | D75: 04/02/2026 | E75: 16/02/2026 | F75: Pooja Shah | G75: Female | H75: 20/06/1980 | J75: South | K75: Home Appliances | L75: Iron | M75: 1 | N75: 2200 | O75: 15 | P75: 1870 | Q75: 4 | R75: Card | S75: Aisha | T75: pooja.shah@company.com | U75: 9286410494 | V75: Completed | W75: =C75 -> P202 | X75: {=_xlfn.XLOOKUP(C75,C:C, _xlfn.HSTACK(L:L,K:K,S:S,Product_master!E:E,Product_master!F:F ))} -> #NAME? | Y75: #NAME? | Z75: #NAME? | AA75: #NAME? | AB75: #NAME?
A76: ORD10075 | B76: C003 | C76: P103 | D76: 26/01/2026 | E76: 28/01/2026 | F76: Rohit Singh | G76: Male | H76: 02/11/1982 | I76: Pune | J76: West | K76: Electronics | L76: Keyboard | M76: 3 | N76: 1200 | O76: 10 | P76: 3240 | Q76: 5 | R76: Cash | S76: Rahul | T76: rohit.singh@company.com | U76: 9311555196 | V76: Completed | W76: =C76 -> P103 | X76: {=_xlfn.XLOOKUP(C76,C:C, _xlfn.HSTACK(L:L,K:K,S:S,Product_master!E:E,Product_master!F:F ))} -> #NAME? | Y76: #NAME? | Z76: #NAME? | AA76: #NAME? | AB76: #NAME?
A77: ORD10076 | B77: C008 | C77: P201 | D77: 27/06/2025 | E77: 07/07/2025 | F77: Kavya Nair | G77: Female | H77: 10/01/1980 | I77: Bengaluru | J77: South | K77: Home Appliances | L77: Mixer | M77: 10 | N77: 3500 | O77: 20 | P77: 28000 | Q77: 5 | R77: Card | S77: Ritika | T77: kavya.nair@company.com | U77: 9101810266 | V77: Completed | W77: =C77 -> P201 | X77: {=_xlfn.XLOOKUP(C77,C:C, _xlfn.HSTACK(L:L,K:K,S:S,Product_master!E:E,Product_master!F:F ))} -> #NAME? | Y77: #NAME? | Z77: #NAME? | AA77: #NAME? | AB77: #NAME?
A78: ORD10077 | B78: C007 | C78: P102 | D78: 17/03/2026 | E78: 19/03/2026 | F78: Arjun Rao | G78: Male | H78: 27/04/1981 | I78: Delhi | J78: North | K78: Electronics | L78: Mouse | M78: 18 | N78: 700 | O78: 5 | P78: 11970 | Q78: 3 | R78: Card | S78: Neha | T78: arjun.rao@company.com | U78: 9464556593 | V78: Cancelled | W78: =C78 -> P102 | X78: {=_xlfn.XLOOKUP(C78,C:C, _xlfn.HSTACK(L:L,K:K,S:S,Product_master!E:E,Product_master!F:F ))} -> #NAME? | Y78: #NAME? | Z78: #NAME? | AA78: #NAME? | AB78: #NAME?
A79: ORD10078 | B79: C005 | C79: P102 | D79: 09/06/2025 | E79: 18/06/2025 | F79: Vikas Mehta | G79: Male | H79: 12/03/1985 | I79: Bengaluru | J79: South | K79: Electronics | L79: Mouse | M79: 12 | N79: 700 | O79: 15 | P79: 7140 | Q79: 2 | R79: UPI | S79: Rahul | T79: vikas.mehta@company.com | U79: 9338278358 | V79: Completed | W79: =C79 -> P102 | X79: {=_xlfn.XLOOKUP(C79,C:C, _xlfn.HSTACK(L:L,K:K,S:S,Product_master!E:E,Product_master!F:F ))} -> #NAME? | Y79: #NAME? | Z79: #NAME? | AA79: #NAME? | AB79: #NAME?
A80: ORD10079 | B80: C009 | C80: P103 | D80: 15/11/2025 | E80: 16/11/2025 | F80: Mohit Verma | G80: Male | H80: 15/03/1999 | I80: Mumbai | J80: West | K80: Electronics | L80: Keyboard | M80: 8 | N80: 1200 | O80: 0 | P80: 9600 | Q80: 4 | R80: Card | S80: Rahul | T80: mohit.verma@company.com | U80: 9621410770 | V80: Pending | W80: =C80 -> P103 | X80: {=_xlfn.XLOOKUP(C80,C:C, _xlfn.HSTACK(L:L,K:K,S:S,Product_master!E:E,Product_master!F:F ))} -> #NAME? | Y80: #NAME? | Z80: #NAME? | AA80: #NAME? | AB80: #NAME?
A81: ORD10080 | B81: C003 | C81: P301 | D81: 06/11/2025 | E81: 10/11/2025 | F81: Rohit Singh | G81: Male | H81: 07/07/1983 | I81: Pune | J81: West | K81: Stationery | L81: Notebook | M81: 2 | N81: 60 | O81: 0 | P81: 120 | Q81: 2 | R81: UPI | S81: Rahul | T81: rohit.singh@company.com | U81: 9981333189 | V81: Completed | W81: =C81 -> P301 | X81: {=_xlfn.XLOOKUP(C81,C:C, _xlfn.HSTACK(L:L,K:K,S:S,Product_master!E:E,Product_master!F:F ))} -> #NAME? | Y81: #NAME? | Z81: #NAME? | AA81: #NAME? | AB81: #NAME?
A82: ORD10081 | B82: C001 | C82: P303 | D82: 01/01/2025 | E82: 07/01/2025 | F82: Amit Sharma | G82: Male | H82: 06/03/1989 | I82: Pune | J82: West | K82: Stationery | L82: Marker | M82: 10 | N82: 45 | O82: 15 | P82: 382.5 | Q82: 3 | R82: NetBanking | S82: Ritika | T82: amit.sharma@company.com | U82: 9723450355 | V82: Cancelled | W82: =C82 -> P303 | X82: {=_xlfn.XLOOKUP(C82,C:C, _xlfn.HSTACK(L:L,K:K,S:S,Product_master!E:E,Product_master!F:F ))} -> #NAME? | Y82: #NAME? | Z82: #NAME? | AA82: #NAME? | AB82: #NAME?
A83: ORD10082 | B83: C005 | C83: P201 | D83: 25/04/2026 | E83: 03/05/2026 | F83: Vikas Mehta | G83: Male | H83: 20/06/1982 | I83: Kolkata | J83: East | K83: Home Appliances | L83: Mixer | M83: 12 | N83: 3500 | O83: 5 | P83: 39900 | Q83: 3 | R83: NetBanking | S83: Aisha | T83: vikas.mehta@company.com | U83: 9886243907 | V83: Pending | W83: =C83 -> P201 | X83: {=_xlfn.XLOOKUP(C83,C:C, _xlfn.HSTACK(L:L,K:K,S:S,Product_master!E:E,Product_master!F:F ))} -> #NAME? | Y83: #NAME? | Z83: #NAME? | AA83: #NAME? | AB83: #NAME?
A84: ORD10083 | B84: C003 | C84: P301 | D84: 19/09/2025 | E84: 27/09/2025 | F84: Rohit Singh | G84: Male | H84: 23/06/2001 | I84: Mumbai | J84: West | K84: Stationery | L84: Notebook | M84: 2 | N84: 60 | O84: 15 | P84: 102 | Q84: 1 | R84: UPI | S84: Neha | T84: rohit.singh@company.com | U84: 9473931904 | V84: Completed | W84: =C84 -> P301 | X84: {=_xlfn.XLOOKUP(C84,C:C, _xlfn.HSTACK(L:L,K:K,S:S,Product_master!E:E,Product_master!F:F ))} -> #NAME? | Y84: #NAME? | Z84: #NAME? | AA84: #NAME? | AB84: #NAME?
A85: ORD10084 | B85: C003 | C85: P103 | D85: 18/03/2025 | E85: 21/03/2025 | F85: Rohit Singh | G85: Male | H85: 19/07/1983 | I85: Hyderabad | J85: South | K85: Electronics | L85: Keyboard | M85: 18 | N85: 1200 | O85: 15 | P85: 18360 | Q85: 3 | R85: Card | S85: Neha | T85: rohit.singh@company.com | U85: 9287159610 | V85: Pending | W85: =C85 -> P103 | X85: {=_xlfn.XLOOKUP(C85,C:C, _xlfn.HSTACK(L:L,K:K,S:S,Product_master!E:E,Product_master!F:F ))} -> #NAME? | Y85: #NAME? | Z85: #NAME? | AA85: #NAME? | AB85: #NAME?
A86: ORD10085 | B86: C008 | C86: P104 | D86: 30/10/2025 | E86: 31/10/2025 | F86: Kavya Nair | G86: Female | H86: 24/03/1993 | I86: Mumbai | J86: West | K86: Electronics | L86: Monitor | M86: 18 | N86: 12000 | O86: 15 | P86: 183600 | Q86: 2 | R86: Cash | S86: Rahul | T86: kavya.nair@company.com | U86: 9876513858 | V86: Completed | W86: =C86 -> P104 | X86: {=_xlfn.XLOOKUP(C86,C:C, _xlfn.HSTACK(L:L,K:K,S:S,Product_master!E:E,Product_master!F:F ))} -> #NAME? | Y86: #NAME? | Z86: #NAME? | AA86: #NAME? | AB86: #NAME?
A87: ORD10086 | B87: C007 | C87: P302 | D87: 31/10/2025 | E87: 11/11/2025 | F87: Arjun Rao | G87: Male | H87: 10/05/1995 | I87: Ahmedabad | J87: West | K87: Stationery | L87: Pen | M87: 7 | N87: 20 | O87: 0 | P87: 140 | Q87: 2 | R87: Card | S87: Ritika | T87: arjun.rao@company.com | U87: 9237400853 | V87: Cancelled | W87: =C87 -> P302 | X87: {=_xlfn.XLOOKUP(C87,C:C, _xlfn.HSTACK(L:L,K:K,S:S,Product_master!E:E,Product_master!F:F ))} -> #NAME? | Y87: #NAME? | Z87: #NAME? | AA87: #NAME? | AB87: #NAME?
... A119: ORD10118 | B119: C001 | C119: P303 | D119: 31/05/2025 | E119: 11/06/2025 | F119: Amit Sharma | G119: Male | H119: 07/09/1995 | I119: Pune | J119: West | K119: Stationery | L119: Marker | M119: 16 | N119: 45 | O119: 0 | P119: 720 | Q119: 1 | R119: NetBanking | S119: Aisha | T119: amit.sharma@company.com | U119: 9807154421 | V119: Completed | W119: =C119 -> P303 | X119: {=_xlfn.XLOOKUP(C119,C:C, _xlfn.HSTACK(L:L,K:K,S:S,Product_master!E:E,Product_master!F:F ))} -> #NAME? | Y119: #NAME? | Z119: #NAME? | AA119: #NAME? | AB119: #NAME?
A120: ORD10119 | B120: C009 | C120: P103 | D120: 30/05/2025 | E120: 02/06/2025 | F120: Mohit Verma | G120: Male | H120: 08/03/1988 | I120: Ahmedabad | J120: West | K120: Electronics | L120: Keyboard | M120: Ten | N120: 1200 | O120: 15 | P120: 7140 | Q120: 4 | R120: UPI | S120: Karan | T120: mohit.verma@company.com | U120: 9919834000 | V120: Pending | W120: =C120 -> P103 | X120: {=_xlfn.XLOOKUP(C120,C:C, _xlfn.HSTACK(L:L,K:K,S:S,Product_master!E:E,Product_master!F:F ))} -> #NAME? | Y120: #NAME? | Z120: #NAME? | AA120: #NAME? | AB120: #NAME?
A121: ORD10120 | B121: C002 | C121: P104 | D121: 19/08/2025 | E121: 30/08/2025 | F121: Priya Patel | G121: Female | H121: 07/07/1989 | I121: Jaipur | J121: North | K121: Electronics | L121: Monitor | M121: 14 | N121: 12000 | O121: 15 | P121: 142800 | Q121: 2 | R121: NetBanking | S121: Aisha | T121: priya.patel@company.com | U121: 9739798818 | V121: Pending | W121: =C121 -> P104 | X121: {=_xlfn.XLOOKUP(C121,C:C, _xlfn.HSTACK(L:L,K:K,S:S,Product_master!E:E,Product_master!F:F ))} -> #NAME? | Y121: #NAME? | Z121: #NAME? | AA121: #NAME? | AB121: #NAME?
A122: ORD10121 | B122: C003 | C122: P203 | D122: 14/12/2025 | E122: 16/12/2025 | F122: Rohit Singh | G122: Male | H122: 11/11/1993 | I122: Pune | J122: West | K122: Home Appliances | L122: Microwave | M122: 8 | N122: 8500 | O122: 20 | P122: 54400 | Q122: 3 | R122: Card | S122: Rahul | T122: rohit.singh@company.com | U122: 9208625306 | V122: Completed | W122: =C122 -> P203 | X122: {=_xlfn.XLOOKUP(C122,C:C, _xlfn.HSTACK(L:L,K:K,S:S,Product_master!E:E,Product_master!F:F ))} -> #NAME? | Y122: #NAME? | Z122: #NAME? | AA122: #NAME? | AB122: #NAME?
A123: ORD10122 | B123: C007 | C123: P303 | D123: 31/01/2026 | E123: 10/02/2026 | F123: Arjun Rao | G123: Male | H123: 01/02/2000 | I123: Bengaluru | J123: South | K123: Stationery | L123: Marker | M123: 3 | N123: 45 | O123: 0 | P123: 135 | Q123: 4 | R123: UPI | S123: Aisha | T123: arjun.rao@company.com | U123: 9970178536 | V123: Cancelled | W123: =C123 -> P303 | X123: {=_xlfn.XLOOKUP(C123,C:C, _xlfn.HSTACK(L:L,K:K,S:S,Product_master!E:E,Product_master!F:F ))} -> #NAME? | Y123: #NAME? | Z123: #NAME? | AA123: #NAME? | AB123: #NAME?
A124: ORD10123 | B124: C001 | C124: P102 | D124: 03/01/2026 | E124: 04/01/2026 | F124: Amit Sharma | G124: Male | H124: 22/06/1986 | I124: Jaipur | J124: North | K124: Electronics | L124: Mouse | M124: 13 | N124: 700 | O124: 5 | P124: 8645 | Q124: 3 | R124: Card | S124: Neha | T124: amit.sharma@company.com | U124: 9633745195 | V124: Pending | W124: =C124 -> P102 | X124: {=_xlfn.XLOOKUP(C124,C:C, _xlfn.HSTACK(L:L,K:K,S:S,Product_master!E:E,Product_master!F:F ))} -> #NAME? | Y124: #NAME? | Z124: #NAME? | AA124: #NAME? | AB124: #NAME?
A125: ORD10124 | B125: C004 | C125: P103 | D125: 20/10/2025 | E125: 26/10/2025 | F125: Anita Gupta | G125: Female | H125: 16/02/1986 | I125: Mumbai | J125: West | K125: Electronics | L125: Keyboard | M125: 14 | N125: 1200 | O125: 20 | P125: 13440 | Q125: 5 | R125: NetBanking | S125: Aisha | T125: anita.gupta@company.com | U125: 9922102053 | V125: Completed | W125: =C125 -> P103 | X125: {=_xlfn.XLOOKUP(C125,C:C, _xlfn.HSTACK(L:L,K:K,S:S,Product_master!E:E,Product_master!F:F ))} -> #NAME? | Y125: #NAME? | Z125: #NAME? | AA125: #NAME? | AB125: #NAME?
A126: ORD10125 | B126: C002 | C126: P303 | D126: 11/05/2025 | E126: 21/05/2025 | F126: Priya Patel | G126: Female | H126: 18/09/1991 | I126: Delhi | J126: North | K126: Stationery | L126: Marker | M126: 2 | N126: 45 | O126: 5 | P126: 85.5 | Q126: 3 | R126: UPI | S126: Ritika | T126: priya.patel@company.com | U126: 9135963930 | V126: Cancelled | W126: =C126 -> P303 | X126: {=_xlfn.XLOOKUP(C126,C:C, _xlfn.HSTACK(L:L,K:K,S:S,Product_master!E:E,Product_master!F:F ))} -> #NAME? | Y126: #NAME? | Z126: #NAME? | AA126: #NAME? | AB126: #NAME?
A127: ORD10126 | B127: C004 | C127: P103 | D127: 02/01/2026 | E127: 06/01/2026 | F127: Anita Gupta | G127: Female | H127: 04/01/1981 | I127: Bengaluru | J127: South | K127: Electronics | L127: Keyboard | M127: 2 | N127: 1200 | O127: 20 | P127: 1920 | Q127: 3 | R127: Card | S127: Neha | T127: anita.gupta@company.com | U127: 9429405275 | V127: Completed | W127: =C127 -> P103 | X127: {=_xlfn.XLOOKUP(C127,C:C, _xlfn.HSTACK(L:L,K:K,S:S,Product_master!E:E,Product_master!F:F ))} -> #NAME? | Y127: #NAME? | Z127: #NAME? | AA127: #NAME? | AB127: #NAME?
A128: ORD10127 | B128: C003 | C128: P101 | D128: 20/04/2026 | E128: 26/04/2026 | F128: Rohit Singh | G128: Male | H128: 12/10/2004 | I128: Bengaluru | J128: South | K128: Electronics | L128: Laptop | M128: 10 | N128: 55000 | O128: 5 | P128: 522500 | Q128: 5 | R128: UPI | S128: Aisha | T128: rohit.singh@company.com | U128: 9521757571 | V128: Pending | W128: =C128 -> P101 | X128: {=_xlfn.XLOOKUP(C128,C:C, _xlfn.HSTACK(L:L,K:K,S:S,Product_master!E:E,Product_master!F:F ))} -> #NAME? | Y128: #NAME? | Z128: #NAME? | AA128: #NAME? | AB128: #NAME?
A129: ORD10128 | B129: C006 | C129: P201 | D129: 04/08/2025 | E129: 05/08/2025 | F129: Sneha Joshi | G129: Female | H129: 25/03/1984 | I129: Jaipur | J129: North | K129: Home Appliances | L129: Mixer | M129: 15 | N129: 3500 | O129: 10 | P129: 47250 | Q129: 3 | R129: NetBanking | S129: Neha | T129: sneha.joshi@company.com | U129: 9467375455 | V129: Completed | W129: =C129 -> P201 | X129: {=_xlfn.XLOOKUP(C129,C:C, _xlfn.HSTACK(L:L,K:K,S:S,Product_master!E:E,Product_master!F:F ))} -> #NAME? | Y129: #NAME? | Z129: #NAME? | AA129: #NAME? | AB129: #NAME?
A130: ORD10129 | B130: C002 | C130: P202 | D130: 13/08/2025 | E130: 18/08/2025 | F130: Priya Patel | G130: Female | H130: 09/09/1982 | I130: Bengaluru | J130: South | K130: Home Appliances | L130: Iron | M130: 10 | N130: 2200 | O130: 15 | P130: 18700 | Q130: 4 | R130: Card | S130: Rahul | T130: priya.patel@company.com | U130: 9838809695 | V130: Pending | W130: =C130 -> P202 | X130: {=_xlfn.XLOOKUP(C130,C:C, _xlfn.HSTACK(L:L,K:K,S:S,Product_master!E:E,Product_master!F:F ))} -> #NAME? | Y130: #NAME? | Z130: #NAME? | AA130: #NAME? | AB130: #NAME?
A131: ORD10130 | B131: C006 | C131: P201 | D131: 16/06/2025 | E131: 24/06/2025 | F131: Sneha Joshi | G131: Female | H131: 15/02/1993 | I131: Pune | J131: West | K131: Home Appliances | L131: Mixer | M131: 11 | N131: 3500 | O131: 5 | P131: 36575 | Q131: 5 | R131: Cash | S131: Ritika | T131: sneha.joshi@company.com | U131: 9296609782 | V131: Cancelled | W131: =C131 -> P201 | X131: {=_xlfn.XLOOKUP(C131,C:C, _xlfn.HSTACK(L:L,K:K,S:S,Product_master!E:E,Product_master!F:F ))} -> #NAME? | Y131: #NAME? | Z131: #NAME? | AA131: #NAME? | AB131: #NAME?
A132: ORD10131 | B132: C004 | C132: P103 | D132: 27/04/2026 | E132: 30/04/2026 | F132: Anita Gupta | G132: Female | H132: 08/04/2003 | I132: Bengaluru | J132: South | K132: Electronics | L132: Keyboard | M132: 14 | N132: 1200 | O132: 0 | P132: 16800 | Q132: 5 | R132: Cash | S132: Rahul | T132: anita.gupta@company.com | U132: 9848259992 | V132: Cancelled | W132: =C132 -> P103 | X132: {=_xlfn.XLOOKUP(C132,C:C, _xlfn.HSTACK(L:L,K:K,S:S,Product_master!E:E,Product_master!F:F ))} -> #NAME? | Y132: #NAME? | Z132: #NAME? | AA132: #NAME? | AB132: #NAME?
... A299: ORD10298 | B299: C003 | C299: P101 | D299: 13/01/2025 | E299: 16/01/2025 | F299: Rohit Singh | G299: Male | H299: 03/01/2004 | I299: Hyderabad | J299: South | K299: Electronics | L299: Laptop | M299: 11 | N299: 55000 | O299: 5 | P299: 574750 | Q299: 1 | R299: UPI | S299: Ritika | T299: rohit.singh@company.com | U299: 9482699727 | V299: Cancelled | W299: =C299 -> P101 | X299: {=_xlfn.XLOOKUP(C299,C:C, _xlfn.HSTACK(L:L,K:K,S:S,Product_master!E:E,Product_master!F:F ))} -> #NAME? | Y299: #NAME? | Z299: #NAME? | AA299: #NAME? | AB299: #NAME?
A300: ORD10299 | B300: C007 | C300: P201 | D300: 05/10/2025 | E300: 17/10/2025 | F300: Arjun Rao | G300: Male | H300: 02/05/1992 | I300: Jaipur | J300: North | K300: Home Appliances | L300: Mixer | M300: 12 | N300: 3500 | O300: 0 | P300: 42000 | Q300: 2 | R300: NetBanking | T300: arjun.rao@company.com | U300: 9332473934 | V300: Pending | W300: =C300 -> P201 | X300: {=_xlfn.XLOOKUP(C300,C:C, _xlfn.HSTACK(L:L,K:K,S:S,Product_master!E:E,Product_master!F:F ))} -> #NAME? | Y300: #NAME? | Z300: #NAME? | AA300: #NAME? | AB300: #NAME?
A301: ORD10300 | B301: C009 | C301: P303 | D301: 25/02/2026 | E301: 08/03/2026 | F301: Mohit Verma | G301: Male | H301: 26/01/2003 | I301: Hyderabad | J301: South | K301: Stationery | L301: Marker | M301: 15 | N301: 45 | O301: 10 | P301: 607.5 | Q301: 2 | R301: Cash | S301: Karan | T301: mohit.verma@company.com | U301: 9647657382 | V301: Pending | W301: =C301 -> P303 | X301: {=_xlfn.XLOOKUP(C301,C:C, _xlfn.HSTACK(L:L,K:K,S:S,Product_master!E:E,Product_master!F:F ))} -> #NAME? | Y301: #NAME? | Z301: #NAME? | AA301: #NAME? | AB301: #NAME?
A302: ORD10301 | B302: C001 | C302: P303 | D302: 16/05/2025 | E302: 26/05/2025 | F302: Amit Sharma | G302: Male | H302: 20/05/1987 | I302: Bengaluru | J302: South | K302: Stationery | L302: Marker | M302: 13 | N302: 45 | O302: 0 | P302: 585 | Q302: 5 | R302: NetBanking | S302: Rahul | T302: amit.sharma@company.com | U302: 9736797776 | V302: Pending | W302: =C302 -> P303 | X302: {=_xlfn.XLOOKUP(C302,C:C, _xlfn.HSTACK(L:L,K:K,S:S,Product_master!E:E,Product_master!F:F ))} -> #NAME? | Y302: #NAME? | Z302: #NAME? | AA302: #NAME? | AB302: #NAME?
A303: ORD10302 | B303: C003 | C303: P101 | D303: 02/01/2026 | E303: 05/01/2026 | F303: Rohit Singh | G303: Male | H303: 07/09/1975 | I303: Bengaluru | J303: South | K303: Electronics | L303: Laptop | M303: 8 | N303: 55000 | O303: 0 | P303: 440000 | Q303: 2 | R303: UPI | S303: Karan | T303: rohit.singh@company.com | U303: 9745773533 | V303: Cancelled | W303: =C303 -> P101 | X303: {=_xlfn.XLOOKUP(C303,C:C, _xlfn.HSTACK(L:L,K:K,S:S,Product_master!E:E,Product_master!F:F ))} -> #NAME? | Y303: #NAME? | Z303: #NAME? | AA303: #NAME? | AB303: #NAME?
A304: ORD10303 | B304: C006 | C304: P101 | D304: 23/07/2025 | E304: 27/07/2025 | F304: Sneha Joshi | G304: Female | H304: 10/08/1980 | I304: Delhi | J304: North | K304: Electronics | L304: Laptop | M304: 4 | N304: 55000 | O304: 20 | P304: 176000 | Q304: 5 | R304: Cash | S304: Rahul | T304: sneha.joshi@company.com | U304: 9246715757 | V304: Pending | W304: =C304 -> P101 | X304: {=_xlfn.XLOOKUP(C304,C:C, _xlfn.HSTACK(L:L,K:K,S:S,Product_master!E:E,Product_master!F:F ))} -> #NAME? | Y304: #NAME? | Z304: #NAME? | AA304: #NAME? | AB304: #NAME?
A305: ORD10304 | B305: C008 | C305: P201 | D305: 23/04/2026 | E305: 26/04/2026 | F305: Kavya Nair | G305: Female | H305: 07/04/1989 | I305: Ahmedabad | J305: West | K305: Home Appliances | L305: Mixer | M305: 19 | N305: 3500 | O305: 5 | P305: 63175 | Q305: 1 | R305: Card | S305: Neha | T305: kavya.nair@company.com | U305: 9904065774 | V305: Completed | W305: =C305 -> P201 | X305: {=_xlfn.XLOOKUP(C305,C:C, _xlfn.HSTACK(L:L,K:K,S:S,Product_master!E:E,Product_master!F:F ))} -> #NAME? | Y305: #NAME? | Z305: #NAME? | AA305: #NAME? | AB305: #NAME?
A306: ORD10305 | B306: C005 | C306: P103 | D306: 02/03/2025 | E306: 06/03/2025 | F306: Vikas Mehta | G306: Male | H306: 20/08/1998 | I306: Jaipur | J306: North | K306: Electronics | L306: Keyboard | M306: 17 | N306: 1200 | O306: 15 | P306: 17340 | Q306: 2 | R306: NetBanking | S306: Rahul | T306: vikas.mehta@company.com | U306: 9652985385 | V306: Completed | W306: =C306 -> P103 | X306: {=_xlfn.XLOOKUP(C306,C:C, _xlfn.HSTACK(L:L,K:K,S:S,Product_master!E:E,Product_master!F:F ))} -> #NAME? | Y306: #NAME? | Z306: #NAME? | AA306: #NAME? | AB306: #NAME?
A307: ORD10306 | B307: C008 | C307: P202 | D307: 09/02/2026 | E307: 17/02/2026 | F307: Kavya Nair | G307: Female | H307: 03/04/2001 | I307: Hyderabad | J307: South | K307: Home Appliances | L307: Iron | M307: 8 | N307: 2200 | O307: 5 | P307: 16720 | Q307: 3 | R307: Card | S307: Neha | T307: kavya.nair@company.com | U307: 9427001508 | V307: Pending | W307: =C307 -> P202 | X307: {=_xlfn.XLOOKUP(C307,C:C, _xlfn.HSTACK(L:L,K:K,S:S,Product_master!E:E,Product_master!F:F ))} -> #NAME? | Y307: #NAME? | Z307: #NAME? | AA307: #NAME? | AB307: #NAME?
A308: ORD10307 | B308: C006 | C308: P102 | D308: 16/02/2025 | E308: 26/02/2025 | F308: Sneha Joshi | G308: Female | H308: 05/03/1992 | I308: Mumbai | J308: West | K308: Electronics | L308: Mouse | M308: 17 | N308: 700 | O308: 20 | P308: 9520 | Q308: 4 | R308: NetBanking | S308: Neha | T308: sneha.joshi@company.com | U308: 9666803655 | V308: Completed | W308: =C308 -> P102 | X308: {=_xlfn.XLOOKUP(C308,C:C, _xlfn.HSTACK(L:L,K:K,S:S,Product_master!E:E,Product_master!F:F ))} -> #NAME? | Y308: #NAME? | Z308: #NAME? | AA308: #NAME? | AB308: #NAME?
A309: ORD10308 | B309: C006 | C309: P203 | D309: 28/08/2025 | E309: 08/09/2025 | F309: Sneha Joshi | G309: Female | H309: 28/12/1976 | I309: Pune | J309: West | K309: Home Appliances | L309: Microwave | M309: 6 | N309: 8500 | O309: 15 | P309: 43350 | Q309: 1 | R309: Cash | S309: Aisha | T309: sneha.joshi@company.com | U309: 9134878547 | V309: Completed | W309: =C309 -> P203 | X309: {=_xlfn.XLOOKUP(C309,C:C, _xlfn.HSTACK(L:L,K:K,S:S,Product_master!E:E,Product_master!F:F ))} -> #NAME? | Y309: #NAME? | Z309: #NAME? | AA309: #NAME? | AB309: #NAME?
A310: ORD10309 | B310: C010 | C310: P201 | D310: 06/10/2025 | E310: 11/10/2025 | F310: Pooja Shah | G310: Female | H310: 04/09/1986 | I310: Hyderabad | J310: South | K310: Home Appliances | L310: Mixer | M310: 3 | N310: 3500 | O310: 10 | P310: 9450 | Q310: 1 | R310: NetBanking | S310: Rahul | T310: pooja.shah@company.com | U310: 9253593557 | V310: Completed | W310: =C310 -> P201 | X310: {=_xlfn.XLOOKUP(C310,C:C, _xlfn.HSTACK(L:L,K:K,S:S,Product_master!E:E,Product_master!F:F ))} -> #NAME? | Y310: #NAME? | Z310: #NAME? | AA310: #NAME? | AB310: #NAME?
A311: ORD10310 | B311: C009 | C311: P104 | D311: 17/01/2025 | E311: 29/01/2025 | F311: Mohit Verma | G311: Male | H311: 14/08/1989 | I311: Ahmedabad | J311: West | K311: Electronics | L311: Monitor | M311: 2 | N311: 12000 | O311: 20 | P311: 19200 | Q311: 1 | R311: Card | S311: Aisha | T311: mohit.verma@company.com | U311: 9183094051 | V311: Completed | W311: =C311 -> P104 | X311: {=_xlfn.XLOOKUP(C311,C:C, _xlfn.HSTACK(L:L,K:K,S:S,Product_master!E:E,Product_master!F:F ))} -> #NAME? | Y311: #NAME? | Z311: #NAME? | AA311: #NAME? | AB311: #NAME?
A312: ORD10311 | B312: C005 | C312: P302 | D312: 13/10/2025 | E312: 16/10/2025 | F312: Vikas Mehta | G312: Male | H312: 02/03/1991 | I312: Delhi | J312: North | K312: Stationery | L312: Pen | M312: 12 | N312: 20 | O312: 20 | P312: 192 | Q312: 2 | R312: Card | S312: Rahul | T312: vikas.mehta@company.com | U312: 9293147620 | V312: Completed | W312: =C312 -> P302 | X312: {=_xlfn.XLOOKUP(C312,C:C, _xlfn.HSTACK(L:L,K:K,S:S,Product_master!E:E,Product_master!F:F ))} -> #NAME? | Y312: #NAME? | Z312: #NAME? | AA312: #NAME? | AB312: #NAME?
... A370: ORD10369 | B370: C010 | C370: P301 | D370: 01/04/2026 | E370: 05/04/2026 | F370: Pooja Shah | G370: Female | H370: 04/01/1987 | I370: Hyderabad | J370: South | K370: Stationery | L370: Notebook | M370: 19 | N370: 60 | O370: 15 | P370: 969 | Q370: 4 | R370: NetBanking | S370: Neha | T370: pooja.shah@company.com | U370: 9435947486 | V370: Cancelled | W370: =C370 -> P301 | X370: {=_xlfn.XLOOKUP(C370,C:C, _xlfn.HSTACK(L:L,K:K,S:S,Product_master!E:E,Product_master!F:F ))} -> #NAME? | Y370: #NAME? | Z370: #NAME? | AA370: #NAME? | AB370: #NAME?
A371: ORD10370 | B371: C001 | C371: P101 | E371: 02/02/2025 | F371: Amit Sharma | G371: Male | H371: 14/05/1992 | I371: Delhi | J371: North | K371: Electronics | L371: Laptop | M371: 15 | N371: 55000 | O371: 0 | P371: 825000 | Q371: 5 | R371: Card | S371: Neha | T371: amit.sharma@company.com | U371: 9411668831 | V371: Cancelled | W371: =C371 -> P101 | X371: {=_xlfn.XLOOKUP(C371,C:C, _xlfn.HSTACK(L:L,K:K,S:S,Product_master!E:E,Product_master!F:F ))} -> #NAME? | Y371: #NAME? | Z371: #NAME? | AA371: #NAME? | AB371: #NAME?
A372: ORD10371 | B372: C009 | C372: P303 | D372: 06/10/2025 | E372: 08/10/2025 | F372: Mohit Verma | G372: Male | H372: 03/05/1989 | I372: Bengaluru | J372: South | K372: Stationery | L372: Marker | M372: 11 | N372: 45 | O372: 5 | P372: 470.25 | Q372: 5 | R372: NetBanking | S372: Karan | T372: mohit.verma@company.com | U372: 9523682403 | V372: Completed | W372: =C372 -> P303 | X372: {=_xlfn.XLOOKUP(C372,C:C, _xlfn.HSTACK(L:L,K:K,S:S,Product_master!E:E,Product_master!F:F ))} -> #NAME? | Y372: #NAME? | Z372: #NAME? | AA372: #NAME? | AB372: #NAME?
A373: ORD10372 | B373: C006 | C373: P302 | D373: 12/06/2025 | E373: 17/06/2025 | F373: Sneha Joshi | G373: Female | H373: 19/12/1990 | I373: Jaipur | J373: North | K373: Stationery | L373: Pen | M373: 9 | N373: 20 | O373: 10 | P373: 162 | Q373: 1 | R373: Card | S373: Rahul | T373: sneha.joshi@company.com | U373: 9652936744 | V373: Cancelled | W373: =C373 -> P302 | X373: {=_xlfn.XLOOKUP(C373,C:C, _xlfn.HSTACK(L:L,K:K,S:S,Product_master!E:E,Product_master!F:F ))} -> #NAME? | Y373: #NAME? | Z373: #NAME? | AA373: #NAME? | AB373: #NAME?
A374: ORD10373 | B374: C004 | C374: P303 | D374: 18/11/2025 | E374: 20/11/2025 | F374: Anita Gupta | G374: Female | H374: 09/07/1995 | I374: Bengaluru | J374: South | K374: Stationery | L374: Marker | M374: 5 | N374: 45 | O374: 5 | P374: 213.75 | Q374: 3 | R374: Card | S374: Neha | T374: anita.gupta@company.com | U374: 9726464733 | V374: Pending | W374: =C374 -> P303 | X374: {=_xlfn.XLOOKUP(C374,C:C, _xlfn.HSTACK(L:L,K:K,S:S,Product_master!E:E,Product_master!F:F ))} -> #NAME? | Y374: #NAME? | Z374: #NAME? | AA374: #NAME? | AB374: #NAME?
A375: ORD10374 | B375: C007 | C375: P102 | D375: 01/11/2025 | E375: 02/11/2025 | F375: Arjun Rao | G375: Male | H375: 23/12/1998 | I375: Hyderabad | J375: South | K375: Electronics | L375: Mouse | M375: 5 | N375: 700 | O375: 10 | P375: 3150 | Q375: 2 | R375: UPI | S375: Rahul | T375: arjun.rao@company.com | U375: 9273520544 | V375: Completed | W375: =C375 -> P102 | X375: {=_xlfn.XLOOKUP(C375,C:C, _xlfn.HSTACK(L:L,K:K,S:S,Product_master!E:E,Product_master!F:F ))} -> #NAME? | Y375: #NAME? | Z375: #NAME? | AA375: #NAME? | AB375: #NAME?
A376: ORD10375 | B376: C005 | C376: P102 | D376: 24/01/2025 | E376: 31/01/2025 | F376: Vikas Mehta | G376: Male | H376: 23/12/1979 | I376: Kolkata | J376: East | K376: Electronics | L376: Mouse | M376: 1 | N376: 700 | O376: 0 | P376: 700 | Q376: 1 | R376: UPI | S376: Karan | T376: vikas.mehta@company.com | U376: 9374259988 | V376: Completed | W376: =C376 -> P102 | X376: {=_xlfn.XLOOKUP(C376,C:C, _xlfn.HSTACK(L:L,K:K,S:S,Product_master!E:E,Product_master!F:F ))} -> #NAME? | Y376: #NAME? | Z376: #NAME? | AA376: #NAME? | AB376: #NAME?
A377: ORD10376 | B377: C008 | C377: P102 | D377: 13/02/2026 | E377: 21/02/2026 | F377: Kavya Nair | G377: Female | H377: 15/12/1975 | I377: Mumbai | J377: West | K377: Electronics | L377: Mouse | M377: 13 | N377: 700 | O377: 20 | P377: 7280 | Q377: 2 | R377: Card | S377: Ritika | T377: kavya.nair@company.com | U377: 9538129419 | V377: Completed | W377: =C377 -> P102 | X377: {=_xlfn.XLOOKUP(C377,C:C, _xlfn.HSTACK(L:L,K:K,S:S,Product_master!E:E,Product_master!F:F ))} -> #NAME? | Y377: #NAME? | Z377: #NAME? | AA377: #NAME? | AB377: #NAME?
A378: ORD10377 | B378: C009 | C378: P104 | D378: 08/02/2025 | E378: 19/02/2025 | F378: Mohit Verma | G378: Male | H378: 17/05/1993 | I378: Pune | J378: West | K378: Electronics | L378: Monitor | M378: 20 | N378: 12000 | O378: 0 | P378: 240000 | Q378: 2 | R378: Card | S378: Neha | T378: mohit.verma@company.com | U378: 9382815686 | V378: Completed | W378: =C378 -> P104 | X378: {=_xlfn.XLOOKUP(C378,C:C, _xlfn.HSTACK(L:L,K:K,S:S,Product_master!E:E,Product_master!F:F ))} -> #NAME? | Y378: #NAME? | Z378: #NAME? | AA378: #NAME? | AB378: #NAME?
A379: ORD10378 | B379: C007 | C379: P103 | D379: 28/12/2025 | E379: 06/01/2026 | F379: Arjun Rao | G379: Male | H379: 17/09/1976 | I379: Kolkata | J379: East | K379: Electronics | L379: Keyboard | M379: 9 | N379: 1200 | O379: 15 | P379: 9180 | Q379: 1 | R379: UPI | S379: Ritika | T379: arjun.rao@company.com | U379: 9450746157 | V379: Pending | W379: =C379 -> P103 | X379: {=_xlfn.XLOOKUP(C379,C:C, _xlfn.HSTACK(L:L,K:K,S:S,Product_master!E:E,Product_master!F:F ))} -> #NAME? | Y379: #NAME? | Z379: #NAME? | AA379: #NAME? | AB379: #NAME?
A380: ORD10379 | B380: C007 | C380: P302 | D380: 01/10/2025 | E380: 03/10/2025 | F380: Arjun Rao | G380: Male | H380: 22/12/1996 | I380: Jaipur | J380: North | K380: Stationery | L380: Pen | M380: 3 | N380: 20 | O380: 15 | P380: 51 | Q380: 3 | R380: Cash | S380: Neha | T380: arjun.rao@company.com | U380: 9349012570 | V380: Pending | W380: =C380 -> P302 | X380: {=_xlfn.XLOOKUP(C380,C:C, _xlfn.HSTACK(L:L,K:K,S:S,Product_master!E:E,Product_master!F:F ))} -> #NAME? | Y380: #NAME? | Z380: #NAME? | AA380: #NAME? | AB380: #NAME?
A381: ORD10380 | B381: C006 | C381: P101 | D381: 18/12/2025 | E381: 19/12/2025 | F381: Sneha Joshi | G381: Female | H381: 25/12/1995 | I381: Delhi | J381: North | K381: Electronics | L381: Laptop | M381: 8 | N381: 55000 | O381: 20 | P381: 352000 | Q381: 5 | R381: Card | S381: Karan | T381: sneha.joshi@company.com | U381: 9442163790 | V381: Pending | W381: =C381 -> P101 | X381: {=_xlfn.XLOOKUP(C381,C:C, _xlfn.HSTACK(L:L,K:K,S:S,Product_master!E:E,Product_master!F:F ))} -> #NAME? | Y381: #NAME? | Z381: #NAME? | AA381: #NAME? | AB381: #NAME?
A382: ORD10381 | B382: C006 | C382: P301 | D382: 29/09/2025 | E382: 07/10/2025 | F382: Sneha Joshi | G382: Female | H382: 23/06/1985 | I382: Delhi | J382: North | K382: Stationery | L382: Notebook | M382: 17 | N382: 60 | O382: 20 | P382: 816 | Q382: 1 | R382: UPI | S382: Ritika | T382: sneha.joshi@company.com | U382: 9953329223 | V382: Pending | W382: =C382 -> P301 | X382: {=_xlfn.XLOOKUP(C382,C:C, _xlfn.HSTACK(L:L,K:K,S:S,Product_master!E:E,Product_master!F:F ))} -> #NAME? | Y382: #NAME? | Z382: #NAME? | AA382: #NAME? | AB382: #NAME?
A383: ORD10382 | B383: C003 | C383: P302 | D383: 14/05/2025 | E383: 22/05/2025 | F383: Rohit Singh | G383: Male | H383: 10/02/1984 | I383: Bengaluru | J383: South | K383: Stationery | L383: Pen | M383: 4 | N383: 20 | O383: 15 | P383: 68 | Q383: 3 | R383: NetBanking | S383: Aisha | T383: rohit.singh@company.com | U383: 9202321359 | V383: Pending | W383: =C383 -> P302 | X383: {=_xlfn.XLOOKUP(C383,C:C, _xlfn.HSTACK(L:L,K:K,S:S,Product_master!E:E,Product_master!F:F ))} -> #NAME? | Y383: #NAME? | Z383: #NAME? | AA383: #NAME? | AB383: #NAME?
... A399: ORD10398 | B399: C007 | C399: P104 | D399: 31/01/2025 | E399: 04/02/2025 | F399: Arjun Rao | G399: Male | H399: 10/12/1978 | I399: Kolkata | J399: East | K399: Electronics | L399: Monitor | M399: 19 | N399: 12000 | O399: 0 | P399: 228000 | Q399: 4 | R399: UPI | S399: Aisha | T399: arjun.rao@company.com | U399: 9136906750 | V399: Pending | W399: =C399 -> P104 | X399: {=_xlfn.XLOOKUP(C399,C:C, _xlfn.HSTACK(L:L,K:K,S:S,Product_master!E:E,Product_master!F:F ))} -> #NAME? | Y399: #NAME? | Z399: #NAME? | AA399: #NAME? | AB399: #NAME?
A400: ORD10399 | B400: C001 | C400: P102 | E400: 03/11/2025 | F400: Amit Sharma | G400: Male | H400: 01/09/1979 | I400: Bengaluru | J400: South | K400: Electronics | L400: Mouse | M400: 12 | N400: 700 | O400: 15 | P400: 7140 | Q400: 3 | R400: Card | S400: Ritika | T400: amit.sharma@company.com | U400: 9485286324 | V400: Completed | W400: =C400 -> P102 | X400: {=_xlfn.XLOOKUP(C400,C:C, _xlfn.HSTACK(L:L,K:K,S:S,Product_master!E:E,Product_master!F:F ))} -> #NAME? | Y400: #NAME? | Z400: #NAME? | AA400: #NAME? | AB400: #NAME?
A401: ORD10400 | B401: C008 | C401: P103 | D401: 13/05/2025 | E401: 21/05/2025 | F401: Kavya Nair | G401: Female | H401: 08/04/2001 | I401: Delhi | J401: North | K401: Electronics | L401: Keyboard | M401: 16 | N401: 1200 | O401: 20 | P401: 15360 | Q401: 1 | R401: Cash | S401: Rahul | T401: kavya.nair@company.com | U401: 9414633966 | V401: Pending | W401: =C401 -> P103 | X401: {=_xlfn.XLOOKUP(C401,C:C, _xlfn.HSTACK(L:L,K:K,S:S,Product_master!E:E,Product_master!F:F ))} -> #NAME? | Y401: #NAME? | Z401: #NAME? | AA401: #NAME? | AB401: #NAME?
A402: ORD10401 | B402: C009 | C402: P203 | D402: 27/12/2025 | E402: 04/01/2026 | F402: Mohit Verma | G402: Male | H402: 01/01/1983 | I402: Hyderabad | J402: South | K402: Home Appliances | L402: Microwave | M402: 10 | N402: 8500 | O402: 5 | P402: 80750 | Q402: 5 | R402: NetBanking | S402: Ritika | T402: mohit.verma@company.com | U402: 9833735234 | V402: Completed | W402: =C402 -> P203 | X402: {=_xlfn.XLOOKUP(C402,C:C, _xlfn.HSTACK(L:L,K:K,S:S,Product_master!E:E,Product_master!F:F ))} -> #NAME? | Y402: #NAME? | Z402: #NAME? | AA402: #NAME? | AB402: #NAME?
A403: ORD10402 | B403: C008 | C403: P302 | D403: 11/02/2025 | E403: 21/02/2025 | F403: Kavya Nair | G403: Female | H403: 09/08/1989 | I403: Ahmedabad | J403: West | K403: Stationery | L403: Pen | M403: 18 | N403: 20 | O403: 20 | P403: 288 | Q403: 1 | R403: UPI | S403: Ritika | T403: kavya.nair@company.com | U403: 9523689108 | V403: Pending | W403: =C403 -> P302 | X403: {=_xlfn.XLOOKUP(C403,C:C, _xlfn.HSTACK(L:L,K:K,S:S,Product_master!E:E,Product_master!F:F ))} -> #NAME? | Y403: #NAME? | Z403: #NAME? | AA403: #NAME? | AB403: #NAME?
A404: ORD10403 | B404: C009 | C404: P203 | D404: 13/03/2026 | E404: 19/03/2026 | F404: Mohit Verma | G404: Male | H404: 22/10/1993 | I404: Mumbai | J404: West | K404: Home Appliances | L404: Microwave | M404: 9 | N404: 8500 | O404: 0 | P404: 76500 | Q404: 2 | R404: Card | S404: Ritika | T404: mohit.verma@company.com | U404: 9812909831 | V404: Pending | W404: =C404 -> P203 | X404: {=_xlfn.XLOOKUP(C404,C:C, _xlfn.HSTACK(L:L,K:K,S:S,Product_master!E:E,Product_master!F:F ))} -> #NAME? | Y404: #NAME? | Z404: #NAME? | AA404: #NAME? | AB404: #NAME?
...

Sheet Q5)Sales_summary_report
A1: Order_ID | B1: Customer_ID | C1: Product_ID | D1: Order_Date | E1: Delivery_Date | F1: Customer_Name | G1: Gender | H1: DOB | I1: City | J1: Region | K1: Category | L1: Product_Name | M1: Quantity | N1: Unit_Price | O1: Discount_% | P1: Sales | Q1: Rating | R1: Payment_Mode | S1: Salesperson | T1: Email | U1: Phone | V1: Order_Status
A2: ORD10001 | B2: C008 | C2: P202 | D2: 18/09/2025 | E2: 22/09/2025 | F2: Kavya Nair | G2: Female | H2: 01/08/1976 | I2: Hyderabad | J2: South | K2: Home Appliances | L2: Iron | M2: 4 | N2: 2200 | O2: 10 | P2: 7920 | Q2: 4 | R2: Cash | S2: Ritika | T2: KAvya.nair@company.com | U2: 9431429797 | V2: Completed
A3: ORD10002 | B3: C008 | C3: P104 | D3: 27/04/2025 | E3: 04/05/2025 | F3: Kavya Nair | G3: Female | H3: 16/10/2000 | I3: Delhi | J3: North | K3: Electronics | L3: Monitor | M3: 17 | N3: 12000 | O3: 10 | P3: 183600 | Q3: 1 | R3: NetBanking | S3: Rahul | T3: kavya.nair@company.com | U3: 9129865339 | V3: Completed
A4: ORD10003 | B4: C010 | C4: P101 | D4: 03/09/2025 | E4: 14/09/2025 | F4: pooja shah | G4: Female | H4: 16/09/1994 | I4: Bengaluru | J4: South | K4: Electronics | L4: Laptop | M4: 5 | N4: 55000 | O4: 5 | P4: 261250 | Q4: 3 | R4: NetBanking | S4: Aisha | T4: pooja.shah@company.com | U4: 9380975626 | V4: Pending | X4: Total Sales Amnt for completed electronics product= | Z4: =SUMIFS(P2:P501, K2:K501, "Electronics", V2:V501, "completed") -> 7222090
A5: ORD10002 | B5: C008 | C5: P202 | D5: 21/03/2026 | E5: 02/04/2026 | F5: Kavya Nair | G5: Female | H5: 07/03/2004 | I5: Bengaluru | J5: South | K5: Home Appliances | L5: Iron | M5: 5 | N5: 2200 | O5: 5 | P5: 10450 | Q5: 5 | R5: NetBanking | S5: Aisha | T5: kavya.nair@company.com | U5: 9600261125 | V5: Cancelled
A6: ORD10005 | B6: C009 | C6: P103 | D6: 27/09/2025 | E6: 07/10/2025 | F6: Mohit Verma | G6: Male | H6: 13/04/1976 | I6: Delhi | J6: North | K6: Electronics | L6: Keyboard | M6: 8 | N6: 1200 | O6: 5 | P6: 9120 | Q6: 2 | R6: Card | S6: Aisha | T6: mohit.verma@company.com | U6: 9724635978 | V6: Pending
A7: ORD10006 | B7: C007 | C7: P202 | D7: 04/01/2026 | E7: 12/01/2026 | F7: arjun Rao | G7: Male | H7: 07/02/1988 | I7: Hyderabad | J7: South | K7: Home Appliances | L7: Iron | M7: 4 | N7: 2200 | O7: 0 | P7: 8800 | Q7: 1 | R7: UPI | S7: Ritika | T7: arjun.rao@company.com | U7: 9780584905 | V7: Completed
A8: ORD10007 | B8: C008 | C8: P201 | D8: 31/02/2025 | E8: 25/02/2026 | F8: Kavya Nair | G8: Female | H8: 20/03/2003 | I8: Hyderabad | J8: South | K8: Home Appliances | L8: Mixer | M8: 2 | N8: 3500 | O8: 5 | P8: 6650 | Q8: 1 | R8: UPI | S8: Ritika | T8: kavya.nair@company.com | U8: 9958252176 | V8: Completed | X8: Total Sales Amnt Genrated by neha in north= | Z8: =SUMIFS(P2:P501, S2:S501, "Neha", J2:J501, "North") -> 1550369.2
A9: ORD10008 | B9: C002 | C9: P104 | D9: 13/04/2025 | E9: 19/04/2025 | F9: Priya Patel | G9: Female | H9: 07/03/1995 | I9: Mumbai | J9: West | K9: Electronics | L9: Monitor | M9: 14 | N9: 12000 | O9: 15 | P9: 142800 | Q9: 4 | R9: NetBanking | S9: Ritika | T9: priYa.patel@company.com | U9: 9705521654 | V9: Completed
A10: ORD10009 | B10: C008 | C10: P104 | D10: 31/01/2026 | E10: 02/02/2026 | F10: kavya Nair | G10: Female | H10: 06/04/1997 | I10: Pune | J10: West | K10: Electronics | L10: Monitor | M10: 4 | N10: 12000 | O10: 15 | P10: 40800 | Q10: 4 | R10: UPI | S10: Neha | T10: kavya.nair@company.com | U10: 9588041011 | V10: Completed
A11: ORD10010 | B11: C002 | C11: P301 | D11: 25/03/2025 | E11: 27/03/2025 | F11: Priya Patel | G11: Female | H11: 07/01/1990 | I11: Mumbai | J11: West | K11: Stationery | L11: Notebook | M11: 6 | N11: 60 | O11: 0 | P11: 360 | Q11: 4 | R11: Card | S11: Neha | T11: PRiya.patel@company.com | U11: 9340540608 | V11: Completed
A12: ORD10011 | B12: C003 | C12: P202 | D12: 19/09/2025 | E12: 23/09/2025 | F12: Rohit Singh | G12: Male | H12: 10/05/1982 | I12: Delhi | J12: North | K12: Home Appliances | L12: Iron | M12: -3 | N12: 2200 | O12: 0 | P12: 35200 | Q12: 2 | R12: Card | S12: Rahul | T12: rohit.singh@company.com | U12: 9521710321 | V12: Pending | X12: No.of Orders where disc>=15% payment mode is UPI= | Z12: =COUNTIFS(O2:O501, ">=15", R2:R501, "UPI") -> 45
A13: ORD10012 | B13: C008 | C13: P201 | D13: 08/03/2025 | E13: 15/03/2025 | F13: Kavya Nair | G13: Female | H13: 23/01/1982 | I13: Ahmedabad | J13: West | K13: Home Appliances | L13: Mixer | M13: 10 | N13: 3500 | O13: 5 | P13: 33250 | Q13: 5 | R13: Card | S13: Aisha | T13: kavya.nair@company.com | U13: 9123535241 | V13: Cancelled
A14: ORD10013 | B14: C002 | C14: P202 | D14: 10/01/2025 | E14: 15/01/2025 | F14: Priya Patel | G14: Female | H14: 06/07/1992 | I14: Pune | J14: West | K14: Home Appliances | L14: Iron | M14: 15 | N14: 2200 | O14: 10 | P14: 29700 | Q14: 1 | R14: UPI | S14: Neha | T14: priya.patel@company.com | U14: 9367316892 | V14: Pending
A15: ORD10014 | B15: C003 | C15: P202 | D15: 09/03/2025 | E15: 13/03/2025 | F15: rohit Singh | G15: Male | H15: 19/03/2002 | I15: Mumbai | J15: West | K15: Home Appliances | L15: Iron | M15: 17 | N15: 2200 | O15: 5 | P15: 35530 | Q15: 1 | R15: Cash | S15: Karan | T15: rOhit.singh@company.com | U15: 9778489803 | V15: Completed
A16: ORD10015 | B16: C008 | C16: P201 | D16: 26/07/2025 | E16: 07/08/2025 | F16: Kavya nair | G16: Female | H16: 17/01/2001 | I16: Mumbai | J16: West | K16: Home Appliances | L16: Mixer | M16: 15 | N16: 3500 | O16: 15 | P16: 44625 | Q16: 2 | R16: Cash | S16: Neha | T16: kavya.nair@company.com | U16: 9582960180 | V16: Cancelled | X16: Count of orders with rating of 5 and completed order= | Z16: =COUNTIFS(Q2:Q501, "5", V2:V501, "Completed") -> 27
A17: ORD10016 | B17: C010 | C17: P103 | D17: 08/04/2026 | E17: 11/04/2026 | F17: Pooja Shah | G17: Female | H17: 11/04/2002 | I17: Hyderabad | J17: South | K17: Electronics | L17: Keyboard | M17: 3 | N17: 1200 | O17: 5 | P17: 3420 | Q17: 5 | R17: UPI | S17: Ritika | T17: pooja.shahcompany.com | U17: 9611394005 | V17: Completed
A18: ORD10017 | B18: C004 | C18: P203 | D18: 22/02/2026 | E18: 03/03/2026 | F18: Amit Sharma | G18: Female | H18: 16/01/2002 | I18: Pune | J18: West | K18: Home Appliances | L18: Microwave | M18: 13 | N18: 8500 | O18: 20 | P18: 88400 | Q18: 4 | R18: Card | S18: Rahul | T18: anita.gupta@company.com | U18: 9692599404 | V18: Pending
A19: ORD10018 | B19: C007 | C19: P203 | D19: 28/02/2026 | E19: 05/03/2026 | F19: Arjun Rao | G19: Male | H19: 09/10/1989 | I19: Ahmedabad | J19: West | K19: Home Appliances | L19: Microwave | M19: 4 | N19: 8500 | O19: 20 | P19: 27200 | Q19: 5 | R19: Card | S19: Aisha | T19: arjun.rao@company.com | U19: 9426119622 | V19: Pending
A20: ORD10019 | B20: C007 | C20: P102 | D20: 01/12/2025 | E20: 04/12/2025 | F20: arjun rao | G20: Male | H20: 28/10/1991 | I20: Mumbai | J20: West | K20: Electronics | L20: Mouse | M20: 9 | N20: 700 | O20: 5 | P20: 5985 | Q20: 3 | R20: UPI | S20: Ritika | T20: arjun.Rao@company.com | U20: 9184436009 | V20: Pending | X20: Avg of sales in west region of quantity>5= | Z20: =AVERAGEIFS(P2:P501,J2:J501, "West", M2:M501, ">5") -> 82824.451
A21: ORD10020 | B21: C008 | C21: P101 | D21: 25/06/2025 | E21: 03/07/2025 | F21: Kavya Nair | G21: Female | H21: 01/03/1990 | I21: Ahmedabad | J21: West | K21: Electronics | L21: Laptop | M21: 8 | N21: 55000 | O21: 20 | P21: 352000 | Q21: 1 | R21: Cash | S21: Karan | T21: kavya.nair@company.com | U21: 9263774934 | V21: Completed
